Workbook

Sheet google_form
A1: Timestamp | B1: Email Address | C1: Data category | D1: Product name | E1: Reference | F1: Citation | G1: Citation DOI | H1: Image URL | I1: Data access link | J1: Spatial resolution | K1: Temporal resolution | L1: Period | M1: Spatial domain | N1: Sampling type | O1: Highlights | P1: Description | Q1: Citation DOI status | R1: Data access status
A2: 45961.925 | C2: Data compilations | D2: SOCAT | E2: Bakker, D. C. E., Pfeil, B., Landa, C. S., Metzl, N., O'Brien, K. M., Olsen, A., Smith, K., Cosca, C., Harasawa, S., Jones, S. D., Nakaoka, S., Nojiri, Y., Schuster, U., Steinhoff, T., Sweeney, C., Takahashi, T., Tilbrook, B., Wada, C., Wanninkhof, R., Alin, S. R., Balestrini, C. F., Barbero, L., Bates, N. R., Bianchi, A. A., Bonou, F., Boutin, J., Bozec, Y., Burger, E. F., Cai, W.-J., Castle, R. D., Chen, L., Chierici, M., Currie, K., Evans, W., Featherstone, C., Feely, R. A., Fransson, A., Goyet, C., Greenwood, N., Gregor, L., Hankin, S., Hardman-Mountford, N. J., Harlay, J., Hauck, J., Hoppema, M., Humphreys, M. P., Hunt, C. W., Huss, B., Ibánhez, J. S. P., Johannessen, T., Keeling, R., Kitidis, V., Körtzinger, A., Kozyr, A., Krasakopoulou, E., Kuwata, A., Landschützer, P., Lauvset, S. K., Lefèvre, N., Lo Monaco, C., Manke, A., Mathis, J. T., Merlivat, L., Millero, F. J., Monteiro, P. M. S., Munro, D. R., Murata, A., Newberger, T., Omar, A. M., Ono, T., Paterson, K., Pearce, D., Pierrot, D., Robbins, L. L., Saito, S., Salisbury, J., Schlitzer, R., Schneider, B., Schweitzer, R., Sieger, R., Skjelvan, I., Sullivan, K. F., Sutherland, S. C., Sutton, A. J., Tadokoro, K., Telszewski, M., Tuma, M., van Heuven, S. M. A. C., Vandemark, D., Ward, B., Watson, A. J., and Xu, S. (2016). A multi-decade record of high-quality fCO2 data in version 3 of the Surface Ocean CO2 Atlas (SOCAT), Earth Syst. Sci. Data, 8, 383–413, https://doi.org/10.5194/essd-8-383-2016. | F2: Bakker et al. (2016) | G2: https://doi.org/10.5194/essd-8-383-2016 | H2: https://socat.info/wp-content/uploads/2017/06/cropped-socat_cat.png | I2: https://socat.info/ | K2: continuous | L2: 1957 - 2025 | M2: Open ocean, Coastal ocean, Surface | N2: Continuous | O2: The largest collection of surface ocean carbon observations | P2: The Surface Ocean CO2 Atlas features surface fCO2 measurements from both the open ocean and the coastal ocean, predominantly sourced from research vessels, ships of opportunity, and autonomous platforms including fixed moorings and uncrewed surface vehicles (USVs) (Bakker et al., 2016). It represents the most extensive collection of observational ocean CO2 data for the global surface ocean. Since 2013, SOCAT has been updated annually. Dataset flags indicate the estimated uncertainty and completeness of metadata in SOCAT synthesis products. The SOCAT gridded product contains fCO2 values with an estimated uncertainty of less than 5 µatm. | Q2: =getStatusCode(G2) -> 200 | R2: =getStatusCode(I2) -> 200
A3: 45962.863 | C3: Data compilations | D3: LDEO Surface pCO2 Database | E3: Takahashi, T., Sutherland, S. C., Wanninkhof, R., Sweeney, C., Feely, R. A., Chipman, D. W., Hales, B., Friederich, G., Chavez, F., Sabine, C., Watson, A., Bakker, D. C. E., Schuster, U., Metzl, N., Yoshikawa-Inoue, H., Ishii, M., Midorikawa, T., Nojiri, Y., Körtzinger, A., Steinhoff, T., and de Baar, H. J. W.: Climatological mean and decadal change in Surface Ocean pCO2, and net sea–air CO2 flux over the Global Oceans, Deep Sea Research Part II: Topical Studies in Oceanography, 56(8–10), 554–577, https://doi.org/10.1016/j.dsr2.2008.12.009, 2009. | F3: Takahashi et a. (2009) | G3: https://doi.org/10.1016/j.dsr2.2008.12.009 | H3: https://www.ncei.noaa.gov/access/ocean-carbon-acidification-data-system/oceans/LDEO_Underway_Database/LDEOv2019_map.jpg | I3: https://www.ncei.noaa.gov/data/oceans/ncei/ocads/metadata/0160492.html | K3: continuous | M3: Open ocean, Surface | N3: Continuous | O3: The LDEO database reports pCO2 exclusively from equilibrator-CO2 analyzer systems | P3: Dr. Taro Takahashi [LDEO, Palisades, New York] started synthesizing global surface ocean CO2 data in 1997, compiling three decades of observations (~250,000 measurements) to create inaugural monthly global surface pCO2 maps (Takahashi et al., 1997; Takahashi et al., 2002). The most recent version (V2019) expanded this dataset to approximately 14.2 million surface water pCO2 measurements spanning from 1957–2019. Distinct from the SOCAT database, the LDEO database reports pCO2, instead of fCO2, exclusively from equilibrator-CO2 analyzer systems, with an average estimated uncertainty of ± 2.5 µatm. The database is also interpolated onto a global surface ocean 4° × 5° grid for a reference year 2000 (Takahashi et al., 2009) and 2010 (Fay et al., 2024). | Q3: =getStatusCode(G3) -> 403 | R3: =getStatusCode(I3) -> 200
A4: 45961.948 | C4: Data compilations | D4: GLODAPv2 | E4: Lauvset, S. K., Lange, N., Tanhua, T., Bittig, H. C., Olsen, A., Kozyr, A., Álvarez, M., Azetsu-Scott, K., Brown, P. J., Carter, B. R., Cotrim da Cunha, L., Hoppema, M., Humphreys, M. P., Ishii, M., Jeansson, E., Murata, A., Müller, J. D., Pérez, F. F., Schirnick, C., Steinfeldt, R., Suzuki, T., Ulfsbo, A., Velo, A., Woosley, R. J., and Key, R. M.: The annual update GLODAPv2.2023: the global interior ocean biogeochemical data product, Earth Syst. Sci. Data, 16, 2047–2072, https://doi.org/10.5194/essd-16-2047-2024, 2024 | F4: Lauvset et al. (2024) | G4: https://doi.org/10.5194/essd-16-2047-2024 | H4: https://glodap.info/wp-content/uploads/2017/09/cropped-glodap_logo_trans.png | I4: https://glodap.info/ | K4: discrete | L4: 1960 - 2024 | M4: Open ocean, Water column | N4: Discrete bottle | O4: Adjustments are applied by comparing data in the deep ocean (>2000 m) using a crossover and inversion method as described by Johnson et al. (2001). | P4: The Global Ocean Data Analysis Project Version 2 (GLODAPv2) aggregates biogeochemical data collected from discrete bottle samples, offering extensive global coverage from the surface to depths (Key et al., 2015; Olsen et al., 2016; Lauvset et al., 2024). While GLODAP is primarily a product for basin-scale hydrographic data, it also includes coastal datasets and observations from a few time-series. The GLODAPv2 data product provides rigorously quality-controlled measurements for 14 essential oceanographic variables: temperature, salinity, dissolved oxygen (DO), nitrate, silicate, phosphate, DIC, TA, pH, chlorofluorocarbons (CFC-11, CFC-12, CFC-113), carbon tetrachloride (CCl4), and sulfur hexafluoride (SF6). These variables, excluding temperature, undergo both primary and secondary quality control procedures to detect outliers and adjust for significant measurement biases. GLODAPv2 was first published in 2016 and was updated annually through a living data process in Earth System Science Data from 2019 through “v2023,” which was published in 2024. For these updates, new data (including historical data not previously included in the data product) are quality controlled and adjusted to the 2016 version (Olsen et al., 2019; Olsen et al., 2020; Lauvset et al., 2021; Lauvset et al., 2022; Lauvset et al., 2024). Since the global repeat hydrography programs operate with decadal repetitions, the aim is to produce a completely new version of GLODAP, where all cruise datasets will be reevaluated, every decade. Release of the GLODAPv3 data product is planned for 2026, and is expected to evolve the secondary data quality control practices relative to those used in GLODAPv2. For more information on the secondary quality control process, refer to Tanhua et al. (2010) and Lauvset and Tanhua (2015). GLODAPv2 offers two kind of products: the collection of quality controlled data from discrete bottle samples taken at sampling location (Key et al., 2015; Olsen et al., 2016; Olsen et al., 2019; Olsen et al., 2020; Lauvset et al., 2021; Lauvset et al., 2022; Lauvset et al., 2024), and a gridded product, interpolated to a 1° × 1° grid and the 33 standard depth levels of World Ocean Atlas (WOA) (Lauvset et al., 2016). | Q4: =getStatusCode(G4) -> 200 | R4: =getStatusCode(I4) -> 200
A5: 45973.973 | B5: jswift@ucsd.edu | C5: Data compilations | D5: Quality Edited Hydrographic Data | E5: Swift, James H. and Barna, A. (2026). Quality Edited Vertical Ocean Section and Gridded Hydrographic Data. UC San Diego Library Digital Collections. Dataset. https://doi.org/10.6075/J0K074P0 | F5: Swift et al. (2026) | G5: n/a | H5: https://i.ibb.co/Q7YZfHK2/Swift-Vertical-Section-Map.png | I5: https://joa.ucsd.edu/Data_homepage | K5: irregular | L5: 1967-2025 | M5: Open ocean, Water column | N5: Discrete bottle | O5: Similar to GLODAPv2, with no adjustments | P5: Similar to GLODAPv2, with no adjustments | Q5: =getStatusCode(G5) -> #ERROR! | R5: =getStatusCode(I5) -> 404
A6: 45962.719 | C6: Data compilations | D6: World Ocean Database | E6: Mishonov, A. V., Boyer, T. P., Baranova, O. K., Bouchard, C. N., Cross, S. L., Garcia H. E., Locarnini, R. A., Paver, C. R., Wang, Z., Seidov, D., Grodsky, A. I., Beauchamp, J. G.: World Ocean Database 2023, C. Bouchard, Technical Ed., NOAA Atlas NESDIS 97, 206 pp., https://doi.org/10.25923/z885-h264, 2024. | F6: Mishonov et al. (2024) | G6: https://doi.org/10.25923/z885-h264 | H6: https://www.ncei.noaa.gov/sites/g/files/anmtlf171/files/inline-images/World%20Ocean%20Atlas%202023%20Climatology%2C%20Decade%202015-2022.png | I6: https://www.ncei.noaa.gov/products/world-ocean-database | K6: discrete | M6: Open ocean, Water column | N6: Discrete bottle | O6: Similar to GLODAPv2, with no adjustments | P6: In addition to the GLODAPv2 and JOA Suite, users can also access historical and recent original biogeochemical data collected from discrete bottle samples in a uniform format and units, along with their originator quality control (QC) flags, through the World Ocean Database (WOD) (Mishonov et al., 2024). Like the JOA Suite, these measured data remain unaltered. The WOD allows users to filter and subset data with specific variables, platforms, institutions, projects, regions, or time periods (Garcia et al., 2024). Users can visualize sampling locations on a “distribution plot” and access a cruise list for all selected data and variables. Users also have the option of exporting data in NetCDF or Comma-Separated Values (CSV) formats. Additionally, all data in the WOD are reproducible and traceable to their original data sources archived at NOAA’s National Centers for Environmental Information (NCEI). | Q6: =getStatusCode(G6) -> 200 | R6: =getStatusCode(I6) -> 200
A7: 45964.649 | C7: Data compilations | D7: SNAPO-CO2 | E7: Metzl, N., Fin, J., Lo Monaco, C., Mignon, C., Alliouane, S., Antoine, D., Bourdin, G., Boutin, J., Bozec, Y., Conan, P., Coppola, L., Diaz, F., Douville, E., Durrieu de Madron, X., Gattuso, J.-P., Gazeau, F., Golbol, M., Lansard, B., Lefèvre, D., Lefèvre, N., Lombard, F., Louanchi, F., Merlivat, L., Olivier, L., Petrenko, A., Petton, S., Pujo-Pay, M., Rabouille, C., Reverdin, G., Ridame, C., Tribollet, A., Vellucci, V., Wagener, T., and Wimart-Rousseau, C.: A synthesis of ocean total alkalinity and dissolved inorganic carbon measurements from 1993 to 2022: the SNAPO-CO2-v1 dataset, Earth Syst. Sci. Data, 16, 89–120, https://doi.org/10.5194/essd-16-89-2024, 2024. | F7: Metzl et al (2024) | G7: https://doi.org/10.5194/essd-16-89-2024 | H7: https://www.seanoe.org/data/00911/102337/illustration.gif | I7: https://doi.org/10.17882/102337 | K7: discrete | L7: 1993-2022 | M7: Open ocean, Coastal ocean, Surface, Water column | N7: Discrete bottle | O7: A compilation of cruises from multiple French initiatives | P7: Synthesis of 44,400 measurements of DIC and TA from a series of research cruises and ships of opportunity across various oceanic regions from 1993-2022, from several French research programs, to create a product called “Service National d’Analyse des Paramètres Océaniques du CO2 (SNAPO-CO2)”. | Q7: =getStatusCode(G7) -> 200 | R7: =getStatusCode(I7) -> 200
A8: 45962.038 | B8: Liqing.Jiang@noaa.gov | C8: Data compilations | D8: CODAP-NA | E8: Jiang, L.-Q., Feely, R. A., Wanninkhof, R., Greeley, D., Barbero, L., Alin, S., Carter, B. R., Pierrot, D., Featherstone, C., Hooper, J., Melrose, C., Monacci, N., Sharp, J. D., Shellito, S., Xu, Y.-Y., Kozyr, A., Byrne, R. H., Cai, W.-J., Cross, J., Johnson, G. C., Hales, B., Langdon, C., Mathis, J., Salisbury, J., and Townsend, D. W.: Coastal Ocean Data Analysis Product in North America (CODAP-NA) – an internally consistent data product for discrete inorganic carbon, oxygen, and nutrients on the North American ocean margins, Earth Syst. Sci. Data, 13, 2777–2799, https://doi.org/10.5194/essd-13-2777-2021, 2021. | F8: Jiang et al. (2021) | G8: https://doi.org/10.5194/essd-13-2777-2021 | H8: https://essd.copernicus.org/articles/13/2777/2021/essd-13-2777-2021-f01-web.png | I8: https://www.ncei.noaa.gov/data/oceans/ncei/ocads/metadata/0219960.html | K8: discrete | L8: 2003 - 2018 | M8: Coastal ocean, Water column | N8: Discrete bottle | O8: A discrete bottle based data product similar to GLODAPv2, but for the North American coastal ocean | P8: Jiang et al. (2021) synthesized two decades of discrete measurements of carbonate system variables, DO, and nutrient data from the North American continental shelves to generate the first version of Coastal Ocean Data Analysis Data Product in North America (CODAP-NA). The 2021 release encompasses 3,391 oceanographic profiles from 61 research cruises spanning the North American continental shelves from Alaska to Mexico in the west and from Canada to the Caribbean in the east. It includes 14 key variables, including temperature, salinity, DO, DIC, TA, pH, carbonate ion, fCO2, silicate, phosphate, nitrate. | Q8: =getStatusCode(G8) -> 200 | R8: =getStatusCode(I8) -> 200
A9: 46031.742 | B9: liqing.jiang@noaa.gov | C9: Data compilations | D9: AZMP Carbon | E9: Gibb, O., Cyr, F., Azetsu-Scott, K., Chassé, J., Childs, D., Gabriel, C.-E., Galbraith, P. S., Maillet, G., Pepin, P., Punshon, S., and Starr, M.: Spatiotemporal variability in pH and carbonate parameters on the Canadian Atlantic continental shelf between 2014 and 2022, Earth Syst. Sci. Data, 15, 4127–4162, https://doi.org/10.5194/essd-15-4127-2023, 2023. | F9: Gibb et al. (2023) | G9: https://doi.org/10.5194/essd-15-4127-2023 | H9: https://essd.copernicus.org/articles/15/4127/2023/essd-15-4127-2023-avatar-web.png | I9: https://doi.org/10.20383/102.0673 | K9: irregular | M9: Coastal ocean, Water column | N9: Discrete bottle | O9: A compilation of cruises from the Atlantic Zone Monitoring Program (AZMP) since 2014 | P9: Gibb et al. (2023) compiled ocean carbonate system variables data from the Canadian Atlantic Zone Monitoring Program (AZMP Carbon) since 2014. More than 100 seagoing missions are represented in this dataset. The sampling strategy generally corresponds to full-depth water samples mostly collected along standardized hydrographic sections. Implemented in 1998, the AZMP aims to characterize and understand the causes of oceanic variability at the seasonal, interannual and decadal scales in support of, among other things, fisheries management in the Atlantic Zone (including the Gulf of St. Lawrence, the Scotian shelf and the Newfoundland and Labrador shelf). Since 2014, a minimum of two of the three following carbonate system variables, DIC, TA, and pH, are also acquired by the program at standardized hydrographic stations across the zone (sampled up to three times a year). Each measurement is completed with corresponding temperature, salinity and, when available, nutrients and DO concentration data. | Q9: =getStatusCode(G9) -> 200 | R9: =getStatusCode(I9) -> 200
A10: 46004.052 | B10: egkennedy@alaska.edu | C10: Data compilations | D10: MOCHA | E10: Kennedy, E. G., Zulian, M., Hamilton, S. L., Hill, T. M., Delgado, M., Fish, C. R., Gaylord, B., Kroeker, K. J., Palmer, H. M., Ricart, A. M., Sanford, E., Spalding, A. K., Ward, M., Carrasco, G., Elliott, M., Grisby, G. V., Harris, E., Jahncke, J., Rocheleau, C. N., Westering, S., and Wilmot, M. I.: A high-resolution synthesis dataset for multistressor analyses along the US West Coast, Earth Syst. Sci. Data, 16, 219-243, https://doi.org/10.5194/essd-16-219-2024, 2024. | F10: Kennedy et al., 2023 | G10: https://doi.org/10.25921/2vve-fh39 | H10: https://i.ibb.co/XrpxsXPX/data-locs-composite-bs.png | I10: https://www.ncei.noaa.gov/access/metadata/landing-page/bin/iso?id=gov.noaa.nodc:0277984 | K10: irregular, daily | L10: 1949-2022 | M10: Regional, Coastal ocean, Surface, Water column | N10: Continuous, Discrete bottle | O10: A compilation of cruises, autonomous sensors, and shore observations for the U.S. West Coast. | P10: MOCHA compiles temperature, salinity, DO, ocean carbonate system variables (DIC, TA, pH, pCO2 , fCO2 ), nutrients, and chlorophyll observations from the full water column along the U.S. west coast. This synthesis brings together 71 different sources, including high-resolution autonomous sensors, synoptic oceanographic cruises, and shoreline samples, into a single quality-controlled product that facilitates linking nearshore, high-resolution observations to broader oceanographic conditions. MOCHA spans from the shoreline to well-beyond the continental shelf and includes over 15 million observations. The MOCHA synthesis is also available as a "daily aggregated" dataset, with all data sources averaged by day, location, and depth. | Q10: =getStatusCode(G10) -> 200 | R10: =getStatusCode(I10) -> 200
A11: 45968.793 | B11: avelo@iim.csic.es | C11: Data compilations | D11: ARIOS | E11: Padin, X.A., Velo, A., Pérez, F.F., 2020. ARIOS: a database for ocean acidification assessment in the Iberian upwelling system (1976–2018). Earth Syst. Sci. Data 12, 2647–2663. https://doi.org/10.5194/essd-12-2647-2020 | F11: Padin et al. (2020) | G11: https://doi.org/10.5194/essd-12-2647-2020 | H11: https://essd.copernicus.org/articles/12/2647/2020/essd-12-2647-2020-f01-web.png | I11: https://doi.org/10.20350/digitalCSIC/12498 | K11: irregular, discrete | L11: 1976-2018 | M11: Coastal ocean, Surface, Water column, Regional | N11: Discrete bottle | O11: 17,653 samples from 3,343 stations measuring pH, alkalinity, and biogeochemical params off NW Iberian Peninsula (1976-2018). Data primarily from Ría de Vigo, spanning Bay of Biscay to Portuguese coast | P11: A data product of 17 653 discrete samples from 3343 oceanographic stations combining measurements of pH, alkalinity and other biogeochemical parameters off the northwestern Iberian Peninsula from June 1976 to September 2018 is presented in this study. The oceanography cruises funded by 24 projects were primarily carried out in the Ría de Vigo coastal inlet but also in an area ranging from the Bay of Biscay to the Portuguese coast. The robust seasonal cycles and long-term trends were only calculated along a longitudinal section, gathering data from the coastal and oceanic zone of the Iberian upwelling system. The pH in the surface waters of these separated regions, which were highly variable due to intense photosynthesis and the remineralization of organic matter, showed an interannual acidification ranging from −0.0012 to −0.0039 yr−1 that grew towards the coastline. This result is obtained despite the buffering capacity increasing in the coastal waters further inland as shown by the increase in alkalinity by 1.1±0.7 and 2.6±1.0 µmol kg−1 yr−1 in the inner and outer Ría de Vigo respectively, driven by interannual changes in the surface salinity of 0.0193±0.0056 and 0.0426±0.016 psu yr−1 respectively. The loss of the vertical salinity gradient in the long-term trend in the inner ria was consistent with other significant biogeochemical changes such as a lower oxygen concentration and fertilization of the surface waters. These findings seem to be related to a growing footprint of sediment remineralization of organic matter in the surface layer of a more homogeneous water column. | Q11: =getStatusCode(G11) -> 200 | R11: =getStatusCode(I11) -> 200
A12: 45964.778 | C12: Data compilations | D12: Marine Inorganic Carbonate Chemistry in the Northern Gulf of Alaska | E12: Monacci, N. M., Cross, J. N., Evans, W., Mathis, J. T., and Wang, H.: A decade of marine inorganic carbon chemistry observations in the northern Gulf of Alaska – insights into an environment in transition, Earth Syst. Sci. Data, 16, 647–665, https://doi.org/10.5194/essd-16-647-2024, 2024. | F12: Monacci et al. (2024) | G12: https://doi.org/10.5194/essd-16-647-2024 | H12: https://essd.copernicus.org/articles/16/647/2024/essd-16-647-2024-avatar-web.png | I12: https://www.ncei.noaa.gov/data/oceans/ncei/ocads/metadata/0277034.html | K12: discrete | L12: 2008 - 2017 | M12: Coastal ocean, Water column | N12: Discrete bottle | O12: A synthesis of twenty cruises from 2008 to 2017 on the Gulf of Alaska (GAK) Line | P12: Monacci et al. (2023) compiled a data product of discrete seawater samples collected each May and September over a 10-year period from 2008 to 2017 along the long-term hydrographic line in the Gulf of Alaska (GAK Line). Samples were collected from a sampling rosette on a profiling CTD. Data variables include profiled seawater temperature, salinity, and DO. Discrete sample variables include DO (i.e., Winkler titrations), macronutrients (nitrate, nitrite, phosphate, silicic acid), DIC, and TA. All carbonate system variables were analyzed at the Ocean Acidification Research Center (OARC) at the University of Alaska Fairbanks (UAF). The repeat hydrographic cruises were funded by the Alaska Ocean Observing System (AOOS), the Exxon Valdez Oil Spill Trustee Council (EVOS), Gulf Watch Alaska, and the North Pacific Research Board (NPRB) and were mostly conducted aboard the United States Fish and Wildlife Service (USFWS) R/V Tiĝlax̂. | Q12: =getStatusCode(G12) -> 200 | R12: =getStatusCode(I12) -> 200
A13: 45987.642 | B13: nicole.besemer@noaa.gov | C13: Data compilations | D13: Coral Reef Carbonate Chemistry Off the Florida Keys | E13: Palacio-Castro, A. M., Enochs, I. C., Besemer, N., Boyd, A., Jankulak, M., Kolodziej, G., et al. (2023). Coral reef carbonate chemistry reveals interannual, seasonal, and spatial impacts on ocean acidification off Florida. Global Biogeochemical Cycles, 37, e2023GB007789. https://doi.org/10.1029/2023GB007789 | F13: Palacio-Castro et al. (2023) | G13: https://doi.org/10.1029/2023GB007789 | H13: https://i.ibb.co/yc5J25Q6/gbc21508-fig-0001-m.jpg | I13: https://www.ncei.noaa.gov/access/metadata/landing-page/bin/iso?id=gov.noaa.nodc:NCRMP-CO3-Atlantic | K13: irregular, bi-monthly | M13: Regional, Coastal ocean, Surface | N13: Discrete bottle | O13: Temporal trends of DIC, TA, pCO2, pH, Ωarag, in different areas of the Florida Keys | P13: Analysis of discrete seawater samples compiled from 38 permanent stations located along 10 inshore-offshore transects at the Florida Coral Reef. These samples were collected as part of NOAA's National Coral Reef Monitoring Program (NCRMP) and the South Florida Ecosystem Restoration Research (SFER) cruises. The time-series analysis provides insight into the dynamic carbonate conditions spanning the inshore to offshore gradients, encompassing four distinct regions of the Florida Coral Reef: Biscayne Bay, the Upper Keys, Middle Keys, and Lower Keys. | Q13: =getStatusCode(G13) -> 403 | R13: =getStatusCode(I13) -> 200
A14: 45979.717 | B14: simone.r.alin@noaa.gov, janewton@uw.edu | C14: Data compilations | D14: Salish Cruise Data Package | E14: Alin, S.R., J.A. Newton, R.A. Feely, B. Curry, D. Greeley, J. Herndon, and M. Warner (2024a). A decade-long cruise time-series (2008–2018) of physical and biogeochemical conditions in the southern Salish Sea, North America. Earth System Science Data, 16, 837–865, https://doi.org/10.5194/essd-16-837-2024 | F14: Alin et al. (2025a) | G14: https://doi.org/10.5194/essd-16-837-2024 | H14: https://essd.copernicus.org/articles/16/837/2024/essd-16-837-2024-avatar-web.png | I14: https://www.ncei.noaa.gov/access/ocean-carbon-acidification-data-system/oceans/SalishCruise_DataPackage.html | K14: seasonal, discrete, continuous | L14: 2008–2024 | M14: Coastal ocean, Estuaries, Water column | N14: Discrete bottle, Continuous | O14: A QCed compilation of cruise datasets from 2008 to 2024 in the southern Salish Sea and northern Washington coast. | P14: Alin et al. (2025a) compiled data from 61 individual cruise data sets that sampled marine waters of the southern Salish Sea and northern Washington coast (United States) from 2008 to 2024. Ongoing seasonal sampling occurred during April, July, and September for Puget Sound cruises has occurred since 2014 and most frequently during May and October for Sound-to-Sea cruises, which sample from Puget Sound through the Strait of Juan de Fuca to the northern Washington coast. The Salish cruise data package contains observations from a oceanographic water column profiles, with CTD sensor measurements of temperature, salinity, and oxygen; as well as discrete measurements of oxygen, nutrient, and inorganic carbonate content. | Q14: =getStatusCode(G14) -> 200 | R14: =getStatusCode(I14) -> 200
A15: 45979.717 | B15: simone.r.alin@noaa.gov, janewton@uw.edu | C15: Data compilations | D15: Salish Cruise Multi-stressor Data Product | E15: Alin, S.R., J.A. Newton, R.A. Feely, S. Siedlecki, and D. Greeley (2024b). Seasonality and response of ocean acidification and hypoxia to major environmental anomalies in the southern Salish Sea, North America (2014–2018). Biogeosciences, 21, 1639–1673, https://doi.org/10.5194/bg-21-1639-2024 | F15: Alin et al. (2025b) | G15: https://doi.org/10.5194/bg-21-1639-2024 | H15: https://bg.copernicus.org/articles/21/1639/2024/bg-21-1639-2024-avatar-web.png | I15: https://www.ncei.noaa.gov/access/ocean-carbon-acidification-data-system/oceans/SalishCruises_DataProduct.html | K15: seasonal, discrete, continuous | L15: 2008–2024 | M15: Coastal ocean, Estuaries, Water column | N15: Discrete bottle, Continuous | O15: A multi-stressor (ocean acidification, hypoxia, marine heatwaves) data product based on cruises from 2008 to 2024 in the southern Salish Sea and northern Washington coast (USA). | P15: Alin et al. (2025b) provides a data product including all finalized records from the Salish cruise data package that had a complete suite of measurements for CTD temperature, salinity, and oxygen, as well as discrete measurements of oxygen, nutrients, dissolved inorganic carbon, and total akalinity. This product also provides the most commonly used calculated carbonate system variables--pH (on the total scale), carbon dioxide fugacity (fCO2) and partial , Ωarag, and Ωcalc--to facilitate their use by a broader group of end users. | Q15: =getStatusCode(G15) -> 200 | R15: =getStatusCode(I15) -> 200
A16: 45967.509 | B16: ana.franco@bsc.es | C16: Data compilations | D16: Line P Marine Carbonate Chemistry Compilation | E16: Franco, A. C., Ianson, D., Ross, T., Hamme, R. C., Monahan, A. H., Christian, J. R., Davelaar, M., Johnson, W. K., Miller, L. A., Robert, M., and Tortell, P. D. 2021. Anthropogenic and climatic contributions to observed carbon system trends in the northeast Pacific. Global Biogeochemical Cycles, 35(7). https://doi.org/10.1029/2020GB006829 | F16: Franco et al., (2021) | G16: https://doi.org/10.1029/2020GB006829 | H16: https://i.ibb.co/4wb5JLp1/fig1-map-francoetal2021.png | I16: https://www.ncei.noaa.gov/data/oceans/ncei/ocads/metadata/0234342.html | K16: irregular, sub-annual, discrete | L16: 1990 - 2019 | M16: Open ocean, Water column, Regional | N16: Discrete bottle | O16: A compilation of fifty-five Line P cruises containing discrete DIC and TA profiles at five stations in the Northeast Pacific Ocean. Sampled approximately three times per year from 1990 to 2019 | P16: This dataset contains marine carbonate system measurements collected during 55 Line P cruises from 1990 to 2019 in the subarctic Northeast Pacific. The dataset contains quality-controlled, discrete profiles of dissolved inorganic carbon (DIC), total alkalinity (TA), temperature, salinity, dissolved oxygen and nutrients. From a total of 27 hydrographic time-series stations, only the five major stations where DIC and TA are routinely sampled were included in this compilation. Cruises were conducted approximately three times per year, typically in February, May/June and August/September. Each vertical profile was individually inspected and contrasted with the whole pool of data relative to salinity, density, and oxygen to detect and flag poor quality data following the World Ocean Circulation Experiment (WOCE) quality control convention. The recommended cruise-specific adjustments from the Pacific Ocean Interior Carbon (PACIFICA) data synthesis were applied. The Line P carbonate chemistry timeseries is maintained by Fisheries and Oceans Canada and continues to the present day. Data are available and continuously updated in the Line P repository, which can be publicly accessed after generating an account at https://waterproperties.ca. | Q16: =getStatusCode(G16) -> 403 | R16: =getStatusCode(I16) -> 200
A17: 45973.935 | B17: jens.terhaar@unibe.ch | C17: Data compilations | D17: Anthropogenic Carbon in the Arctic Ocean | E17: Terhaar, J., Tanhua, T., Stöven, T., Orr, J. C., and Bopp, L.: Evaluation of data‐based estimates of anthropogenic carbon in the Arctic Ocean, Journal of Geophysical Research: Oceans, 125(6), https://doi.org/10.1029/2020jc016124, 2020. | F17: Terhaar et al. (2020) | G17: https://doi.org/10.1029/2020jc016124 | H17: https://www.seanoe.org/data/00927/103920/illustration.gif | I17: https://www.seanoe.org/data/00927/103920/ | K17: climatology | L17: 2005 | M17: Open ocean | N17: Discrete bottle | O17: Observation-based estimates of anthropogenic carbon in the Arctic Ocean | P17: This dataset includes anthropogenic carbon estimates in the Arctic Ocean based on measurements of transient tracers, such as CFC-12 and SF6 (Terhaar et al., 2020; Tanhua et al., 2009). Using the transient time distribution (TTD) method, anthropogenic carbon estimates were estimated at measurement locations across all basins of the Arctic Ocean between 1983 and 2005. In addition to these estimates, adjusted estimates of anthropogenic carbon at these locations are provided to account for differences in the saturation of transient tracers and anthropogenic carbon in Arctic Ocean surface waters that caused anthropogenic carbon estimates to be biased low (Terhaar et al., 2020). It is recommended to use the adjusted estimates. This dataset can be accessed at https://doi.org/10.17882/103920 (Terhaar et al., 2024). | Q17: =getStatusCode(G17) -> 403 | R17: =getStatusCode(I17) -> 200
A18: 45975.472 | B18: nick.bates@bios.edu | C18: Time series | D18: BATS | E18: Bates, N., Johnson, R. J., Lomas, M. W., Smith, D., Lethaby, P. J., Bakker, R., Davey, E., Derbyshire, L., Enright, M., Garley, R., Hayden, M. G., Lomas, D., May, R., Medley, C., Stuart, E., Chambers, E. (2025) Discrete bottle samples collected at the Bermuda Atlantic Time-series Study (BATS) site in the Sargasso Sea from October 1988 through December 2024. Biological and Chemical Oceanography Data Management Office (BCO-DMO). (Version 8) Version Date 2025-06-27 [if applicable, indicate subset used]. doi:10.26008/1912/bco-dmo.3782.8 [access date];</br></br>Bates, N., and Johnson, R.J., 2023. Forty years of ocean acidification observations (1983-2023) in the Sargasso Sea at the Bermuda Atlantic Time-series Study (BATS) site. Frontiers in Marine Science, 10, https://doi.org/10.3389/fmars.2023.1289931. | F18: Bates and Johnson (2023) | G18: https://doi.org/10.3389/fmars.2023.1289931 | H18: https://www.frontiersin.org/files/Articles/1289931/fmars-10-1289931-HTML-r1/image_m/fmars-10-1289931-g001.jpg | I18: https://www.bco-dmo.org/project/2124 | K18: monthly | L18: 1988-2025 | M18: Open ocean | N18: Discrete bottle | O18: Forty years of ocean acidification observations (1983-2023) in the Sargasso Sea at the Bermuda Atlantic Time-series Study (BATS) site. | P18: Ocean physical and biogeochemical conditions are rapidly changing over time. Forty years of observations from 1983 to 2023 collected at the Bermuda Atlantic Time-series Study (BATS) site near Bermuda in the North Atlantic Ocean shows continuing trends of surface warming, increase in salinity, loss of dissolved oxygen (DO), increase in carbon dioxide (CO2), and ocean acidification (OA) effects. Over this period, the ocean has warmed by about +1°C, increased in salinity by +0.136, and lost DO by 12.5 µmol kg−1 or ~6%. Since the 1980s, ocean dissolved inorganic carbon (DIC), total alkalinity (TA), a tracer of anthropogenic CO2 (CTrOCA), and fugacities/partial pressures of CO2 (i.e., fCO2 and pCO2) have continued to increase substantially, with no evidence of a reduction in the rates of change over time. Contemporaneously, ocean pH has decreased by ~0.1 pH units [with ocean acidity (i.e., H+) increasing by >30%], and the saturation states of calcium carbonate minerals (Ωcalcite and Ωaragonite) have decreased. These OA indicators show that the chemical conditions for calcification have become less favorable over the past 40 years. Updating of data and trends at the BATS site show how ocean chemistry of the 2020s is now outside the range observed in the 1980s, and how essential these data are for predicting the response of ocean chemistry and marine ecosystems to future shifting earth and ocean conditions. | Q18: =getStatusCode(G18) -> 200 | R18: =getStatusCode(I18) -> 200
A19: 45977.154 | B19: jdore@montana.edu | C19: Time series | D19: HOT | E19: Dore, J. E., Lukas, R., Sadler, D. W., Church, M. J., and Karl, D. M.: Physical and biogeochemical modulation of ocean acidification in the central North Pacific, Proc. Natl. Acad. Sci., 106, 12235-12240, https://doi.org/10.1073/pnas.0906044106, 2009. | F19: Dore et al. (2009) | G19: https://doi.org/10.1073/pnas.0906044106 | H19: https://i.ibb.co/B2vPqjyw/HOTlogo.jpg | I19: https://doi.org/10.1575/1912/bco-dmo.3773.1 | K19: monthly | L19: 1988-2025 | M19: Open ocean, Water column | N19: Continuous, Discrete bottle | O19: 35+ years of inorganic carbon dynamics in the open waters of the central North Pacific | P19: The Hawaii Ocean Time-series (HOT) CO2 measurement program documents 35+ years of inorganic carbon dynamics in the open waters of the central North Pacific. Since October 1988, full ocean depth profiles of DIC and TA have been analyzed, and direct measurements of pH have been made over most of this longest-running Pacific Ocean time-series study. The program is based on shipboard observations and experiments conducted on ~10 expeditions per annum to Station ALOHA (22.75°N, 158°W). | Q19: =getStatusCode(G19) -> 200 | R19: =getStatusCode(I19) -> 403
A20: 46032.028 | B20: Liqing.Jiang@noaa.gov | C20: Time series | D20: ESTOC | E20: González-Dávila, M. and Santana-Casiano J. M.: Long-term trends of pH and inorganic carbon in the Eastern North Atlantic: the ESTOC site, Front. Mar. Sci., 10, 1236214, https://doi.org/10.3389/fmars.2023.1236214, 2023. | F20: González-Dávila and Santana-Casiano (2023) | G20: https://doi.org/10.3389/fmars.2023.1236214 | H20: https://www.frontiersin.org/files/Articles/1236214/fmars-10-1236214-HTML-r1/image_m/fmars-10-1236214-g001.jpg | I20: https://doi.org/10.1594/PANGAEA.959856 | K20: irregular | M20: Open ocean | N20: Continuous, Discrete bottle | O20: The longest continuous monthly record of warming, rising carbon dioxide levels, and OA in the eastern North Atlantic | P20: The European Station for Time-series in the Ocean (ESTOC) began carbon dioxide monitoring in October 1995, providing a 30-year record on DIC, TA, and pH. This dataset represents the longest continuous monthly record of warming, rising carbon dioxide levels, and acidification in the eastern North Atlantic (González-Dávila and Santana-Casiano, 2023). ESTOC is located 100 km north of the Canary Islands archipelago (https://plocan.eu/en/installations/ocean-observatory). The program includes a ship-based observation system, measuring physical, chemical, and biological variables throughout the 3,670-meter water column. It also features a moored platform for surface meteorological and oceanic observations as well as subsurface measurements, maintained by the Canary Island Oceanic Platform (PLOCAN, https://plocan.eu/en) and the University of Las Palmas de Gran Canaria (https://iocag.ulpgc.es/research/research-units/quima). Carbonate system measurements include full-depth bottle sampling for photometric pH, TA, and DIC, conducted monthly from 1995 to 2008, every two months until 2018, and semiannually in recent years due to limited ship time, timed to coincide with moored structure maintenance. ESTOC is also visited every two weeks by a volunteer observing ship, ES-SOOP-CanOA (https://meta.icos-cp.eu/resources/stations/OS_687B), part of the European Research Infrastructure ICOS (https://www.icos-cp.eu/observations/ocean/stations), which provides real-time surface data on carbon dioxide fluxes and OA. The program also includes the CO2-ESTOC oceanographic buoy (https://meta.icos-cp.eu/labeling/). | Q20: =getStatusCode(G20) -> 200 | R20: =getStatusCode(I20) -> 200
A21: 45965.727 | B21: liqing.jiang@noaa.gov | C21: Time series | D21: Point B Time-series | E21: Kapsenberg, L., Alliouane, S., Gazeau, F., Mousseau, L., and Gattuso, J.-P.: Coastal ocean acidification and increasing total alkalinity in the northwestern Mediterranean Sea, Ocean Sci., 13, 411–426, https://doi.org/10.5194/os-13-411-2017, 2017. | F21: Kapsenberg et al. (2017) | G21: https://doi.org/10.5194/os-13-411-2017 | H21: https://i.ibb.co/8gK4B2BP/Point-B.png | I21: https://doi.org/10.1594/PANGAEA.727120 | K21: discrete | M21: Coastal ocean | N21: Discrete bottle | O21: Carbonate chemistry at a coastal site of the Bay of Villefranche, France | P21: The Point B Time-series documents the carbonate chemistry at a coastal site of the Bay of Villefranche (43.686200N 7.314800E) in Villefranche-sur-mer, France, northwestern Mediterranean Sea. Since January 2007, seawater is sampled weekly at 1 and 50 m, and analyzed for DIC and TA. Salinity and temperature are extracted from CTD profiles. Variables of the carbonate system such as pH (total scale) are calculated using the R package seacarb. | Q21: =getStatusCode(G21) -> 200 | R21: =getStatusCode(I21) -> 200
A22: 45965.744 | B22: liqing.jiang@noaa.gov | C22: Time series | D22: Ny-Ålesund Time-series | E22: Gattuso, J.-P., Alliouane, S., and Fischer, P.: High-frequency, year-round time series of the carbonate chemistry in a high-Arctic fjord (Svalbard), Earth Syst. Sci. Data, 15, 2809–2825, https://doi.org/10.5194/essd-15-2809-2023, 2023. | F22: Gattuso et al. (2023) | G22: https://doi.org/10.5194/essd-15-2809-2023 | H22: https://essd.copernicus.org/articles/15/2809/2023/essd-15-2809-2023-avatar-web.png | I22: https://doi.org//10.1594/PANGAEA.957028 | K22: continuous, discrete | M22: Coastal ocean | N22: Continuous | O22: Carbonate chemistry at a coastal site of Kongsfjorden, Spitsbergen | P22: The Ny-Ålesund Time-series documents the carbonate chemistry at a coastal site of Kongsfjorden, Spitsbergen (78.930660N 11.920030E) during the period 2015-2021. It is the first high-frequency (1 hour), multi-year (6 years) dataset of salinity, temperature, pCO2, pH, as well as calculated DIC and TA in the High-Arctic Ocean (Gattuso et al., 2023). | Q22: =getStatusCode(G22) -> 200 | R22: =getStatusCode(I22) -> 200
A23: 46030.626 | B23: nlan@norceresearch.no | C23: Time series | D23: SPOTS | E23: Lange, N., Fiedler, B., Álvarez, M., Benoit-Cattin, A., Benway, H., Buttigieg, P. L., Coppola, L., Currie, K., Flecha, S., Gerlach, D. S., Honda, M., Huertas, I. E., Lauvset, S. K., Muller-Karger, F., Körtzinger, A., O'Brien, K. M., Ólafsdóttir, S. R., Pacheco, F. C., Rueda-Roa, D., Skjelvan, I., Wakita, M., White, A., and Tanhua, T.: Synthesis Product for Ocean Time Series (SPOTS) – a ship-based biogeochemical pilot, Earth Syst. Sci. Data, 16, 1901–1931, https://doi.org/10.5194/essd-16-1901-2024, 2024. | F23: Lange et al., (2024) | G23: https://doi.org/10.5194/essd-16-1901-2024 | H23: https://i.ibb.co/qYM6NNbv/Logo.png | I23: https://www.bco-dmo.org/dataset/896862 | K23: irregular | L23: 1983 - 2021 | M23: Open ocean, Coastal ocean, Water column | N23: Discrete bottle | O23: The pilot includes biogeochemical data from 12 fixed ship-based time-series programs | P23: The Synthesis Product for Ocean Time-Series (SPOTS) is a ship-based biogeochemical pilot, aiming at regularly providing high quality data from fixed time-series stations with consistent format and semantics (Lange et al., 2024a). The pilot includes data from 12 fixed ship-based time-series programs with a focus on the Global Ocean Observing System’s biogeochemical essential ocean variables. These stations represent unique marine environments across a variety of spatiotemporal resolutions and ranges, with data from 1983 to 2021. | Q23: =getStatusCode(G23) -> 200 | R23: =getStatusCode(I23) -> 200
A24: 45962.744 | C24: Time series | D24: pCO2 and pH Time-series from 40 Surface Buoys | E24: Sutton, A. J., Feely, R. A., Maenner-Jones, S., Musielwicz, S., Osborne, J., Dietrich, C., Monacci, N., Cross, J., Bott, R., Kozyr, A., Andersson, A. J., Bates, N. R., Cai, W.-J., Cronin, M. F., De Carlo, E. H., Hales, B., Howden, S. D., Lee, C. M., Manzello, D. P., McPhaden, M. J., Meléndez, M., Mickett, J. B., Newton, J. A., Noakes, S. E., Noh, J. H., Olafsdottir, S. R., Salisbury, J. E., Send, U., Trull, T. W., Vandemark, D. C., and Weller, R. A.: Autonomous seawater pCO2 and pH time series from 40 surface buoys and the emergence of anthropogenic trends, Earth Syst. Sci. Data, 11, 421–439, https://doi.org/10.5194/essd-11-421-2019, 2019. | F24: Sutton et al. (2019) | G24: https://doi.org/10.5194/essd-11-421-2019 | H24: https://essd.copernicus.org/articles/11/421/2019/essd-11-421-2019-avatar-web.png | I24: https://www.ncei.noaa.gov/access/ocean-carbon-acidification-data-system/oceans/Moorings/ndp097.html | K24: continuous | M24: Open ocean, Coastal ocean, Surface | N24: Continuous | O24: Based on 40 moored surface pCO2 time-series, with 17 of them containing pH | P24: Sutton et al. (2019) established a living dataset comprising 40 individual autonomous moored surface ocean pCO2 time-series established between 2004 and 2013, 17 of them also include autonomous pH measurements. These time-series characterize a wide range of surface ocean carbonate system conditions, across a variety of environments, including 17 oceanic and 13 coastal locations, as well as 10 coral reefs. | Q24: =getStatusCode(G24) -> 200 | R24: =getStatusCode(I24) -> 200
A25: 46121.63 | B25: sebastien.petton@ifremer.fr | C25: Time series | D25: French coastal carbonate time-series | E25: Petton, S., Pernet, F., Le Roy, V., Huber, M., Martin, S., Macé, É., Bozec, Y., Loisel, S., Rimmelin-Maury, P., Grossteffan, É., Repecaud, M., Quemener, L., Retho, M., Manac'h, S., Papin, M., Pineau, P., Lacoue-Labarthe, T., Deborde, J., Costes, L., Polsenaere, P., Rigouin, L., Benhamou, J., Gouriou, L., Lequeux, J., Labourdette, N., Savoye, N., Messiaen, G., Foucault, E., Ouisse, V., Richard, M., Lagarde, F., Voron, F., Kempf, V., Mas, S., Giannecchini, L., Vidussi, F., Mostajir, B., Leredde, Y., Alliouane, S., Gattuso, J.-P., and Gazeau, F.: French coastal network for carbonate system monitoring: the CocoriCO2 dataset, Earth Syst. Sci. Data, 16, 1667–1688, https://doi.org/10.5194/essd-16-1667-2024, 2024. | F25: Petton et al. (2022) | G25: https://doi.org/10.5194/essd-16-1667-2024 | H25: https://i.ibb.co/67Qd9xr3/Fig6-Suivi-Cocori-CO2-p-H.png | I25: https://doi.org/10.17882/96982 | K25: daily, monthly, discrete | L25: 2021 - 2025 | M25: Coastal ocean, Estuaries | N25: Continuous, Discrete bottle | O25: High-frequency pH and biweekly carbonate chemistry monitoring at six strategic shellfish production sites along the French Atlantic and Mediterranean coasts. | P25: Petton et al. (2023a) present a dataset generated by the CocoriCO2 project, launched in 2021 to monitor acidification across French coastal waters. This network relies on six strategic sites for shellfish farming (Atlantic and Mediterranean), where autonomous sensors record high-frequency pH (every 15 min) alongside biweekly monitoring of total alkalinity and dissolved inorganic carbon. Spanning over two years, these time-series reveal significant variability in the carbonate system driven by freshwater inputs, tides, and biological processes, contrasting with the relative stability of the open ocean. | Q25: =getStatusCode(G25) -> 200 | R25: =getStatusCode(I25) -> 200
A26: 45973.952 | B26: afay@ldeo.columbia.edu | C26: Gridded surface | D26: Takahashi ΔfCO2 & Flux Climatology | E26: Fay, A. R., Munro, D. R., McKinley, G. A., Pierrot, D., Sutherland, S. C., Sweeney, C., and Wanninkhof, R. 2024. Updated climatological mean ΔfCO2 and net sea–air CO2 flux over the global open ocean regions, Earth Syst. Sci. Data, 16, 2123–2139, https://doi.org/10.5194/essd-16-2123-2024. | F26: Fay et al. (2024) | G26: https://doi.org/10.5194/essd-16-2123-2024 | H26: https://essd.copernicus.org/articles/16/2123/2024/essd-16-2123-2024-avatar-web.png | I26: https://doi.org/10.25921/295g-sn13 | J26: 1° x 1° | K26: monthly | L26: 2010 | M26: Open ocean | O26: Does not use proxy variables for extrapolation. Only produced as monthly climatology. | P26: Following on previous climatologies published by the late Taro Takahashi in 1997 and 2009, Fay et al. (2024) created a legacy climatology using his methodology and the updated SOCAT database of observations. This product provides 12 months of delta fCO2 values and corresponding fluxes for a base year of 2010 at 4° × 5° resolution subsequently subgridded to 1° × 1° resolution and near-global coverage. This climatology represents the mean of ocean conditions over the last four decades and is distinctive relative to many other mechanistic machine learning approaches in that it interpolates in time and space using only the available fCO2 data and a surface water advection scheme rather than using proxy variables for gap filling. It uses the median of observations to determine a reference year of 2010 and fluxes are provided using air-sea partial pressure differences and inputs from the SeaFlux product (Fay et al., 2021). | Q26: =getStatusCode(G26) -> 200 | R26: =getStatusCode(I26) -> 200
A27: 45964.856 | C27: Gridded surface | D27: MPI-ULB-SOM-FFN | E27: Landschützer, P., Laruelle, G. G., Roobaert, A., and Regnier, P.: A uniform pCO2 climatology combining open and coastal oceans, Earth Syst. Sci. Data, 12, 2537–2553, https://doi.org/10.5194/essd-12-2537-2020, 2020. | F27: Landschützer et al. (2020) | G27: https://doi.org/10.5194/essd-12-2537-2020 | H27: https://essd.copernicus.org/articles/12/2537/2020/essd-12-2537-2020-avatar-web.png | I27: https://www.ncei.noaa.gov/access/ocean-carbon-acidification-data-system/oceans/MPI-ULB-SOM_FFN_clim.html | J27: 0.25° x 0.25° | K27: monthly, climatology | M27: Open ocean, Coastal ocean, Surface | O27: Monthly gridded pCO2 without adjusting for a specific reference year, high-resolution coastal ocean coverage. | P27: Landschützer et al. (2020a) created a uniform pCO2 climatology combining open and coastal oceans. It is a monthly gridded global surface ocean pCO2 data product without adjusting for a specific reference year. Developed on a higher-resolution 0.25° × 0.25° global surface-ocean grid, this product is the result of combining two neural network-based pCO2 products: the open ocean product described below (i.e., Landschützer et al., 2016) and the coastal product created by Laruelle et al. (2017). Consequently, it represents coastal zones better. Data collected between 1998 and 2015 from the SOCAT database (Version 5) were used to create this data product. | Q27: =getStatusCode(G27) -> 200 | R27: =getStatusCode(I27) -> 200
A28: 45964.86 | C28: Gridded surface | D28: VLIZ-SOM-FFN | E28: Landschützer, P., Gruber, N., and Bakker, D. C. E.: Decadal variations and trends of the Global Ocean Carbon Sink, Global Biogeochemical Cycles, 30(10), 1396–1417. https://doi.org/10.1002/2015gb005359, 2016. | F28: Landschützer et al. (2016) | G28: https://doi.org/10.1002/2015gb005359 | H28: https://www.ncei.noaa.gov/data/oceans/archive/arc0105/0160558/8.8/about/0160558_preview.png | I28: https://www.ncei.noaa.gov/data/oceans/ncei/ocads/metadata/0160558.html | J28: 1° x 1° | K28: monthly, climatology | L28: 1982 - 2025 | M28: Open ocean | O28: Monthly gridded pCO2 from 1982 through near present | P28: Landschützer et al. (2016) employed the Self-Organizing-Map Feed-Forward Network (SOM-FFN) neural network method (Landschützer et al., 2013) to map sea surface pCO2 from SOCAT (see No. 1 above) (Bakker et al., 2014) to generate monthly pCO2 fields on a 1° × 1° global surface ocean grid, covering the period from 1982 to near present. It is based on the gridded pCO2 measurements from SOCAT and is updated regularly. The creation of the pCO2 fields involve a two-step neural network approach, which has been extensively detailed and validated in previous works by Landschützer et al. (2013, 2014, 2016). In the initial step, the global ocean is clustered into biogeochemical provinces, and subsequently, the non-linear relationship between CO2 driver variables and gridded data from SOCAT (Bakker et al., 2016) is reconstructed. Air-sea CO2 fluxes are also computed based on the air-sea pCO2 difference, utilizing a bulk gas transfer formulation as described by Landschützer et al. (2013, 2014, 2016). | Q28: =getStatusCode(G28) -> 403 | R28: =getStatusCode(I28) -> 200
A29: 45966.249 | B29: iida-ysk@met.kishou.go.jp | C29: Gridded surface | D29: JMA-MLR | E29: Iida, Y., Takatani, Y., Kojima, A., and Ishii, M. 2021. Global trends of ocean CO2 sink and ocean acidification: An obsevation-based reconstruction of surface ocean inorganic carbon variables, J. Oceanogr. 77, 323-358, https://doi.org/10.1007/s10872-020-00571-5 | F29: Iida et al. (2021) | G29: https://doi.org/10.1007/s10872-020-00571-5 | H29: https://www.data.jma.go.jp/kaiyou/data/db/mar_env/results/co2_flux/animation/fluxmap_fig/flux_2023MN.png | I29: https://doi.org/10.1007/s10872-020-00571-5 | J29: 1° x 1° | K29: monthly | L29: 1990-2023 | M29: Open ocean, Surface | O29: Temporal trends of DIC, TA, pCO2, air-sea CO2 flux, pH, and Ωarag. | P29: Iida et al. (2021) developed a monthly data product for inorganic carbonate variables on a 1° × 1° global surface ocean grid for the period 1993?2018. Variables include DIC, TA, pCO2, sea-air CO2 flux, pH, and Ωarag. They leveraged data products such as SOCAT.v2019 (Bakker et al., 2016) and GLODAPv2.2019 (Olsen et al., 2019), as well as satellite-based variables, including sea-surface dynamic height (SSDH), mixed layer depth (MLD), and chlorophyll-a. The product is updated annually using the latest SOCAT and GLODAPv2 data. | Q29: =getStatusCode(G29) -> 200 | R29: =getStatusCode(I29) -> 200
A30: 45961.91 | B30: gregorl@ethz.ch | C30: Gridded surface | D30: OceanSODA-ETHZv1 | E30: Gregor, L.; Gruber, N. OceanSODA-ETHZ: A Global Gridded Data Set of the Surface Ocean Carbonate System for Seasonal to Decadal Studies of Ocean Acidification. Earth System Science Data 2021, 13 (2), 777–808. https://doi.org/10.5194/essd-13-777-2021. | F30: Gregor and Gruber (2021) | G30: https://doi.org/10.5194/essd-13-777-2021 | H30: https://essd.copernicus.org/articles/13/777/2021/essd-13-777-2021-avatar-web.png | I30: https://www.ncei.noaa.gov/data/oceans/ncei/ocads/metadata/0220059.html | J30: 1° x 1° | K30: monthly | L30: 1982 - 2022 | M30: Open ocean, Surface | O30: Temporal trends of DIC, TA, pCO2, pH, Ωarag, and Ωcalc | P30: A monthly gridded global surface ocean data product for multiple ocean carbonate system variables, including DIC, TA, pCO2, pH (total scale), Ωarag, and Ωcalc (Gregor and Gruber, 2020; Gregor and Gruber, 2021; Gregor and Gruber, 2023; Ma et al., 2023). This dataset is structured on a 1°×1° global surface ocean grid with monthly resolution from 1982–2022, facilitating research on OA over seasonal to decadal scales. The OceanSODA-ETHZ data product was created by extrapolating in time and space the surface ocean observations of fCO2 from SOCATv2022 (Bakker et al., 2016) and TA from GLODAPv2.2022 using the newly developed Geospatial Random Cluster Ensemble Regression (GRaCER) method (Gregor, 2021). TA and pCO2 were then used to calculate the remaining variables of the marine carbonate system with the PyCO2SYS software (Humphreys et al., 2022). Phosphate and silicate from WOA 2018 product were used (Boyer et al., 2018; Garcia et al., 2018a). | Q30: =getStatusCode(G30) -> 200 | R30: =getStatusCode(I30) -> 200
A31: 45961.913 | B31: gregorl@ethz.ch | C31: Gridded surface | D31: OceanSODA-ETHZv2 | E31: Gregor, L.; Shutler, J.; Gruber, N. High-Resolution Variability of the Ocean Carbon Sink. Global Biogeochemical Cycles 2024, 38 (8), e2024GB008127. https://doi.org/10.1029/2024GB008127. | F31: Gregor et al. (2024) | G31: https://doi.org/10.1029/2024GB008127 | H31: https://i.ibb.co/9mHfTX1H/gbc21584-fig-0007-m.jpg | I31: https://zenodo.org/records/11206366 | J31: 0.25° x 0.25° | K31: 8-day | L31: 1982 - 2023 | M31: Open ocean, Surface | O31: Highlighting fine-scale and short-term variability of the ocean carbon sink | P31: A surface fCO₂ product with a 0.25° × 0.25° spatial resolution and an 8-day temporal resolution, providing estimates starting from 1982 (Gregor et al., 2024a; Gregor et al., 2024b). The high-resolution outputs are suitable for investigating the shorter- and finer-scale dynamics of surface fCO2. Despite sharing a name with its predecessor, OceanSODA-ETHZv2 does not provide TA estimates and employs a different methodology, as described in the following steps: 1) The atmospheric trend of CO2 is removed by subtracting marine boundary layer CO2 concentrations from SOCAT fCO2 producing a new target ∆*CO2 to reduce the biases at the start and end of the time-series. 2) An 8-day seasonal climatology of ∆*CO2 is estimated using Gradient Boosted Decision Trees (GBDT), which is later used as a predictor. 3) The non-seasonal thermal component is removed from ∆*CO2, resulting in a new target, ∆*CO2nonT. 4) The new target is estimated using a feed-forward neural network, with the GBDT as one of the forcing variables. 5) Steps 4 through to 1 are inverted to arrive at fCO2. 6) Air-sea CO2 fluxes are computed using ERA5 winds. | Q31: =getStatusCode(G31) -> 403 | R31: =getStatusCode(I31) -> 200
A32: 46031.76 | B32: Liqing.Jiang@noaa.gov | C32: Gridded surface | D32: LDEO-HPD fCO2 | E32: Gloege, L., Yan, M., Zheng, T., and McKinley, G. A.: Improved quantification of ocean carbon uptake by using machine learning to merge global models and pCO2 data, Journal of Advances in Modeling Earth Systems, 14(2), https://doi.org/10.1029/2021ms002620, 2022. | F32: Gloege et al. (2022) | G32: https://doi.org/10.1029/2021ms002620 | H32: https://i.ibb.co/pBXT90wP/jame21511-fig-0001-m.jpg | I32: https://zenodo.org/records/4760205 | J32: 1° x 1° | K32: monthly | L32: 1982-2018 | M32: Open ocean, Surface | O32: Temporal evolution of surface ocean fCO2 and air–sea CO2 exchange | P32: The LDEO Hybrid Physics Data (LDEO-HPD) estimates the temporal evolution of surface ocean fCO2 and air–sea CO2 exchange, utilizing the strengths of observations and global ocean biogeochemical models (GOBMs) (Gloege et al., 2022). GOBMs are internally consistent, mechanistic representations of the ocean circulation and carbon cycle, and have long been the standard for making spatiotemporally resolved estimates of air–sea CO2 fluxes. However, there is often a bias between the modeled fCO2 and available surface ocean measurements (Fay and McKinley 2021). The LDEO-HPD approach trains an eXtreme Gradient Boosting (XGB) algorithm to learn a non-linear relationship between model-data fCO2 mismatch and observed predictor variables: sea surface temperature (SST), sea surface salinity (SSS), chlorophyll concentration, mixed layer depth). The GOBM fCO2 is then corrected with the predicted model-data misfit to estimate real-world fCO2 for the observation period (Gloege et al., 2022). This results in reconstructed monthly surface ocean fCO2 and air–sea CO2 fluxes on a 1° × 1° grid in the open ocean beginning in 1982. | Q32: =getStatusCode(G32) -> 200 | R32: =getStatusCode(I32) -> 200
A33: 45973.959 | B33: afay@ldeo.columbia.edu | C33: Gridded surface | D33: LDEO-HPD fCO2, with Extended Temporal Coverage | E33: Gloege, L., Yan, M., Zheng, T. and McKinley, G. A.: Improved quantification of ocean carbon uptake by using machine learning to merge global models and pCO2 data, Journal of Advances in Modeling Earth Systems, 14(2), https://doi.org/10.1029/2021MS002620, 2022; </br></br>Bennington, V., Gloege, L., and McKinley, G. A.: Variability in the global ocean carbon sink from 1959 to 2020 by correcting models with observations, Geophysical Research Letters, 49(14), https://doi.org/10.1029/2022GL098632, 2022 | F33: Gloege et al. (2022), Bennington et al. (2022) | G33: https://doi.org/10.1029/2022GL098632 | H33: https://i.ibb.co/pBXT90wP/jame21511-fig-0001-m.jpg | I33: https://zenodo.org/records/13891722 | J33: 1° x 1° | K33: monthly | L33: 1959-2023 | M33: Open ocean | O33: LDEO-HPD uses model-data misfit climatology to extend estimate back in time to 1959 | P33: LDEO-HPD with Extended Temporal Coverage builds on the work of Gloege et al. (2022), the LDEO-HPD product, extending the timeseries back in time to predict fCO2 for all available model years. Bennington et al. (2022) find that the largest component of the GOBM corrections is climatological. The smaller corrections at other timescales suggest either that these are well captured by the GOBMs or the data are insufficient. The dominance of climatological corrections supports the extension of the LDEO-HPD fCO2 product backwards in time. A climatology of model-observation misfits for the best-observed period (2000–present) is applied to the GOBMs for 1959–1981, while an inter-annually varying correction is used for 1982 onward. (Bennington et al., 2022a). This results in reconstructed monthly surface ocean fCO2 and air–sea CO2 fluxes on a 1° × 1° grid covering the open ocean, beginning in 1959. | Q33: =getStatusCode(G33) -> 403 | R33: =getStatusCode(I33) -> 200
A34: 45973.963 | B34: afay@ldeo.columbia.edu | C34: Gridded surface | D34: LDEO fCO2 - Residual Method | E34: Bennington, V., Galjanic, T., & McKinley, G. A. (2022). Explicit physical knowledge in machine learning for ocean carbon flux reconstruction: The pCO2-Residual method. Journal of Advances in Modeling Earth Systems, 14, e2021MS002960. https://doi. org/10.1029/2021MS002960 | F34: Bennington et al. (2022) | G34: https://doi.org/10.1029/2021MS002960 | H34: https://i.ibb.co/xSw1HkMf/jame21703-fig-0001-m.jpg | I34: https://zenodo.org/records/13941548 | J34: 1° x 1° | K34: monthly | L34: 1982-2023 | M34: Open ocean | O34: Removes the temperature component before Machine Learning | P34: LDEO fCO2 - Residual Method estimates full-coverage fCO2 by training a machine learning algorithm on sparse in situ fCO2 data and associated physical and biogeochemical observations. While these associated variables have well-known relationships to fCO2 , it is often unclear how they mechanistically drive fCO2 around the world. The LDEO fCO2 -Residual method takes the basic approach and enhances connections between physical understanding and reconstructed fCO2 . The novel approach used here includes applying pre-processing to the fCO2 data to remove the direct effect of temperature – a relationship well-documented in literature and lab experiments. This enhances the biogeochemical/physical component of fCO2 in the target variable (now fCO2 -Residual) and reduces the complexity that the machine learning must disentangle. The resulting algorithm has physically understandable connections between input data and the output biogeochemical/physical component of fCO2. This results in reconstructed monthly surface ocean fCO2 and air–sea CO2 fluxes on a 1° × 1° grid covering the open ocean, beginning in 1982 and extended to the most recent year of available data. | Q34: =getStatusCode(G34) -> 403 | R34: =getStatusCode(I34) -> 200
A35: 45965.777 | B35: Liqing.Jiang@noaa.gov | C35: Gridded surface | D35: CMEMS-LSCEv1 | E35: Chau, T.-T.-T., Gehlen, M., and Chevallier, F.: A seamless ensemble-based reconstruction of surface ocean pCO2 and air–sea CO2 fluxes over the global coastal and open oceans. Biogeosciences, 19(4), 1087–1109, https://doi.org/10.5194/bg-19-1087-2022, 2022. | F35: Chau et al. (2022) | G35: https://doi.org/10.5194/bg-19-1087-2022 | H35: https://bg.copernicus.org/articles/19/1087/2022/bg-19-1087-2022-avatar-web.png | I35: https://data.ipsl.fr/catalog/srv/eng/catalog.search#/metadata/a2f0891b-763a-49e9-af1b-78ed78b16982 | J35: 1° x 1° | K35: monthly, climatology | L35: 1985 - 2019 | M35: Open ocean, Coastal ocean, Surface | O35: seamless reconstruction from coastal to open ocean | P35: Monthly surface ocean pCO2 and air–sea CO2 fluxes on a 1° × 1° grid in both the open ocean and coastal seas from 1985–2019 were reconstructed by Chau et al., (2022). CMEMS-LSCE is short for Copernicus Marine Environment Monitoring Service - Laboratoire des Sciences du Climat et de l’Environnement. This product is generated from an ensemble-based reconstruction of pCO2 maps trained with gridded data from SOCATv2020 (Bakker et al., 2016). Sea-surface pCO2 values (converted from the original fCO2 values in SOCATv2020) were regressed against a set of predictors with non-linear functions, i.e., feed-forward neural network (FFNN) models. The predictors include: sea-surface height (SSH), SST, SSS, MLD, chlorophyll a (Chl-a), atmospheric CO2 mole fraction (xCO2), and geographical coordinates (longitudes and latitudes). | Q35: =getStatusCode(G35) -> 200 | R35: =getStatusCode(I35) -> 200
A36: 45965.786 | B36: Liqing.Jiang@noaa.gov | C36: Gridded surface | D36: CMEMS-LSCEv2 | E36: Chau, T.-T.-T., Gehlen, M., Metzl, N., and Chevallier, F.: CMEMS-LSCE: a global, 0.25°, monthly reconstruction of the surface ocean carbonate system, Earth Syst. Sci. Data, 16, 121–160, https://doi.org/10.5194/essd-16-121-2024, 2024. | F36: Chau et al. (2024) | G36: https://doi.org/10.5194/essd-16-121-2024 | H36: https://essd.copernicus.org/articles/16/121/2024/essd-16-121-2024-avatar-web.png | I36: https://doi.org/10.48670/moi-00047 | J36: 0.25° x 0.25° | K36: monthly, climatology | L36: 1985 - 2025 | M36: Open ocean, Coastal ocean, Surface | O36: Yearly extension of time-series & monthly reconstruction at low latency | P36: CMEMS-LSCEv2 corresponds to the latest version of the CMEMS-LSCE FFNN. It uses the same ensemble-based reconstruction method for pCO2 maps as CMEMS-LSCEv1. Improvements include downscaling the spatial resolution to 0.25° × 0.25° and reproducing additional surface ocean carbonate system variables on a global grid from 1985 onwards (Chau et al., 2024a). The additional surface ocean carbonate system variables are: pCO2, DIC, TA, pH, Ωarag, and Ωcalc. Surface ocean pCO2 is reconstructed based on an ensemble of neural network models mapping gridded observation-based data provided by SOCATv2022 (Bakker et al., 2016). Surface ocean TA is estimated with a multiple linear regression approach (Carter et al., 2016, 2017). The remaining carbonate variables are calculated from pCO2 and TA using a MATLAB version of CO2SYS (Lewis and Wallace, 1998; Van Heuven et al., 2011). The CMEMS-LSCE product is updated yearly for surface ocean pCO2, air-sea fluxes, and the carbonate system variables. Updates are phased with release of the SOCAT database. For surface ocean pCO2 and air-sea fluxes the temporal coverage is extended to the present date with a latency of 1 month (Chau et al., 2024b). | Q36: =getStatusCode(G36) -> 200 | R36: =getStatusCode(I36) -> 200
A37: 46031.766 | B37: Liqing.Jiang@noaa.gov | C37: Gridded surface | D37: CarboScope (Jena-MLS) | E37: Rödenbeck, Christian, DeVries, T., Hauck, J., Le Quéré, C., & Keeling, R. F.: Data-based estimates of interannual sea-air CO2 flux variations 1957-2020 and their relation to environmental drivers, Biogeosciences, 19(10), 2627–2652, https://doi.org/10.5194/bg-19-2627-2022, 2022. | F37: Rödenbeck et al. (2022) | G37: https://doi.org/10.5194/bg-19-2627-2022 | H37: https://bg.copernicus.org/articles/19/2627/2022/bg-19-2627-2022-avatar-web.png | I37: https://www.bgc-jena.mpg.de/CarboScope/ | J37: 2.5° x 2° | K37: daily | L37: 1957-2020 | M37: Open ocean | O37: Variability of pCO2 and air–sea CO2 fluxes since 1957, sensitivities to SST and wind speed variations | P37: The Jena Mixed-Layer Scheme (within the CarboScope family of data-based estimates of carbon-cycle variability) is based on observed sea surface pCO2 from SOCAT (see above No. 1) (Bakker et al., 2014). It provides daily global fields of pCO2 and air–sea CO2 fluxes from 1957 to the year before present, on a resolution of 2.5° × 2° degrees. In the original method (Rödenbeck et al., 2013), a diagnostic model of the carbon balance in the ocean mixed layer is being fitted to the pCO2 data, by adjusting the ocean-interior sources and sinks of carbon of the mixed layer. The multi-decadal trend is derived from the data-based Ocean Circulation Inverse Model (OCIM) estimate provided by DeVries (2022b). Since a later extension described in Rödenbeck et al. (2022), the variability in the ocean-interior sources and sinks is first regressed against variability in SST and wind speed. The regression step is followed by a correction step with explicit temporal variability, to also represent data variability not yet represented by the predictors of the regression. The CarboScope product is updated yearly. | Q37: =getStatusCode(G37) -> 200 | R37: =getStatusCode(I37) -> 200
A38: 45965.553 | B38: andrew.watson@exeter.ac.uk | C38: Gridded surface | D38: UoEX-Watson | E38: Watson, A. J., Schuster, U., Shutler, J. D., Holding, T., Ashton, I. G., Landschützer, P., Woolf, D., and Goddijn-Murphy, L.: Revised estimates of ocean-atmosphere CO2 flux are consistent with ocean carbon inventory, Nature Communications, 11(1), 1–6, https://doi.org/10.1038/s41467-020-18203-3, 2020. | F38: Watson et al (2020) | G38: https://doi.org/10.1038/s41467-020-18203-3 | H38: https://i.ibb.co/tpmH1dzt/Watson.png | I38: https://www.ncei.noaa.gov/data/oceans/ncei/ocads/data/0301544/ | J38: 1° x 1° | K38: monthly | L38: 1985-2019 | M38: Open ocean | O38: Air-sea fluxes of CO2 with adjusted skin temperature effect | P38: This is a gridded estimate of the atmosphere-ocean flux of CO2. It takes into account near-surface temperature and salinity deviations due to the surface "skin effect", and small deviations in temperature caused by sampling below the actual surface of the ocean, which most estimates ignore. The result is a substantially larger estimate of net flux into the ocean than most other products. Apart from the surface correction, the SOM-FFN neural net interpolation method developed by Landschutzer et al is followed. | Q38: =getStatusCode(G38) -> 200 | R38: =getStatusCode(I38) -> 200
A39: 45968.156 | B39: zeng@nies.go.jp | C39: Gridded surface | D39: NIES-ML3 | E39: Zeng, J., Iida, Y., Matsunaga, T., and Shirai, T. 2022. Surface ocean CO2 concentration and air-sea flux estimate by machine learning with modelled variable trends. Front. Mar. Sci. 9, 989233. https://doi.org/10.3389/fmars.2022.989233 | F39: Zeng et al. (2022) | G39: https://doi.org/10.3389/fmars.2022.989233 | H39: https://i.ibb.co/zW1nfm1f/Picture3b.png | I39: https://www.nies.go.jp/doi/10.17595/20220311.001-e.html | J39: 1° x 1° | K39: monthly | L39: 1982 - 2024 | M39: Open ocean, Surface | O39: Three machine learning methods were used to simulate surface ocean CO2 trends and construct monthly CO2 maps. | P39: A feed forward neural network (NN), a random forest (RF) and a gradient boost machine (GB) were used to simulate the time variant trends of the surface ocean CO2 and construct monthly global surface ocean CO2 maps. The trends of ocean CO2 were estimated from the annual increase rate of atmospheric CO2 first and then corrected by using the NN, RF and GB with a leave-one-year-out validation method. Including different machine learning methods has the advantages of preventing over fitting by inter-comparison and reducing hot-spot by using the ensemble of their results. | Q39: =getStatusCode(G39) -> 200 | R39: =getStatusCode(I39) -> 200
A40: 45961.952 | B40: gregorl@ethz.ch | C40: Gridded surface | D40: CSIR-ML6 | E40: Gregor, L., Lebehot, A. D., Kok, S., and Scheel Monteiro, P. M.: A comparative assessment of the uncertainties of global surface ocean CO2 estimates using a machine-learning ensemble (CSIR-ML6 version 2019a) – have we hit the wall?, Geosci. Model Dev., 12, 5113–5136, https://doi.org/10.5194/gmd-12-5113-2019, 2019. | F40: Gregor et al. (2019) | G40: https://doi.org/10.5194/gmd-12-5113-2019 | H40: https://gmd.copernicus.org/articles/12/5113/2019/gmd-12-5113-2019-f09-web.png | I40: https://www.ncei.noaa.gov/data/oceans/ncei/ocads/metadata/0206205.html | J40: 1° x 1° | K40: monthly | L40: 1982 - 2020 | M40: Open ocean, Surface | O40: Various ML methods produce different results when data is sparse, but all still achieving roughly the same uncertainty | P40: Provides monthly 1° × 1° estimates of surface pCO2 (Gregor et al., 2019a). The approach uses the conceptual two-step approach of clustering and performing regressions for each cluster as Landschützer et al. (2016). CSIR-ML6 investigates the efficacy of various machine learning (ML) methods in estimating surface pCO2, namely, feed-forward neural networks (FFNN), extremely randomized trees (ERT), gradient boosting machines (GBM), and support vector regression (SVR). It is found that the ensemble of all but the ERT method resulted in the best estimate, highlighting the fact that various ML methods do not produce the same outcome, particularly when data is sparse. Further, the variance between ensemble members can inform us about regions where uncertainty may be large due to methodological differences. Despite this, all methods achieve roughly the same uncertainty – a barrier, or wall beyond which the community has yet to overcome. | Q40: =getStatusCode(G40) -> 200 | R40: =getStatusCode(I40) -> 200
A41: 45966.155 | B41: zhongguorong@qdio.ac.cn | C41: Gridded surface | D41: Stepwise-FFNN | E41: Zhong, G., Li, X., Song, J., Qu, B., Wang, F., Wang, Y., ... & Duan, L. 2022. Reconstruction of global surface ocean pCO2 using region-specific predictors based on a stepwise FFNN regression algorithm, Biogeosciences, 19, 845-859, https://doi.org/10.5194/bg-19-845-2022. | F41: Zhong et al. (2022) | G41: http://doi.org/10.12157/IOCAS.20250814.001 | H41: https://appletmsdc.qdio.ac.cn//files/metadata/images/2025-08-14_1955061943601487874/DATA20251000212_11415094_1.jpg | I41: http://doi.org/10.12157/IOCAS.20250814.001 | J41: 1° x 1° | K41: monthly | L41: 1992 - 2024 | M41: Open ocean, Surface | O41: ML-based selection of predictors considering regional differences of pCO2 drivers | P41: A monthly global 1° × 1° surface ocean pCO2 product from January 1992 to December 2024, constructed by combining the stepwise regression algorithm and a feed-forward neural network (FFNN) to select predictors of pCO2 based on the mean absolute error in each of the 11 biogeochemical provinces defined by the self-organizing map (SOM) method. | Q41: =getStatusCode(G41) -> 200 | R41: =getStatusCode(I41) -> 200
A42: 45962.758 | C42: Gridded surface | D42: AOML-ET | E42: Wanninkhof, R., Triñanes, J., Pierrot, D., Munro, D. R., Sweeney, C., and Fay, A. R.: Trends in sea-air CO2 fluxes and sensitivities to atmospheric forcing using an extremely randomized trees machine learning approach, Global Biogeochemical Cycles, 39, https://doi.org/10.1029/2024GB008315, 2025. | F42: Wanninkhof et al. (2015) | G42: https://doi.org/10.1029/2024GB008315 | H42: https://www.ncei.noaa.gov/data/oceans/archive/arc0235/0298989/2.2/about/0298989_preview.jpg | I42: https://www.ncei.noaa.gov/data/oceans/ncei/ocads/metadata/0298989.html | J42: 1° x 1° | K42: monthly, climatology | L42: 1998 - 2023 | M42: Open ocean, Surface | O42: Monthly global sea-air CO2 flux maps in modern era | P42: Wanninkhof et al. (2025) developed a monthly global ocean data product of seawater pCO2 and sea-air CO2 fluxes, referred to as AOML-ET, using an extremely randomized trees (ET) machine learning technique. These maps are created on 1° × 1° spatial grids, providing global surface ocean coverages from 1998 to 2023. AOML-ET incorporates several predictor variables, including time, location, SST, SSS, MLD, and chlorophyll-a. The model was trained using the v2020 and v2023 releases of the SOCAT data product (No. 1). Sea-air CO2 fluxes were calculated using the air-sea CO2 partial pressure difference (∆pCO2) and a bulk gas transfer formulation incorporating windspeed. | Q42: =getStatusCode(G42) -> 403 | R42: =getStatusCode(I42) -> 200
A43: 45966.455 | B43: alizee.roobaert@vliz.be | C43: Gridded surface | D43: ULB-SOM-FFN-Coastalv2.1 | E43: Roobaert, A., Regnier, P., Landschützer, P., and Laruelle, G. G.: A novel sea surface pCO2-product for the global coastal ocean resolving trends over 1982–2020, Earth System Science Data, 16(1), 421–441, https://doi.org/10.5194/essd-16-421-2024, 2024. | F43: Roobaert et al. (2024) | G43: https://doi.org/10.5194/essd-16-421-2024 | H43: https://essd.copernicus.org/articles/16/421/2024/essd-16-421-2024-f01-web.png | I43: https://doi.org/10.25921/4sde-p068 | J43: 0.25° x 0.25° | K43: monthly | L43: 1982-2020 | M43: Coastal ocean | O43: Global temporal trends of coastal pCO2 and air-sea CO2 fluxes based on SOCATv2022 with data collected from 1982–2020 | P43: Roobaert et al. (2024) present high-resolution (0.25° × 0.25° grid) monthly maps showing the distribution of sea surface pCO2 across the global coastal oceans, spanning from 1982 to 2020. This product (ULB-SOM-FFN-coastalv2.1) builds upon the work by Laruelle et al. (2017), incorporating a two-step methodology that utilizes Self Organizing Maps (SOM) and Feed Forward Networks (FFN). This updated product now captures temporal variability, enabling the assessment of interannual variability and long-term trends in coastal air-sea CO2 exchange, unlike the product by Laruelle et al. (2017), which only offers a climatology for a short period (1998-2015). The enhancements include additional environmental predictors and an expanded dataset for training and validation, featuring approximately 18 million direct coastal observations from the SOCAT database, specifically the SOCATv2022 release (Bakker et al., 2016). The product is available at OCADS: https://www.ncei.noaa.gov/data/oceans/ncei/ocads/metadata/0279118.html (Roobaert et al., 2023). | Q43: =getStatusCode(G43) -> 200 | R43: =getStatusCode(I43) -> 200
A44: 45964.893 | C44: Gridded surface | D44: RFR-LME | E44: Sharp, J. D., Jiang, L.-Q., Carter, B. R., Lavin, P. D., Yoo, H., and Cross, S. L., 2024. A mapped dataset of surface ocean acidification indicators in large marine ecosystems of the United States, Sci. Data, 11, 715, https://doi.org/10.1038/s41597-024-03530-7. | F44: Sharp et al. (2024) | G44: https://doi.org/10.1038/s41597-024-03530-7 | H44: https://i.ibb.co/ynxb1Hry/Screenshot-2025-11-07-at-09-32-32.png | I44: https://www.ncei.noaa.gov/data/oceans/ncei/ocads/metadata/0287551.html | J44: 0.25° x 0.25° | K44: monthly | L44: 1998 - 2024 | M44: Coastal ocean, Surface, Regional | O44: Temporal trends of OA indicators and estimated uncertainties across 11 U.S. Large Marine Ecosystems (LMEs), with monthly coverage from 1998–2024. | P44: A data product delineating the temporal trends of ocean acidification indicators mapped on a 0.25°× 0.25° spatial grid, across eleven U.S. Large Marine Ecosystems (LMEs), with monthly coverage from 1998–2024. The method combines Gaussian Mixture Models to categorize the data into environmentally similar subregions, Random Forest Regressions (RFRs) for the spatial and temporal extrapolation of observational fCO2 data, and regressions to estimate total alkalinity (Carter et al. 2021) to provide a second carbonate system constraint for the computation of multiple ocean acidification indicators. | Q44: =getStatusCode(G44) -> 200 | R44: =getStatusCode(I44) -> 200
A45: 46031.773 | B45: Liqing.Jiang@noaa.gov | C45: Gridded surface | D45: ReCAD-NAACOM-pCO2 | E45: Wu, Z., Lu, W., Roobaert, A., Song, L., Yan, X.-H., and Cai, W.-J.: A machine-learning reconstruction of sea surface pCO2 in the North American Atlantic Coastal Ocean Margin from 1993 to 2021, Earth Syst. Sci. Data. https://doi.org/10.5194/essd-17-43-2025, 2025. | F45: Wu et al. (2025) | G45: https://doi.org/10.5194/essd-17-43-2025 | H45: https://essd.copernicus.org/articles/17/43/2025/essd-17-43-2025-avatar-web.png | I45: https://doi.org/10.5281/zenodo.11500974 | J45: 0.25° x 0.25° | K45: monthly | L45: 1993-2021 | M45: Coastal ocean | O45: Sea surface pCO2 in the North American Atlantic Coastal Ocean Margins (NAACOM) | P45: Wu et al. (2025) developed a reconstructed pCO2 product for the North American Atlantic Coastal Ocean Margins (NAACOM), spanning from the Gulf of Mexico/Gulf of America to the Grand Banks, called the Reconstructed Coastal Acidification Database-pCO2 (ReCAD-NAACOM-pCO2). This product employed a two-step approach combining random forest regression and linear regression to generate monthly pCO2 data at 0.25° spatial resolution from 1993–2021. The model was trained using SOCAT v2023 observations as ground-truth values, incorporating various satellite-derived and reanalysis environmental variables known to influence sea surface pCO2. | Q45: =getStatusCode(G45) -> 200 | R45: =getStatusCode(I45) -> 200
A46: 45962.768 | C46: Gridded surface | D46: Gridded Surface OA Indicators in the Northern Caribbean Sea | E46: Wanninkhof, R., Pierrot, D., Sullivan, K., Barbero, L., and Triñanes, J.: A 17-year dataset of surface water fugacity of CO2 along with calculated pH, aragonite saturation state and air–sea CO2 fluxes in the northern Caribbean Sea, Earth Syst. Sci. Data, 12, 1489–1509, https://doi.org/10.5194/essd-12-1489-2020, 2020. | F46: Wanninkhof et al. (2020) | G46: https://doi.org/10.5194/essd-12-1489-2020 | H46: https://essd.copernicus.org/articles/12/1489/2020/essd-12-1489-2020-avatar-web.png | I46: https://www.ncei.noaa.gov/data/oceans/ncei/ocads/metadata/0207749.html | J46: 1° x 1° | K46: monthly, climatology | L46: 2002 - 2019 | M46: Coastal ocean | O46: A 17-year record of fCO2, TA, pH, Ωarag, and air-sea CO2 flux in the Caribbean Sea | P46: This dataset contains a high-quality dataset of derived products from over a million observations of surface water partial pressure/fugacity of carbon dioxide (pCO2w/fCO2w), for the Caribbean Sea, Gulf of Mexico/Gulf of America and North-West Atlantic Ocean covering the timespan from 2002-01-01 to 2019-12-30. The derived quantities include TA, acidity (pH), Ωarag and air-sea CO2 flux (Wanninkhof et al., 2020). | Q46: =getStatusCode(G46) -> 200 | R46: =getStatusCode(I46) -> 200
A47: 46031.783 | B47: Liqing.Jiang@noaa.gov | C47: Gridded surface | D47: OA Data in the Gulf of Mexico/Gulf of America and Wider Caribbean | E47: van Hooidonk, R.: Modeled ocean acidification data in the Gulf of Mexico and wider Caribbean using satellites and climate model data for the Ocean Acidification Products for the Gulf of Mexico and East Coast project from 2014-01-01 to 2020-12-31 (NCEI Accession 0245950), NOAA National Centers for Environmental Information, Dataset, https://doi.org/10.25921/tt1c-dx53, 2022. | F47: van Hooidonk (2022) | G47: https://doi.org/10.25921/tt1c-dx53 | H47: https://upload.wikimedia.org/wikipedia/commons/thumb/5/59/Aomlogo.svg/330px-Aomlogo.svg.png | I47: https://www.ncei.noaa.gov/data/oceans/ncei/ocads/metadata/0245950.html | J47: 0.088° x 0.088° | K47: monthly | L47: 2014-2020 | M47: Regional, Surface | O47: https://upload.wikimedia.org/wikipedia/commons/thumb/5/59/Aomlogo.svg/330px-Aomlogo.svg.png | P47: The Acidification, Climate, and Coral Reef Ecosystems Team (ACCRETE) Lab within AOML’s Ocean Chemistry and Ecosystems Division (OCED) developed a data product for tracking OA in the Caribbean and Gulf of Mexico/Gulf of America from 2014 to 2020 (van Hooidonk, 2022). Utilizing satellite imagery and a data-assimilative hybrid model, the tool maps key indicators of the water's carbonate system, including pCO2, TA, pH, Ωarag, and Ωcalc. This innovation builds upon an update to the experimental OA Product Suite (OAPS) developed by NOAA's Coral Reef Watch. | Q47: =getStatusCode(G47) -> 200 | R47: =getStatusCode(I47) -> 200
A48: 46031.789 | B48: Liqing.Jiang@noaa.gov | C48: Gridded surface | D48: pCO2 Climatology of the Baltic Sea | E48: Bittig, H.C., Jacobs, E., Neumann, T., and Rehder, G.: A regional pCO2 climatology of the Baltic Sea from in situ pCO2 observations and a model-based extrapolation approach, Earth Syst. Sci. Data, 16(2), 753–773, https://doi.org/10.5194/essd-16-753-2024, 2024. | F48: Bittig et al. (2024) | G48: https://doi.org/10.5194/essd-16-753-2024 | H48: https://essd.copernicus.org/articles/16/753/2024/essd-16-753-2024-avatar-web.png | I48: https://doi.org/10.1594/PANGAEA.961119 | J48: 0.10° x 0.05° | K48: monthly, climatology | L48: 2003-2021 | M48: Regional | O48: Does not use proxy variables for extrapolation. Spatial scales adjust locally to data density | P48: Bittig et al. (2024) used biogeochemical model output to inform the mapping of sea surface pCO2 observations in the Baltic Sea and to build a mean monthly climatology for the period 2003 to 2021, with spatial resolutions of 0.10° × 0.05° (approximately 3 nautical miles in both directions). In a first step, spatial patterns of variability were extracted from 20 years of model surface pCO2 data by an EOF analysis. These spatial patterns were then used to map surface pCO2 observations from SOCAT (see above No. 1) (Bakker et al., 2014) onto the Baltic Sea domain. By using an ensemble approach with varying number of EOF patterns, the spatial scales of the mapping were locally adjusted based on the observation’s data density. Mapped monthly fields of pCO2 from 2003–2021 were combined for the product into a mean monthly climatology and a spatially-resolved linear trend. | Q48: =getStatusCode(G48) -> 200 | R48: =getStatusCode(I48) -> 200
A49: 45974.246 | B49: kunal.c@incois.gov.in | C49: Gridded surface | D49: INCOIS-ReML | E49: Joshi, A., Ghoshal, P.K., Chakraborty, K. et al. Sea-surface pCO2 maps for the Bay of Bengal based on advanced machine learning algorithms. Sci Data 11, 384 (2024). https://doi.org/10.1038/s41597-024-03236-w | F49: Joshi et al. (2024) | G49: https://doi.org/10.1038/s41597-024-03236-w | H49: https://i.ibb.co/cShr87g7/pCO2-BoB.png | I49: https://www.ncei.noaa.gov/data/oceans/ncei/ocads/metadata/0307627.html | J49: 0.083° x 0.083° | K49: monthly | L49: 2015 | M49: Regional | O49: This data product integrates publicly available open-ocean observations with data from the Indian EEZ region in the Bay of Bengal to provide surface pCO2 and air-sea CO2 flux estimates. | P49: The Indian National Centre for Ocean Information Services-Regional Machine Learning model (INCOIS-ReML) pCO2 data product offers machine learning based monthly climatological sea surface pCO2 and the corresponding air-sea CO2 flux for the Bay of Bengal (Joshi et al., 2024). This high-resolution (0.083° × 0.083°) monthly climatological pCO2 data product is available from the INCOIS Portal: https://las.incois.gov.in, and from OCADS: https://www.ncei.noaa.gov/data/oceans/ncei/ocads/metadata/0307627.html (Joshi et al., 2025a). | Q49: =getStatusCode(G49) -> 200 | R49: =getStatusCode(I49) -> 200
A50: 45974.26 | B50: kunal.c@incois.gov.in | C50: Gridded surface | D50: INCOIS_TA | E50: Joshi, A. P., Ghoshal, P. K., Chakraborty, K., Roy, R., Jayaram, C., Sridevi, B., & Sarma, V. V. S. S. (2025). Long-term changes of surface total alkalinity and its driving mechanisms in the north Indian Ocean. Global Biogeochemical Cycles, 39, e2024GB008344. https://doi.org/10.1029/2024GB008344 | F50: Joshi et al. (2025) | G50: https://doi.org/10.1029/2024GB008344 | H50: https://i.ibb.co/BYn8GyH/Climatology-TA.png | I50: https://www.ncei.noaa.gov/data/oceans/ncei/ocads/metadata/0307789.html | J50: 0.083° x 0.083° | K50: monthly | L50: 1993-2020 | M50: Regional | O50: This data product integrates publicly available open-ocean observations with data collected during Indian scientific expeditions and from the Indian Exclusive Economic Zone to provide surface TA estimates for the North Indian Ocean. | P50: The Indian National Centre for Ocean Information Services-Total Alkalinity (INCOIS_TA) data product offers a machine learning based monthly interannual surface TA from 1993-2020 for the North Indian Ocean (Joshi et al., 2025). This data product integrates publicly available open-ocean observations with data collected during Indian scientific expeditions and from the Indian Exclusive Economic Zone. This high-resolution (0.083° × 0.083°) long-term monthly TA data product is available from the INCOIS Portal: https://las.incois.gov.in, and from OCADS: https://www.ncei.noaa.gov/data/oceans/ncei/ocads/metadata/0307789.html (Joshi et al., 2025). | Q50: =getStatusCode(G50) -> 403 | R50: =getStatusCode(I50) -> 200
A51: 45965.8 | B51: Liqing.Jiang@noaa.gov | C51: Gridded subsurface | D51: GLODAPv2 Climatology | E51: Lauvset, S. K., Key, R. M., Olsen, A., van Heuven, S., Velo, A., Lin, X., Schirnick, C., Kozyr, A., Tanhua, T., Hoppema, M., Jutterström, S., Steinfeldt, R., Jeansson, E., Ishii, M., Perez, F. F., Suzuki, T., and Watelet, S.: A new global interior ocean mapped climatology: The 1° × 1° GLODAP version 2, Earth System Science Data, 8(2), 325–340, https://doi.org/10.5194/essd-8-325-2016, 2016. | F51: Lauvset et al. (2016) | G51: https://doi.org/10.5194/essd-8-325-2016 | H51: https://i.ibb.co/dwFT2QJx/GLODAPv2-Climatology.png | I51: https://www.ncei.noaa.gov/data/oceans/ncei/ocads/metadata/0286118.html | J51: 1° x 1° | K51: climatology | L51: 2002 | M51: Open ocean, Water column | O51: Ocean interior climatology for multiple variables from surface to the bottom of the ocean (referenced to year 2002) | P51: Lauvset et al. (2016) generated a comprehensive set of global interior ocean climatologies, mapping key biogeochemical variables on a 1° × 1° grid for 33 depth levels from surface to 5500 m. These climatologies cover temperature, salinity, DO, nitrate, phosphate, silicate, DIC, TA, pH, Ωarag, and Ωcalc). This data product was created based on the quality-controlled and internally consistent GLODAPv2.2016 (Olsen et al., 2016) using the data-interpolating variational analysis (DIVA) method (Barth et al., 2014). The conceivably confounding temporal trends in DIC, pH, Ωarag and Ωcalc due to anthropogenic influence were removed prior to mapping by normalizing their values to a reference year of 2002 using first-order calculations of anthropogenic carbon accumulation rates. For all variables, all data from the full 1972–2013 period were used, including data that did not receive full secondary quality control. This data product is not updated each year along with the main GLODAPv2 data product. | Q51: =getStatusCode(G51) -> 200 | R51: =getStatusCode(I51) -> 200
A52: 45962.211 | C52: Gridded subsurface | D52: Aragonite Saturation Climatology | E52: Jiang, L.-Q., Feely, R. A., Carter, B. R., Greeley, D. J., Gledhill, D. K., and Arzayus, K. M.: Climatological distribution of aragonite saturation state in the global oceans, Global Biogeochemical Cycles, 29(10), 1656–1673, https://doi.org/10.1002/2015GB005198, 2015. | F52: Jiang et al. (2015) | G52: https://doi.org/10.1002/2015GB005198 | H52: https://i.ibb.co/KpxH4y77/gbc20348-fig-0002-m.jpg | I52: https://www.ncei.noaa.gov/data/oceans/ncei/ocads/metadata/0139360.html | J52: 1° x 1° | K52: climatology | L52: 2000 | M52: Open ocean, Water column | O52: Ocean interior climatology for (Ωarag) from surface to 4000 m (referenced to year 2000) | P52: Jiang et al. (2015a) developed an interior ocean Ωarag climatology (referenced to 2000), on a 1° × 1° grid at 9 standardized depth levels from the surface down to 4000m. This was accomplished by integrating data from the first version of GLODAP (Key et al., 2004), CARINA (Key et al., 2010), and PACIFICA (Suzuki et al., 2013), along with additional recent cruise datasets up to 2012. | Q52: =getStatusCode(G52) -> 403 | R52: =getStatusCode(I52) -> 200
A53: 45964.924 | B53: lydi@vy-carb.com | C53: Gridded subsurface | D53: MOBO-DIC (Version 2020) | E53: Keppler, L., Landschützer, P., Gruber, N., Lauvset, S. K., and Stemmler, I.: Seasonal carbon dynamics in the near-global ocean, Global Biogeochemical Cycles, 34(12), e2020GB006571, https://doi.org/10.1029/2020GB006571, 2020. | F53: Keppler et al., 2020 | G53: https://doi.org/10.1029/2020GB006571 | H53: https://www.ncei.noaa.gov/access/ocean-carbon-acidification-data-system/oceans/ndp_104/Moby.jpg | I53: https://www.ncei.noaa.gov/access/ocean-carbon-acidification-data-system/oceans/ndp_104/ndp104.html | J53: 1° x 1° | K53: monthly, climatology | L53: 2010 | M53: Open ocean | O53: Seasonal variability of DIC in the interior ocean from surface to 2000 m | P53: Keppler et al. (2020) produced a global interior ocean DIC monthly climatology (average climatological values for January through December) on a 1° × 1° grid at 33 standardized depth levels from the surface to 2000 m. | Q53: =getStatusCode(G53) -> 403 | R53: =getStatusCode(I53) -> 200
A54: 45964.928 | B54: lydi@vycarb.com | C54: Gridded subsurface | D54: MOBO-DIC (Version 2023) | E54: Keppler, L., Landschützer, P., Lauvset, S. K., and Gruber, N.: Recent trends and variability in the oceanic storage of dissolved inorganic carbon, Global Biogeochemical Cycles, 37(5), https://doi.org/10.1029/2022gb007677, 2023. | F54: Keppler et al. (2023) | G54: https://doi.org/10.1029/2022gb007677 | H54: https://www.ncei.noaa.gov/access/ocean-carbon-acidification-data-system/oceans/ndp_104/Moby.jpg | I54: https://www.ncei.noaa.gov/data/oceans/ncei/ocads/metadata/0277099.html | J54: 1° x 1° | K54: monthly | L54: 2004-2020 | M54: Open ocean | O54: Temporal trends and interannual variability of DIC in the interior ocean from surface to 1500 m | P54: Keppler et al. (2023) extended the temporal resolution of MOBO-DIC to resolve monthly fields from January 2004 to December 2019, as opposed to the average climatological values in Keppler et al. (2020). | Q54: =getStatusCode(G54) -> 403 | R54: =getStatusCode(I54) -> 200
A55: 45968.8 | B55: avelo@iim.csic.es | C55: Gridded subsurface | D55: Monthly Interior Ocean TA Climatology | E55: Broullón, D., Pérez, F. F., Velo, A., Hoppema, M., Olsen, A., Takahashi, T., Key, R. M., Tanhua, T., González-Dávila, M., Jeansson, E., Kozyr, A., and van Heuven, S. M. A. C.: A global monthly climatology of total alkalinity: a neural network approach, Earth Syst. Sci. Data, 11, 1109–1127, https://doi.org/10.5194/essd-11-1109-2019, 2019. | F55: Broullon et al., (2019) | G55: https://doi.org/10.5194/essd-11-1109-2019 | H55: https://essd.copernicus.org/articles/11/1109/2019/essd-11-1109-2019-f09-web.png | I55: https://doi.org/10.25921/5p69-y471 | J55: 1° x 1° | K55: monthly, climatology | M55: Open ocean, Water column | O55: Ocean interior climatology for TA from surface to bottom | P55: Global climatologies of the seawater CO2 chemistry variables are necessary to assess the marine carbon cycle in depth. The climatologies should adequately capture seasonal variability to properly address ocean acidification and similar issues related to the carbon cycle. Total alkalinity (AT) is one variable of the seawater CO2 chemistry system involved in ocean acidification and frequently measured. We used the Global Ocean Data Analysis Project version 2.2019 (GLODAPv2) to extract relationships among the drivers of the AT variability and AT concentration using a neural network (NNGv2) to generate a monthly climatology. The GLODAPv2 quality-controlled dataset used was modeled by the NNGv2 with a root-mean-squared error (RMSE) of 5.3 µmol kg−1. Validation tests with independent datasets revealed the good generalization of the network. Data from five ocean time-series stations showed an acceptable RMSE range of 3–6.2 µmol kg−1. Successful modeling of the monthly AT variability in the time series suggests that the NNGv2 is a good candidate to generate a monthly climatology. The climatological fields of AT were obtained passing through the NNGv2 the World Ocean Atlas 2013 (WOA13) monthly climatologies of temperature, salinity, and oxygen and the computed climatologies of nutrients from the previous ones with a neural network. The spatiotemporal resolution is set by WOA13: 1∘ × 1∘ in the horizontal, 102 depth levels (0–5500 m) in the vertical and monthly (0–1500 m) to annual (1550–5500 m) temporal resolution. The product is distributed through the data repository of the Spanish National Research Council (CSIC; https://doi.org/10.20350/digitalCSIC/8644, Broullón et al., 2019). | Q55: =getStatusCode(G55) -> 200 | R55: =getStatusCode(I55) -> 200
A56: 45968.803 | B56: avelo@iim.csic.es | C56: Gridded subsurface | D56: Monthly Interior Ocean DIC Climatology | E56: Broullón, D., Pérez, F. F., Velo, A., Hoppema, M., Olsen, A., Takahashi, T., Key, R. M., Tanhua, T., Santana-Casiano, J. M., and Kozyr, A.: A global monthly climatology of oceanic total dissolved inorganic carbon: A Neural Network approach, Earth Syst. Sci. Data, 12(3), 1725–1743, https://doi.org/10.5194/essd-12-1725-2020, 2020 | F56: Broullón et al., (2020) | G56: https://doi.org/10.5194/essd-12-1725-2020 | H56: https://essd.copernicus.org/articles/12/1725/2020/essd-12-1725-2020-f07-web.png | I56: https://doi.org/10.25921/ndgj-jp24 | J56: 1° x 1° | K56: monthly | L56: 1995 | M56: Open ocean, Water column | O56: Ocean interior climatology for DIC from surface to bottom (referenced to year 1995) | P56: Anthropogenic emissions of CO2 to the atmosphere have modified the carbon cycle for more than 2 centuries. As the ocean stores most of the carbon on our planet, there is an important task in unraveling the natural and anthropogenic processes that drive the carbon cycle at different spatial and temporal scales. We contribute to this by designing a global monthly climatology of total dissolved inorganic carbon (TCO2), which offers a robust basis in carbon cycle modeling but also for other studies related to this cycle. A feedforward neural network (dubbed NNGv2LDEO) was configured to extract from the Global Ocean Data Analysis Project version 2.2019 (GLODAPv2.2019) and the Lamont–Doherty Earth Observatory (LDEO) datasets the relations between TCO2 and a set of variables related to the former's variability. The global root mean square error (RMSE) of mapping TCO2 is relatively low for the two datasets (GLODAPv2.2019: 7.2 µmol kg−1; LDEO: 11.4 µmol kg−1) and also for independent data, suggesting that the network does not overfit possible errors in data. The ability of NNGv2LDEO to capture the monthly variability of TCO2 was testified through the good reproduction of the seasonal cycle in 10 time series stations spread over different regions of the ocean (RMSE: 3.6 to 13.2 µmol kg−1). The climatology was obtained by passing through NNGv2LDEO the monthly climatological fields of temperature, salinity, and oxygen from the World Ocean Atlas 2013 and phosphate, nitrate, and silicate computed from a neural network fed with the previous fields. The resolution is in the horizontal, 102 depth levels (0–5500 m), and monthly (0–1500 m) to annual (1550–5500 m) temporal resolution, and it is centered around the year 1995. The uncertainty of the climatology is low when compared with climatological values derived from measured TCO2 in the largest time series stations. Furthermore, a computed climatology of partial pressure of CO2 (pCO2) from a previous climatology of total alkalinity and the present one of TCO2 supports the robustness of this product through the good correlation with a widely used pCO2 climatology (Landschützer et al., 2017). Our TCO2 climatology is distributed through the data repository of the Spanish National Research Council (CSIC; https://doi.org/10.20350/digitalCSIC/10551, Broullón et al., 2020) | Q56: =getStatusCode(G56) -> 200 | R56: =getStatusCode(I56) -> 200
A57: 45962.781 | C57: Gridded subsurface | D57: Acidification Metrics in the Ocean Interior | E57: Fassbender, A. J., Carter, B. R., Sharp, J. D., Huang, Y., Arroyo, M. C., and Frenzel, H.: Amplified subsurface signals of ocean acidification, Global Biogeochemical Cycles, 37, e2023GB007843, https://doi.org/10.1029/2023GB007843, 2023. | F57: Fassbender et al. (2023) | G57: https://doi.org/10.1029/2023GB007843 | H57: https://www.ncei.noaa.gov/data/oceans/archive/arc0227/0290073/1.1/about/0290073_preview.jpg | I57: https://www.ncei.noaa.gov/data/oceans/ncei/ocads/metadata/0290073.html | J57: 1° x 1° | K57: climatology | L57: 1850 - 2002 | M57: Open ocean, Water column | O57: Metrics of acidification in the ocean interior (to 2000 m) and the component of those changes caused by carbonate system nonlinearities | P57: Fassbender et al. (2023) generated estimates of global interior ocean changes to pH, [H+], Ωarag, pCO2, and the Revelle sensitivity factor driven by the accumulation of anthropogenic carbon (Cant) from the preindustrial period to the year 2002, and quantified the component of those changes caused by nonlinearities in the carbonate system. For each OA metric, the dataset includes year 2002 values and quasi-preindustrial values, which were estimated by subtracting Cant from the year 2002 carbonate chemistry information and recomputing each OA metric without considering any warming, circulation, or biological changes that may have occurred since the preindustrial era. | Q57: =getStatusCode(G57) -> 403 | R57: =getStatusCode(I57) -> 200
A58: 45971.493 | B58: jens@carbontosea.org | C58: Gridded subsurface | D58: Ocean Interior Acidification over the Industrial Era | E58: Jens D. Müller, Nicolas Gruber, Progression of ocean interior acidification over the industrial era. Sci. Adv.10, eado3103(2024). DOI:10.1126/sciadv.ado3103 | F58: Müller et al. (2024) | G58: https://doi.org/10.1126/sciadv.ado3103 | H58: https://i.ibb.co/YT3rjvDc/sciadv-ado3103-f1.jpg | I58: https://doi.org/10.25921/tefm-x802 | J58: 1° x 1° | K58: decadal | L58: 1800 - 2014 | M58: Open ocean, Water column | O58: Temporal trends in the progression of acidification in the interior ocean are resolved | P58: Building on the total anthropogenic carbon estimates for 1994 from Sabine et al. (2004) and the decadal changes between 1994 and 2014 reconstructed by Müller et al. (2023a), Müller and Gruber (2024a) quantified ocean interior acidification over the industrial era. To convert the increasing anthropogenic carbon concentrations into acidification estimates, their approach relied on time-invariant climatologies of ocean interior DIC, TA, temperature, salinity, and other relevant variables to determine the background state of the marine carbonate system. Hence, their estimates resolve exclusively the acidification driven by the anthropogenic carbon accumulation. In contrast to direct observations of acidification variables, such as those collected at time-series stations, this approach does not account for changes in the natural carbon cycle or the displacement of water masses. | Q58: =getStatusCode(G58) -> 200 | R58: =getStatusCode(I58) -> 200
A59: 45962.982 | C59: Gridded subsurface | D59: Anthropogenic CO2 from 1994 to 2007 | E59: Gruber, N., Clement, D., Carter, B. R., Feely, R. A., van Heuven, S., Hoppema, M., Ishii, M., Key, R. M., Kozyr, A., Lauvset, S. K., Lo Monaco, C., Mathis, J. T., Murata, A., Olsen, A., Perez, F. F., Sabine, C. L., Tanhua, T., and Wanninkhof, R.: The oceanic sink for anthropogenic CO2 from 1994 to 2007, Science, 363(6432), 1193–1199, https://doi.org/10.1126/science.aau5153, 2019. | F59: Gruber et al. (2019) | G59: https://doi.org/10.1126/science.aau5153 | H59: https://www.ncei.noaa.gov/data/oceans/archive/arc0132/0186034/1.1/about/0186034_preview.jpg | I59: https://www.ncei.noaa.gov/data/oceans/ncei/ocads/metadata/0186034.html | J59: 1° x 1° | K59: climatology | L59: 1994 - 2007 | M59: Open ocean, Water column | O59: The oceanic sink for anthropogenic CO2 over the period 1994 to 2007 | P59: Gruber et al. (2019a) estimated the decadal time-scale changes in the oceanic content of anthropogenic CO2 (∆Cant) between 1994 to 2007. The results were derived from the GLODAPv2.2016 product (Olsen et al., 2016), utilizing the eMLR(C*) methodology pioneered by Clement and Gruber (2018). The product is combined with the estimated amount of Cant for 1994 derived by Sabine et al. (2004) from GLODAPv1 to infer Cant for 2007. | Q59: =getStatusCode(G59) -> 200 | R59: =getStatusCode(I59) -> 200
A60: 45971.486 | B60: jens@carbontosea.org | C60: Gridded subsurface | D60: Decadal Trends in Anthropogenic CO2 from 1994 to 2014 | E60: Müller, J. D., Gruber, N., Carter, B., Feely, R., Ishii, M., Lange, N., et al. (2023). Decadal trends in the oceanic storage of anthropogenic carbon from 1994 to 2014. AGU Advances, 4, e2023AV000875. https://doi.org/10.1029/2023AV000875 | F60: Müller et al. (2023) | G60: https://doi.org/10.1029/2023AV000875 | H60: https://eos.org/wp-content/uploads/2023/08/Fig2_highlight.jpg | I60: https://doi.org/10.25921/ppcf-w020 | J60: 1° x 1° | K60: decadal | L60: 1994 - 2014 | M60: Open ocean, Water column | O60: Temporal trends in the accumulation of anthropogenic CO2 in the interior ocean are resolved | P60: Müller et al. (2023a) extended the analysis by Gruber et al. (2019a) to reconstruct decadal trends in the oceanic storage of ∆Cant in the global ocean interior from mid-year 1994 to mid-year 2004, and further to mid-year 2014. They applied the extended multiple linear regression (eMLR) method (Clement and Gruber, 2018) to ship-borne observations of DIC and other biogeochemical variables from GLODAPv2.2021 (Lauvset et al., 2021). | Q60: =getStatusCode(G60) -> 403 | R60: =getStatusCode(I60) -> 200
A61: 45964.856 | C61: Gridded subsurface | D61: Anthropogenic carbon from 1750 to 2500 (TRACE) | E61: Carter, B. R., Schwinger, J., Sonnerup, R., Fassbender, A. J., Sharp, J. D., Dias, L. M., & Sandborn, D. E. (2025). Tracer-based Rapid Anthropogenic Carbon Estimation (TRACE). Earth System Science Data, 17(6), 3073-3088. | F61: Carter et al. (2025) | G61: https://doi.org/10.5194/essd-17-3073-2025 | H61: https://essd.copernicus.org/articles/17/3073/2025/essd-17-3073-2025-avatar-web.png | I61: https://zenodo.org/records/15692788 | J61: 1° x 1° | K61: irregular | L61: 1750-2500 | M61: Open ocean, Surface, Water column | O61: New methods for rapidly estimating anthropogenic carbon from temperature, salinity, and date are presented. The methods are then used with SSPs to estimate anthropogenic carbon in the ocean globally from 1750 to 2500. | P61: Here, we make modifications to the transit time distribution approach for Canth estimation that render the method more accessible. We also release software (BRCScienceProducts, 2025) called “Tracer-based Rapid Anthropogenic Carbon Estimation version 1” (TRACEv1) that allows users – with one line of code – to obtain Canth and water mass age estimates throughout the global open ocean from user-supplied values of geographic location, pressure, salinity, temperature, and the estimate year. We use this code to generate a data product of global gridded open-ocean Canth distributions (TRACEv1_GGCanth; Carter, 2025) that ranges from the preindustrial era through 2500 under a range of Shared Socioeconomic Pathways (SSPs, or atmospheric CO2 concentration pathways). We estimated the skill of these estimates by reconstructing Canth in models with known distributions of Canth and transient tracers and by conducting perturbation tests. In the model-based reconstruction test, TRACEv1 reproduces the global ocean Canth inventory to within ±10 % in 1980 and 2014. We discuss implications and limitations of the projected Canth distributions and highlight ways that the estimation strategy might be improved. One finding is that the ocean will continue to increase its net Canth inventory at least through 2500 due to deep-ocean ventilation, even with the SSP in which intense mitigation successfully decreases atmospheric Canth by ∼60 % in 2500 relative to the 2024 concentration. A notable limitation of this and similar projections made with TRACEv1 is that ongoing and potential future warming and changing oceanic circulation patterns with climate change are not captured by the method. The data products generated by this research are available as MATLAB code (https://doi.org/10.5281/zenodo.15692788, BRCScienceProducts, 2025) and a spatially and temporally gridded data product (https://doi.org/10.5281/zenodo.15692788, BRCScienceProducts, 2025). | Q61: =getStatusCode(G61) -> 200 | R61: =getStatusCode(I61) -> 200
A62: 45964.862 | C62: Gridded subsurface | D62: Preformed TA and other biogeochemical properties | E62: Carter, B. R., Feely, R. A., Lauvset, S. K., Olsen, A., DeVries, T., & Sonnerup, R. (2021). Preformed properties for marine organic matter and carbonate mineral cycling quantification. Global Biogeochemical Cycles, 35(1), e2020GB006623. | F62: Carter et al. (2021) | G62: https://zenodo.org/records/3745002 | H62: https://i.ibb.co/S488KKjG/gbc21075-fig-0003-m.jpg | I62: https://github.com/BRCScienceProducts/PreformedPropertyEstimates | J62: 1° x 1° | K62: climatology | M62: Open ocean, Water column | O62: We have updated global preformed biogeochemical property estimates and provided the estimates for analysis and model validation | P62: We estimate preformed ocean phosphate, nitrate, oxygen, silicate, and alkalinity by combining a reconstruction of ventilation pathways in the ocean interior with estimates of submixed layer properties. These new preformed property estimates are intended to aid biogeochemical cycling studies and validation of modeled preformed property distributions and are available online. Analyses of net property accumulations (observed minus preformed properties) indicate net remineralization ratios in the ocean interior of [1 P]: [14.1 ± 0.6 N]: [−141 ± 12 O2]: [95 ± 25 Si]: [89 ± 9 TA]. These ratios imply that the interior ocean stores 1,300 (±230) PgC through organic matter remineralization and 540 (±60) PgC through carbonate mineral dissolution and that apparent oxygen utilization can overestimate the interior ocean oxygen consumption by ~25%. Further, only 4 (±1%) and 46 (±5%) of the total alkalinity accumulated from carbonate mineral dissolution are found in seawater that is supersaturated with respect to the aragonite and calcite mineral forms of calcium carbonate, respectively. These small excess alkalinity inventories are due to smaller volumes of the supersaturated water masses and shorter ventilation timescales, as carbonate mineral dissolution rates appear nearly independent of depth and saturation state. | Q62: =getStatusCode(G62) -> 200 | R62: =getStatusCode(I62) -> 200
A63: 45966.161 | B63: zhongguorong@qdio.ac.cn | C63: Gridded subsurface | D63: Monthly Interior Ocean pH Climatology | E63: Zhong, G., Li, X., Song, J., Qu, B., Wang, F., Wang, Y., Zhang, B., Cheng, L., Ma, J., Yuan, H., Duan, L., Li, N., Wang, Q., Xing, J., and Dai, J. 2025. A global monthly 3D field of seawater pH over 3 decades: a machine learning approach, Earth Syst. Sci. Data, 17, 719–740, https://doi.org/10.5194/essd-17-719-2025. | F63: Zhong et al. (2025) | G63: http://doi.org/10.12157/IOCAS.20230720.001 | H63: https://appletmsdc.qdio.ac.cn//files/metadata/images/2025-11-07_1681888486837194754/DATA2023000009_zhongguorong_1.jpg | I63: http://doi.org/10.12157/IOCAS.20230720.001 | J63: 1° x 1° | K63: monthly | L63: 1992 - 2020 | M63: Open ocean, Water column | O63: Temporal variability of pH in the interior ocean from surface to 2000 m over 3 decades | P63: A monthly 1° × 1° gridded global seawater pH (total scale) climatology from 1992 to 2020 at in situ temperature, derived using a machine learning algorithm trained on pH observations from GLODAPv2. The product spans from 1992 to 2020 and covers depths from the surface to 2000 m across 41 vertical levels. | Q63: =getStatusCode(G63) -> 200 | R63: =getStatusCode(I63) -> 200
A64: 45962.673 | C64: Gridded subsurface | D64: CODAP-NA Climatology | E64: Jiang, L.-Q., Boyer, T. P., Paver, C. R., Yoo, H., Reagan, J. R., Alin, S. R., Barbero, L., Carter, B. R., Feely, R. A., and Wanninkhof, R.: Climatological distribution of ocean acidification variables along the North American ocean margins, Earth System Science Data, 16(7), 3383–3390, https://doi.org/10.5194/essd-16-3383-2024, 2024. | F64: Jiang et al. (2024) | G64: https://doi.org/10.5194/essd-16-3383-2024 | H64: https://essd.copernicus.org/articles/16/3383/2024/essd-16-3383-2024-avatar-web.png | I64: https://www.ncei.noaa.gov/data/oceans/ncei/ocads/metadata/0270962.html | J64: 1° x 1° | K64: climatology | L64: 2010 | M64: Coastal ocean, Water column | O64: The first discrete bottle based climatology in the North American ocean margins | P64: Jiang et al. (2024) developed a coastal OA indicators climatology on a 1°×1° grid, covering North American ocean margins from surface to 500 m at 14 standardized depth levels. This product includes 10 key oceanographic variables: fCO2, pH, [H+]total, free hydrogen ion content ([H+]free), carbonate ion content ([CO32-]), Ωarag, Ωcalc, DIC, TA, and Revelle Factor (RF), as well as temperature and salinity. The climatology was produced with the WOA gridding technologies of the NOAA National Centers for Environmental Information (NCEI), based on the recently released Coastal Ocean Data Analysis Product in North America (CODAP-NA) (Jiang et al., 2021), along with GLODAPv2.2022 (Lauvset et al., 2022). The relevant variables were adjusted to the year of 2010 before the gridding. | Q64: =getStatusCode(G64) -> 200 | R64: =getStatusCode(I64) -> 200
A65: 45961.905 | C65: Harmonized | D65: SeaFlux | E65: Fay, A. R., Gregor, L., Landschützer, P., McKinley, G. A., Gruber, N., Gehlen, M., Iida, Y., Laruelle, G. G., Rödenbeck, C., Roobaert, A., and Zeng, J.: SeaFlux: harmonization of air–sea CO2 fluxes from surface pCO2 data products using a standardized approach, Earth Syst. Sci. Data, 13, 4693–4710, https://doi.org/10.5194/essd-13-4693-2021, 2021 | F65: Fay and Gregor et al. (2021) | G65: https://doi.org/10.5194/essd-2021-16 | H65: https://seaflux.readthedocs.io/en/latest/_static/seaflux_logo.png | I65: https://zenodo.org/records/8280457 | J65: 1° x 1° | K65: monthly | L65: 1990 - 2022 | M65: Open ocean, Surface | O65: Careful consideration of flux calculation provides a resource and code to the community for independent flux calculations | P65: Harmonization of air–sea CO2 fluxes from surface pCO2 data products using a standardized approach (Gregor and Fay, 2021). This resource provides an ensemble of six pCO2 products with air-sea CO2 fluxes computed consistently. The six included products are: CMEMS-LSCEv1, CSIR-ML6, JENA-MLS, JMA-MLR, MPI-SOMFFN, and NIES-FNN. First, missing areas of pCO2 estimates (mostly high-latitude and marginal seas) are filled using a linear-regression approach, thus addressing differences in spatial coverage between the mapping products. Further, also accounts for methodological inconsistencies in flux calculations. Fluxes are calculated using three wind products (CCMPv2, ERA5, and JRA55) along with the application of a scaled gas exchange coefficient for each of the wind products. Through these steps, SeaFlux presents a product ensemble of interpolated global surface ocean pCO2 and air–sea carbon flux estimates for the years 1990–2019 | Q65: =getStatusCode(G65) -> 200 | R65: =getStatusCode(I65) -> 200
A66: 46031.755 | B66: liqing.jiang@noaa.gov | C66: Harmonized | D66: RECCAP2 | E66: DeVries, T., Yamamoto, K., Wanninkhof, R., Gruber, N., Hauck, J., Müller, J. D., Bopp, L., Carroll, D., Carter, B., Chau, T., Doney, S. C., Gehlen, M., Gloege, L., Gregor, L., Henson, S., Kim, J. H., Iida, Y., Ilyina, T., Landschützer, P., Le Quéré, C., Munro, D., Nissen, C., Patara, L., Pérez, F. F., Resplandy, L., Rodgers, K. B., Schwinger, J., Séférian, R., Sicardi, V., Terhaar, J., Triñanes, J., Tsujino, H., Watson, A., Yasunaka, S., Zeng, J. (2023). Magnitude, trends, and variability of the Global Ocean Carbon Sink from 1985 to 2018. Global Biogeochemical Cycles, 37(10). https://doi.org/10.1029/2023gb007780, 2023. | F66: DeVries et al. (2023) | G66: https://doi.org/10.1029/2023gb007780 | H66: https://i.ibb.co/NgXDHSQh/gbc21476-fig-0001-m.jpg | I66: https://zenodo.org/records/7990823 | J66: 1° x 1° | K66: monthly | L66: 1985-2018 | M66: Open ocean, Coastal ocean | O66: Quality-controlled data compilation with a harmonized horizontal grid and temporal resolution | P66: In the context of the second iteration of the project REgional Carbon Cycle Assessment and Processes (RECCAP2), the ocean carbon community compiled, quality-controlled, and harmonized (in the sense of providing output on the same regular grid at the same spatial and temporal resolution) 12 GOBMs simulations, 11 pCO2 products, one ocean interior DIC product, and three data assimilation models to constrain the ocean carbon sink between 1985 and 2018. The RECCAP2 synthesis effort stands as a distinct but complementary resource to the GCB project (Friedlingstein et al., 2025), which primarily focuses on anthropogenically perturbed surface CO2 fluxes from a global budgeting perspective. The individual chapters of RECCAP2 were published in this special issue of Global Biogeochemical Cycles: https://agupubs.onlinelibrary.wiley.com/doi/toc/10.1002/(ISSN)2169-8961.RECCAP2. The data products of this assessment are available on a 1° × 1° horizontal grid, with monthly resolution for surface ocean variables such as air–sea CO2 fluxes, and annual resolution for interior ocean variables, such as DIC content. | Q66: =getStatusCode(G66) -> 403 | R66: =getStatusCode(I66) -> 200
A67: 45986.42 | B67: judith.hauck@awi.de | C67: Harmonized | D67: Global Carbon Budget | E67: Friedlingstein, P., O’Sullivan, M., Jones, M. W., Andrew, R. M., Hauck, J., Landschützer, P., Le Quéré, C., Li, H., Luijkx, I. T., Olsen, A., Peters, G. P., Peters, W., Pongratz, J., Schwingshackl, C., Sitch, S., Canadell, J. G., Ciais, P., Jackson, R. B., Alin, S. R., … Zeng, J. (2025). Global Carbon Budget 2024. Earth System Science Data, 17(3), 965–1039. https://doi.org/10.5194/essd-17-965-2025 | F67: Friedlingstein et al. (2025) | G67: https://doi.org/10.5194/essd-17-965-2025 | H67: https://i.ibb.co/TxwRM1tp/GCP.jpg | I67: https://doi.org/10.5281/zenodo.17579108 | J67: 1° x 1° | K67: monthly | L67: 1959-2024 | M67: Open ocean, Coastal ocean, Surface, Water column | O67: Annually updated and quality controlled data sets. Availability of monthly 4D ocean model output. | P67: Global Carbon Budget: The GCB collects annually updated estimates of the ocean carbon sink from currently nine fCO2-products and ten GOBMs for the period 1959 to the past calendar year (Friedlingstein et al., 2025, https://globalcarbonbudget.org/gcb-2024). In contrast to Earth System Models, the GOBMs are here forced with atmospheric reanalysis that ingested atmosphere and ocean observations and are thus thought to be closer to the observed climate. Gridded fields are provided on a 1° × 1° horizontal grid and monthly resolution. In addition, globally and regionally integrated air-sea CO2 fluxes from the native model grids are provided. Globally integrated time-series are adjusted for full ocean coverage and model bias and drift and are available for each individual fCO2-product and GOBM (https://globalcarbonbudget.org/download/1442/?tmstv=1731323337). The model data goes well beyond surface fluxes and includes data to analyze drivers of carbon fluxes, including several 3D variables. The model data request has been updated since RECCAP2 and also provides, for example, monthly interior ocean data of DIC, TA, nutrients and DO. The GOBM data request was also updated to have all variables available that are needed to serve as a testbed for fCO2-products (e.g., sea surface height). Gridded surface data of sea surface fugacity and air-sea CO2 flux of all fCO2-products and GOBMs as used in the latest release of GCB (2024) are published on Zenodo (https://zenodo.org/records/14639761, Hauck et al., 2025). All other GOBM output is available via https://globalcarbonbudgetdata.org/closed-access-requests.html. | Q67: =getStatusCode(G67) -> 200 | R67: =getStatusCode(I67) -> 200
A68: 45969.824 | B68: Liqing.Jiang@noaa.gov | C68: Model-based | D68: Decadal Trends in the Ocean Carbon Sink | E68: DeVries, T., Le Quéré, C., Andrews, O., Berthet, S., Hauck, J., Ilyina, T., Landschützer, P., Lenton, A., Lima, I. D., Nowicki, M., Schwinger, J., and Séférian, R.: Decadal trends in the ocean carbon sink, Proceedings of the National Academy of Sciences, 116(24), 11646–11651, https://doi.org/10.1073/pnas.1900371116, 2019. | F68: DeVries et al. (2019) | G68: https://doi.org/10.1073/pnas.1900371116 | H68: https://i.ibb.co/RTWv9Yp9/pnas-1900371116fig01.jpg | I68: https://doi.org/10.6084/m9.figshare.8091161.v1 | K68: yearly | L68: 1959 - 2016 | M68: Open ocean, Surface | O68: Climate variability drove weakened ocean CO2 uptake in the 1990s, and strengthened CO2 uptake in the 2000s | P68: The DeVries et al. (2019) analysis examines decadal trends in global and regional air-sea CO2 fluxes from a variety of ocean biogeochemical models that contributed to the GCB (see No. 60). Three sets of model simulations were performed. Simulation A uses variable climate forcing (e.g., variable wind stress, heat and freshwater fluxes) and observed atmospheric CO2 forcing, Simulation B uses constant (repeated) climate forcing and observed atmospheric CO2, and simulation C uses both constant climate forcing and constant atmospheric CO2 concentrations. With these simulations, the authors partitioned decadal trends in ocean CO2 uptake into those driven by climate variability and those driven by atmospheric CO2. They found that climate variability drove a weakening trend of the ocean carbon sink during the 1990s, and a strengthening trend during the first decade of the 2000s. The magnitude of these trends agreed with those of an OCIM that was trained to replicate tracer data from the 1990s and 2000s (DeVries et al., 2017), indicating that the decadal trends may be driven by variability in ocean circulation. | Q68: =getStatusCode(G68) -> 200 | R68: =getStatusCode(I68) -> 200
A69: 45964.75 | C69: Model-based | D69: ECCO-Darwin | E69: Carroll, D., Menemenlis, D., Adkins, J. F., Bowman, K. W., Brix, H., & Dutkiewicz, S., et al. (2020). The ECCO-Darwin data-assimilative global ocean biogeochemistry model: Estimates of seasonal to multidecadal surface ocean pCO2 and air-sea CO2 flux. Journal of Advances in Modeling Earth Systems, 12, e2019MS001888. https://doi.org/10.1029/2019MS001888 | F69: Carroll et al. (2020) | G69: https://doi.org/10.5281/zenodo.10627664 | H69: https://ecco-group.org/images/ecco_rotator01.jpg | I69: https://data.nas.nasa.gov/ecco/ | J69: 0.33° x 0.33° | K69: daily, monthly | L69: 1992 - 2018 | M69: Open ocean, Coastal ocean, Surface, Water column | O69: Model-data synthesis product based on the Estimating the Circulation and Climate of the Ocean (ECCO) ocean state estimate. Fully-closed, physically-consistent 3-D biogeochemical budgets. | P69: Carroll et al. (2022) used the Estimating the Circulation and Climate of the Ocean-Darwin (ECCO-Darwin) global-ocean biogeochemistry state estimate to generate a data-constrained DIC budget and investigate how spatiotemporal variability in advection and mixing, air-sea CO2 flux, and the biological pump have modulated the ocean sink for 1995–2018. ECCO-Darwin assimilates ocean circulation and physical tracers, including temperature, salinity, and sea ice, derived from the Estimating the Circulation and Climate of the Ocean (ECCO) LLC270 global-ocean and sea-ice data synthesis (Zhang et al., 2018). Additionally, it assimilates biogeochemical observations encompassing the cycling of carbon, nitrogen, phosphorus (PO 4 ), iron (Fe), silica (SiO 2 ), DO, and TA. This inclusive approach enhances the model’s fidelity by aligning it with a diverse array of observations. All ECCO-Darwin model output is available on the ECCO Data Portal: https://data.nas.nasa.gov/ecco/. The model code and platform-independent instructions for running ECCO-Darwin simulations can be found at: https://github.com/MITgcm-contrib/ecco_darwin. | Q69: =getStatusCode(G69) -> 200 | R69: =getStatusCode(I69) -> 200
A70: 45962.68 | C70: Model-based | D70: Surface pH and Revelle Factor | E70: Jiang, L.-Q., Carter, B. R., Feely, R. A., Lauvset, S., and Olsen, A.: Surface ocean pH and buffer capacity: Past, present and future, Scientific Reports, 9(1), 18624, https://doi.org/10.1038/s41598-019-55039-4, 2019. | F70: Jiang et al. (2019) | G70: https://doi.org/10.1038/s41598-019-55039-4 | H70: https://media.springernature.com/lw685/springer-static/image/art%3A10.1038%2Fs41598-019-55039-4/MediaObjects/41598_2019_55039_Fig6_HTML.png | I70: https://www.ncei.noaa.gov/data/oceans/ncei/ocads/metadata/0206289.html | J70: 1° x 1° | K70: decadal, climatology | L70: 1770 - 2100 | M70: Open ocean, Surface | O70: A model-observation fusion product for pH, acidity and Revelle Factor, leveraging GFDL-ESM2M and SOCATv6 | P70: Jiang et al. (2019a) produced a high-resolution (1°×1°) data product delineating regionally varying view of global surface ocean pH, acidity, and Revelle Factor (RF) from 1770 to 2100 by amalgamating recent observational seawater CO2 data from the SOCAT database (Version 6, 1991–2018, ~23 million observations) (Bakker et al., 2016), and temporal trends at individual locations of the global surface ocean from an Earth System Model, i.e., GFDL-ESM2M (Dunne et al., 2013). The calculations were conducted under historical atmospheric CO2 levels (pre-2005) and four Representative Concentrations Pathways (post-2005) corresponding to the Intergovernmental Panel on Climate Change (IPCC)’s 5th Assessment Report, specifically RCP2.6, RCP4.5, RCP6.0, and RCP8.5. | Q70: =getStatusCode(G70) -> 200 | R70: =getStatusCode(I70) -> 200
A71: 45962.691 | C71: Model-based | D71: Surface OA Indicators | E71: Jiang, L., Dunne, J., Carter, B. R., Tjiputra, J. F., Terhaar, J., Sharp, J. D., Olsen, A., Alin, S., Bakker, D. C., Feely, R. A., Gattuso, J., Hogan, P., Ilyina, T., Lange, N., Lauvset, S. K., Lewis, E. R., Lovato, T., Palmieri, J., Santana‐Falcón, Y., Schwinger, J., Séférian, R., Strand, G., Swart, N., Tanhua, T., Tsujino, H., Wanninkhof, R., Watanabe, M., Yamamoto, A., and Ziehn, T.: Global surface ocean acidification indicators from 1750 to 2100, Journal of Advances in Modeling Earth Systems, 15(3), https://doi.org/10.1029/2022ms003563, 2023. | F71: Jiang et al. (2023) | G71: https://doi.org/10.1029/2022MS003563 | H71: https://i.ibb.co/27sB2HLw/jame21817-fig-0008-m.jpg | I71: https://www.ncei.noaa.gov/data/oceans/ncei/ocads/metadata/0259391.html | J71: 1° x 1° | K71: decadal, climatology | L71: 1750 - 2100 | M71: Open ocean, Surface | O71: A model-observation fusion product for all major OA indicators, leveraging a consortium of 14 Earth System Models and 3 observational data products | P71: Jiang et al. (2023) developed a comprehensive model-data fusion product that delineates the trajectory of 10 OA indicators: fCO2, pH, [H+]total, [H+]free [CO32-], Ωarag, Ωcalc, DIC, TA, and RF, as well as temperature and salinity at all locations of the global surface ocean from 1750 to 2100. This product marks a significant breakthrough in OA forecasting by refining temporal trends with data from 14 Earth System Models (ESMs) within CMIP6, and by applying bias and drift corrections from three updated observational ocean carbonate system data products: SOCAT (Version 2022) (Bakker et al., 2016), GLODAPv2.2022 (Lauvset et al., 2022), and CODAP-NA (Jiang et al., 2021). This dataset offers 10-year averages on a 1° × 1° global surface ocean grid, capturing trends from preindustrial times (1750), through historical conditions (1850–2010), and projects future conditions to 2100 across five Shared Socioeconomic Pathways: SSP1-1.9, SSP1-2.6, SSP2-4.5, SSP3-7.0, and SSP5-8.5. | Q71: =getStatusCode(G71) -> 403 | R71: =getStatusCode(I71) -> 200
A72: 45973.939 | B72: jens.terhaar@unibe.ch | C72: Model-based | D72: Simulated and Constrained Southern Ocean Carbon Sink | E72: Terhaar, Jens, Frölicher, T. L., & Joos, F.: Southern Ocean anthropogenic carbon sink constrained by sea surface salinity, Science Advances, 7(18), https://doi.org/10.1126/sciadv.abd5964, 2021. | F72: Terhaar et al. (2021) | G72: https://doi.org/10.1126/sciadv.abd5964 | H72: https://www.seanoe.org/data/00927/103934/illustration.gif | I72: https://www.seanoe.org/data/00927/103938/ | K72: yearly | L72: 1850-2100 | M72: Open ocean, Regional | O72: A constrained estimate of the ocean carbon sink based on the simulated carbon sink from CMIP5 and CMIP6 models and constrained with observations of the ocean physics and carbonate chemistry | P72: These two datasets include spatially-integrated and annually averaged values for the ocean carbon sink from 1850 to 2100 for different scenarios over the 21st century for the global ocean (Terhaar et al., 2022a, 2022b) and the Southern Ocean (Terhaar et al., 2021b, 2021c). All results are based on CMIP5 and CMIP6 models. For the global ocean carbon sink, values are available for SSP1-2.6, SSP2-4.5, and SSP5-8.5. For the Southern Ocean, values are also available for SSP1-2.6, SSP2-4.5, and SSP5-8.5 and additionally also for RCP2.6, RCP4.5, and RCP8.5. In addition, to the raw simulated values, constrained estimates of the annually averaged ocean carbon sink estimates are available. These constrained estimates adjusted the simulated carbon sink estimates for biases on the ocean’s circulation and surface carbonate chemistry (see Terhaar et al., 2021b, 2022a for details). It is recommended to use the constrained estimates. The datasets are available at https://doi.org/10.17882/103934 and https://doi.org/10.17882/103938. | Q72: =getStatusCode(G72) -> 200 | R72: =getStatusCode(I72) -> 200
A73: 45973.939 | B73: jens.terhaar@unibe.ch | C73: Model-based | D73: Simulated and Constrained Global Ocean Carbon Sink | E73: Terhaar, J., Frölicher, T. L., and Joos, F.: Observation-constrained estimates of the Global Ocean Carbon Sink from earth system models, Biogeosciences, 19(18), 4431–4457, https://doi.org/10.5194/bg-19-4431-2022, 2022. | F73: Terhaar et al., (2022) | G73: https://doi.org/10.5194/bg-19-4431-2022 | H73: https://www.seanoe.org/data/00927/103934/illustration.gif | I73: https://www.seanoe.org/data/00927/103934 | K73: yearly | L73: 1850-2100 | M73: Open ocean | O73: A constrained estimate of the ocean carbon sink based on the simulated carbon sink from CMIP5 and CMIP6 models and constrained with observations of the ocean physics and carbonate chemistry | P73: These two datasets include spatially-integrated and annually averaged values for the ocean carbon sink from 1850 to 2100 for different scenarios over the 21st century for the global ocean (Terhaar et al., 2022a, 2022b) and the Southern Ocean (Terhaar et al., 2021b, 2021c). All results are based on CMIP5 and CMIP6 models. For the global ocean carbon sink, values are available for SSP1-2.6, SSP2-4.5, and SSP5-8.5. For the Southern Ocean, values are also available for SSP1-2.6, SSP2-4.5, and SSP5-8.5 and additionally also for RCP2.6, RCP4.5, and RCP8.5. In addition, to the raw simulated values, constrained estimates of the annually averaged ocean carbon sink estimates are available. These constrained estimates adjusted the simulated carbon sink estimates for biases on the ocean’s circulation and surface carbonate chemistry (see Terhaar et al., 2021b, 2022a for details). It is recommended to use the constrained estimates. The datasets are available at https://doi.org/10.17882/103934 and https://doi.org/10.17882/103938. | Q73: =getStatusCode(G73) -> 200 | R73: =getStatusCode(I73) -> 200
A74: 45973.941 | B74: jens.terhaar@unibe.ch | C74: Model-based | D74: Composite model-based estimate of the ocean carbon sink from 1959 to 2022 | E74: Terhaar, J.: Composite model-based estimate of the ocean carbon sink from 1959 to 2022, Biogeosciences, 22, 1631–1649, https://doi.org/10.5194/bg-22-1631-2025, 2025. | F74: Terhaar (2025) | G74: https://doi.org/10.5194/bg-22-1631-2025 | H74: https://upload.wikimedia.org/wikipedia/commons/thumb/9/9c/Ocean_water.jpg/960px-Ocean_water.jpg | I74: https://doi.org/10.5194/bg-22-1631-2025 | K74: yearly | L74: 1959-2022 | M74: Open ocean | O74: A model-based estimate of the ocean carbon sink combining the respective strengths of hindcast simulations and simulations by coupled earth system models | P74: This data product, developed by Terhaar (2025), presents an estimate of the global ocean carbon sink by combining forced hindcast simulations and simulations made by coupled earth system models. Hindcast models manage to adequately simulate the short-term variability of the ocean, but struggle to simulate the long-term climate change trend (Huguenin et al., 2022; Takano et al., 2023; Hollitzer et al., 2024). Earth system models cannot simulate the observed short-term variability by definition, but accurately simulate long-term trends (Takano et al., 2023; Hollitzer et al., 2024). The composite model-based estimate combines the simulated short-term variability from hindcast simulations and the long-term trend from earth system models. The output is supplied with the associated study (https://bg.copernicus.org/articles/22/1631/2025/) (Terhaar, 2025). | Q74: =getStatusCode(G74) -> 200 | R74: =getStatusCode(I74) -> 200
A75: 45974.274 | B75: kunal.c@incois.gov.in | C75: Model-based | D75: pCIBR_Clim and pCIBR_Int | E75: Ghoshal, P.K., Joshi, A. & Chakraborty, K. An improved long-term high-resolution surface pCO2 data product for the Indian Ocean using machine learning. Sci Data 12, 577 (2025). https://doi.org/10.1038/s41597-025-04914-z | F75: Ghoshal et al. (2025) | G75: https://doi.org/10.1038/s41597-025-04914-z | H75: https://i.ibb.co/8DtF8Zz4/p-CIBR-p-CO2-DECADAL.png | I75: https://www.ncei.noaa.gov/data/oceans/ncei/ocads/metadata/0307788.html | J75: 0.083° x 0.083° | K75: monthly | L75: 1980-2019 | M75: Regional | O75: This product uses a hybrid approach, applying machine learning to correct 1/12° ocean–ecosystem model outputs with SOCAT (1984–2019) and SAS (1991–2019) observations for the Indian Ocean. | P75: A machine learning (ML) model is employed to correct biases in surface pCO2 simulations generated by the INCOIS-BIO-ROMS model (pCO2model) over the period 1980–2019. The ML model is trained using the differences between observed (pCO2obs) and modeled pCO2 to estimate the spatio-temporal deviations (pCO2obs − pCO2model). These interannually and climatologically varying deviations are then added back to the original model output, resulting in two improved data products: pCIBR_Int and pCIBR_Clim (Ghoshal et al., 2025). Evaluation against independent datasets, including moored observations (BOBOA), the gridded SOCAT product, and other ML-based pCO2 products (such as CMEMS-LSCEv2 and OceanSODA), demonstrates a significant improvement of approximately 40% ± 3.31% in RMSE compared to the original model. This high-resolution (0.083° × 0.083°), long-term monthly pCO2 data product is available from the INCOIS Portal (https://las.incois.gov.in) and from OCADS: https://www.ncei.noaa.gov/data/oceans/ncei/ocads/metadata/0307788.html (Ghoshal et al., 2025). | Q75: =getStatusCode(G75) -> 200 | R75: =getStatusCode(I75) -> 200
A76: 45974.268 | B76: kunal.c@incois.gov.in | C76: Model-based | D76: INCOIS‐BIO‐ROMS Surface pCO2 and pH | E76: Chakraborty, K., Joshi, A. P., Ghoshal, P. K., Baduru, B., Valsala, V., Sarma, V. V. S. S., et al. (2024). Indian Ocean acidification and its driving mechanisms over the last four decades (1980–2019). Global Biogeochemical Cycles, 38, e2024GB008139. https://doi.org/10.1029/2024GB008139 | F76: Chakraborty et al. (2024) | G76: https://doi.org/10.1029/2024GB008139 | H76: https://i.ibb.co/wFc3f1bY/p-H-DECADAL.png | I76: https://www.ncei.noaa.gov/data/oceans/ncei/ocads/metadata/0307663.html | J76: 0.083° x 0.083° | K76: monthly | L76: 1980-2019 | M76: Regional | O76: INCOIS-BIO-ROMS, developed following the RECCAP-2 Ocean Modeling Protocol, integrates model simulations with field and reconstructed data to enhance understanding of Ocean Acidification in the Indian Ocean. | P76: INCOIS‐BIO‐ROMS Simulated Surface pCO2 and pH for the Indian Ocean: This data product presents a comprehensive assessment of OA trends across the Indian Ocean and its sub-regions from 1980 to 2019, leveraging outputs from a regional, high-resolution coupled ocean-ecosystem model (INCOIS-BIO-ROMS), an offline biogeochemical (BGC) model, and two machine learning-based products (Chakraborty et al., 2024). INCOIS-BIO-ROMS, configured at 1/12° resolution for the Indian Ocean, was developed in accordance with the “RECCAP-2: Ocean Modeling Protocol” for regional oceans. The INCOIS‐BIO‐ROMS simulated surface pCO2 and pH data product is available from the INCOIS Portal (https://las.incois.gov.in) and from OCADS: https://www.ncei.noaa.gov/data/oceans/ncei/ocads/metadata/0307663.html (Chakraborty et al., 2025). | Q76: =getStatusCode(G76) -> 403 | R76: =getStatusCode(I76) -> 200
A77: 45973.797 | B77: tdevries@geog.ucsb.edu | C77: Model-based | D77: Ocean Circulation Inverse Model (OCIM2-48L) | E77: DeVries, T. (2022). Atmospheric CO2 and sea surface temperature variability cannot explain recent decadal variability of the ocean CO2 sink. Geophysical Research Letters, 49(7), e2021GL096018. | F77: DeVries (2022b) | G77: https://doi.org/10.1029/2021GL096018 | H77: https://i.ibb.co/Xxbcrf2b/Screenshot-2025-11-14-at-08-56-35.png | I77: https://figshare.com/articles/dataset/OCIM2-48L_abiotic_ocean_carbon_cycle_model_output/19341974 | J77: 2° x 2° | K77: yearly | L77: 1780-2020 | M77: Open ocean | O77: Data-constrained estimate of anthropogenic CO2 accumulation in the ocean from inverting physical ocean circulation tracers | P77: Data-constrained estimate of anthropogenic CO2 accumulation in the ocean from inverting physical ocean circulation tracers | Q77: =getStatusCode(G77) -> 403 | R77: =getStatusCode(I77) -> 200

Sheet web_formatted
A1: 0 | B1: Data category | C1: Product name | D1: Citation | E1: Image URL | F1: fa-solid fa-globe | G1: Spatial domains | H1: Spatial domain | I1: fa-solid fa-hourglass-start | J1: Temporal resolution | K1: Temporal resolution | L1: fa-solid fa-ruler-horizontal | M1: Spatial resolution | N1: Spatial resolution | O1: fa-solid fa-calendar-days | P1: Period | Q1: Period | R1: Highlights | S1: Citation | T1: Citation DOI | U1: Data access link | V1: Description | W1: Description | X1: Reference | Y1: Reference
A2: 1 | B2: data-category | C2: card-title | D2: card-subheading | E2: card-image | F2: card-attribute.icon | G2: card-attribute.label | H2: card-attribute.value | I2: card-attribute.icon | J2: card-attribute.label | K2: card-attribute.value | L2: card-attribute.icon | M2: card-attribute.label | N2: card-attribute.value | O2: card-attribute.icon | P2: card-attribute.label | Q2: card-attribute.value | R2: card-summary | S2: card-citation | T2: card-citation-link | U2: card-data-access | V2: card-detail.title | W2: card-detail.content | X2: card-detail.title | Y2: card-detail.content
A3: =A2+1 -> 2 | B3: =HLOOKUP(B$1,google_form!$1:$216,$A3,FALSE) -> Data compilations | C3: =HLOOKUP(C$1,google_form!$1:$216,$A3,FALSE) -> SOCAT | D3: =HLOOKUP(D$1,google_form!$1:$216,$A3,FALSE) -> Bakker et al. (2016) | E3: =HLOOKUP(E$1,google_form!$1:$216,$A3,FALSE) -> https://socat.info/wp-content/uploads/2017/06/cropped-socat_cat.png | F3: =if(ISBLANK($C3), "", F$1) -> fa-solid fa-globe | G3: =if(ISBLANK($C3), "", G$1) -> Spatial domains | H3: =HLOOKUP(H$1,google_form!$1:$196,$A3,FALSE) -> Open ocean, Coastal ocean, Surface | I3: =if(ISBLANK($C3), "", I$1) -> fa-solid fa-hourglass-start | J3: =if(ISBLANK($C3), "", J$1) -> Temporal resolution | K3: =HLOOKUP(K$1,google_form!$1:$196,$A3,FALSE) -> continuous | L3: =if(ISBLANK($C3), "", L$1) -> fa-solid fa-ruler-horizontal | M3: =if(ISBLANK($C3), "", M$1) -> Spatial resolution | N3: =HLOOKUP(N$1,google_form!$1:$196,$A3,FALSE) | O3: =if(ISBLANK($C3), "", O$1) -> fa-solid fa-calendar-days | P3: =if(ISBLANK($C3), "", P$1) -> Period | Q3: =HLOOKUP(Q$1,google_form!$1:$196,$A3,FALSE) -> 1957 - 2025 | R3: =HLOOKUP(R$1,google_form!$1:$196,$A3,FALSE) -> The largest collection of surface ocean carbon observations | S3: =HLOOKUP(S$1,google_form!$1:$196,$A3,FALSE) -> Bakker et al. (2016) | T3: =HLOOKUP(T$1,google_form!$1:$196,$A3,FALSE) -> https://doi.org/10.5194/essd-8-383-2016 | U3: =HLOOKUP(U$1,google_form!$1:$196,$A3,FALSE) -> https://socat.info/ | V3: =if(ISBLANK($C3), "", V$1) -> Description | W3: =HLOOKUP(W$1,google_form!$1:$196,$A3,FALSE) -> The Surface Ocean CO2 Atlas features surface fCO2 measurements from both the open ocean and the coastal ocean, predominantly sourced from research vessels, ships of opportunity, and autonomous platforms including fixed moorings and uncrewed surface vehicles (USVs) (Bakker et al., 2016). It represents the most extensive collection of observational ocean CO2 data for the global surface ocean. Since 2013, SOCAT has been updated annually. Dataset flags indicate the estimated uncertainty and completeness of metadata in SOCAT synthesis products. The SOCAT gridded product contains fCO2 values with an estimated uncertainty of less than 5 µatm. | X3: =if(ISBLANK($C3), "", X$1) -> Reference | Y3: =HLOOKUP(Y$1,google_form!$1:$196,$A3,FALSE) -> Bakker, D. C. E., Pfeil, B., Landa, C. S., Metzl, N., O'Brien, K. M., Olsen, A., Smith, K., Cosca, C., Harasawa, S., Jones, S. D., Nakaoka, S., Nojiri, Y., Schuster, U., Steinhoff, T., Sweeney, C., Takahashi, T., Tilbrook, B., Wada, C., Wanninkhof, R., Alin, S. R., Balestrini, C. F., Barbero, L., Bates, N. R., Bianchi, A. A., Bonou, F., Boutin, J., Bozec, Y., Burger, E. F., Cai, W.-J., Castle, R. D., Chen, L., Chierici, M., Currie, K., Evans, W., Featherstone, C., Feely, R. A., Fransson, A., Goyet, C., Greenwood, N., Gregor, L., Hankin, S., Hardman-Mountford, N. J., Harlay, J., Hauck, J., Hoppema, M., Humphreys, M. P., Hunt, C. W., Huss, B., Ibánhez, J. S. P., Johannessen, T., Keeling, R., Kitidis, V., Körtzinger, A., Kozyr, A., Krasakopoulou, E., Kuwata, A., Landschützer, P., Lauvset, S. K., Lefèvre, N., Lo Monaco, C., Manke, A., Mathis, J. T., Merlivat, L., Millero, F. J., Monteiro, P. M. S., Munro, D. R., Murata, A., Newberger, T., Omar, A. M., Ono, T., Paterson, K., Pearce, D., Pierrot, D., Robbins, L. L., Saito, S., Salisbury, J., Schlitzer, R., Schneider, B., Schweitzer, R., Sieger, R., Skjelvan, I., Sullivan, K. F., Sutherland, S. C., Sutton, A. J., Tadokoro, K., Telszewski, M., Tuma, M., van Heuven, S. M. A. C., Vandemark, D., Ward, B., Watson, A. J., and Xu, S. (2016). A multi-decade record of high-quality fCO2 data in version 3 of the Surface Ocean CO2 Atlas (SOCAT), Earth Syst. Sci. Data, 8, 383–413, https://doi.org/10.5194/essd-8-383-2016.
A4: =A3+1 -> 3 | B4: =HLOOKUP(B$1,google_form!$1:$216,$A4,FALSE) -> Data compilations | C4: =HLOOKUP(C$1,google_form!$1:$216,$A4,FALSE) -> LDEO Surface pCO2 Database | D4: =HLOOKUP(D$1,google_form!$1:$216,$A4,FALSE) -> Takahashi et a. (2009) | E4: =HLOOKUP(E$1,google_form!$1:$216,$A4,FALSE) -> https://www.ncei.noaa.gov/access/ocean-carbon-acidification-data-system/oceans/LDEO_Underway_Database/LDEOv2019_map.jpg | F4: =if(ISBLANK($C4), "", F$1) -> fa-solid fa-globe | G4: =if(ISBLANK($C4), "", G$1) -> Spatial domains | H4: =HLOOKUP(H$1,google_form!$1:$196,$A4,FALSE) -> Open ocean, Surface | I4: =if(ISBLANK($C4), "", I$1) -> fa-solid fa-hourglass-start | J4: =if(ISBLANK($C4), "", J$1) -> Temporal resolution | K4: =HLOOKUP(K$1,google_form!$1:$196,$A4,FALSE) -> continuous | L4: =if(ISBLANK($C4), "", L$1) -> fa-solid fa-ruler-horizontal | M4: =if(ISBLANK($C4), "", M$1) -> Spatial resolution | N4: =HLOOKUP(N$1,google_form!$1:$196,$A4,FALSE) | O4: =if(ISBLANK($C4), "", O$1) -> fa-solid fa-calendar-days | P4: =if(ISBLANK($C4), "", P$1) -> Period | Q4: =HLOOKUP(Q$1,google_form!$1:$196,$A4,FALSE) | R4: =HLOOKUP(R$1,google_form!$1:$196,$A4,FALSE) -> The LDEO database reports pCO2 exclusively from equilibrator-CO2 analyzer systems | S4: =HLOOKUP(S$1,google_form!$1:$196,$A4,FALSE) -> Takahashi et a. (2009) | T4: =HLOOKUP(T$1,google_form!$1:$196,$A4,FALSE) -> https://doi.org/10.1016/j.dsr2.2008.12.009 | U4: =HLOOKUP(U$1,google_form!$1:$196,$A4,FALSE) -> https://www.ncei.noaa.gov/data/oceans/ncei/ocads/metadata/0160492.html | V4: =if(ISBLANK($C4), "", V$1) -> Description | W4: =HLOOKUP(W$1,google_form!$1:$196,$A4,FALSE) -> Dr. Taro Takahashi [LDEO, Palisades, New York] started synthesizing global surface ocean CO2 data in 1997, compiling three decades of observations (~250,000 measurements) to create inaugural monthly global surface pCO2 maps (Takahashi et al., 1997; Takahashi et al., 2002). The most recent version (V2019) expanded this dataset to approximately 14.2 million surface water pCO2 measurements spanning from 1957–2019. Distinct from the SOCAT database, the LDEO database reports pCO2, instead of fCO2, exclusively from equilibrator-CO2 analyzer systems, with an average estimated uncertainty of ± 2.5 µatm. The database is also interpolated onto a global surface ocean 4° × 5° grid for a reference year 2000 (Takahashi et al., 2009) and 2010 (Fay et al., 2024). | X4: =if(ISBLANK($C4), "", X$1) -> Reference | Y4: =HLOOKUP(Y$1,google_form!$1:$196,$A4,FALSE) -> Takahashi, T., Sutherland, S. C., Wanninkhof, R., Sweeney, C., Feely, R. A., Chipman, D. W., Hales, B., Friederich, G., Chavez, F., Sabine, C., Watson, A., Bakker, D. C. E., Schuster, U., Metzl, N., Yoshikawa-Inoue, H., Ishii, M., Midorikawa, T., Nojiri, Y., Körtzinger, A., Steinhoff, T., and de Baar, H. J. W.: Climatological mean and decadal change in Surface Ocean pCO2, and net sea–air CO2 flux over the Global Oceans, Deep Sea Research Part II: Topical Studies in Oceanography, 56(8–10), 554–577, https://doi.org/10.1016/j.dsr2.2008.12.009, 2009.
A5: =A4+1 -> 4 | B5: =HLOOKUP(B$1,google_form!$1:$216,$A5,FALSE) -> Data compilations | C5: =HLOOKUP(C$1,google_form!$1:$216,$A5,FALSE) -> GLODAPv2 | D5: =HLOOKUP(D$1,google_form!$1:$216,$A5,FALSE) -> Lauvset et al. (2024) | E5: =HLOOKUP(E$1,google_form!$1:$216,$A5,FALSE) -> https://glodap.info/wp-content/uploads/2017/09/cropped-glodap_logo_trans.png | F5: =if(ISBLANK($C5), "", F$1) -> fa-solid fa-globe | G5: =if(ISBLANK($C5), "", G$1) -> Spatial domains | H5: =HLOOKUP(H$1,google_form!$1:$196,$A5,FALSE) -> Open ocean, Water column | I5: =if(ISBLANK($C5), "", I$1) -> fa-solid fa-hourglass-start | J5: =if(ISBLANK($C5), "", J$1) -> Temporal resolution | K5: =HLOOKUP(K$1,google_form!$1:$196,$A5,FALSE) -> discrete | L5: =if(ISBLANK($C5), "", L$1) -> fa-solid fa-ruler-horizontal | M5: =if(ISBLANK($C5), "", M$1) -> Spatial resolution | N5: =HLOOKUP(N$1,google_form!$1:$196,$A5,FALSE) | O5: =if(ISBLANK($C5), "", O$1) -> fa-solid fa-calendar-days | P5: =if(ISBLANK($C5), "", P$1) -> Period | Q5: =HLOOKUP(Q$1,google_form!$1:$196,$A5,FALSE) -> 1960 - 2024 | R5: =HLOOKUP(R$1,google_form!$1:$196,$A5,FALSE) -> Adjustments are applied by comparing data in the deep ocean (>2000 m) using a crossover and inversion method as described by Johnson et al. (2001). | S5: =HLOOKUP(S$1,google_form!$1:$196,$A5,FALSE) -> Lauvset et al. (2024) | T5: =HLOOKUP(T$1,google_form!$1:$196,$A5,FALSE) -> https://doi.org/10.5194/essd-16-2047-2024 | U5: =HLOOKUP(U$1,google_form!$1:$196,$A5,FALSE) -> https://glodap.info/ | V5: =if(ISBLANK($C5), "", V$1) -> Description | W5: =HLOOKUP(W$1,google_form!$1:$196,$A5,FALSE) -> The Global Ocean Data Analysis Project Version 2 (GLODAPv2) aggregates biogeochemical data collected from discrete bottle samples, offering extensive global coverage from the surface to depths (Key et al., 2015; Olsen et al., 2016; Lauvset et al., 2024). While GLODAP is primarily a product for basin-scale hydrographic data, it also includes coastal datasets and observations from a few time-series. The GLODAPv2 data product provides rigorously quality-controlled measurements for 14 essential oceanographic variables: temperature, salinity, dissolved oxygen (DO), nitrate, silicate, phosphate, DIC, TA, pH, chlorofluorocarbons (CFC-11, CFC-12, CFC-113), carbon tetrachloride (CCl4), and sulfur hexafluoride (SF6). These variables, excluding temperature, undergo both primary and secondary quality control procedures to detect outliers and adjust for significant measurement biases. GLODAPv2 was first published in 2016 and was updated annually through a living data process in Earth System Science Data from 2019 through “v2023,” which was published in 2024. For these updates, new data (including historical data not previously included in the data product) are quality controlled and adjusted to the 2016 version (Olsen et al., 2019; Olsen et al., 2020; Lauvset et al., 2021; Lauvset et al., 2022; Lauvset et al., 2024). Since the global repeat hydrography programs operate with decadal repetitions, the aim is to produce a completely new version of GLODAP, where all cruise datasets will be reevaluated, every decade. Release of the GLODAPv3 data product is planned for 2026, and is expected to evolve the secondary data quality control practices relative to those used in GLODAPv2. For more information on the secondary quality control process, refer to Tanhua et al. (2010) and Lauvset and Tanhua (2015). GLODAPv2 offers two kind of products: the collection of quality controlled data from discrete bottle samples taken at sampling location (Key et al., 2015; Olsen et al., 2016; Olsen et al., 2019; Olsen et al., 2020; Lauvset et al., 2021; Lauvset et al., 2022; Lauvset et al., 2024), and a gridded product, interpolated to a 1° × 1° grid and the 33 standard depth levels of World Ocean Atlas (WOA) (Lauvset et al., 2016). | X5: =if(ISBLANK($C5), "", X$1) -> Reference | Y5: =HLOOKUP(Y$1,google_form!$1:$196,$A5,FALSE) -> Lauvset, S. K., Lange, N., Tanhua, T., Bittig, H. C., Olsen, A., Kozyr, A., Álvarez, M., Azetsu-Scott, K., Brown, P. J., Carter, B. R., Cotrim da Cunha, L., Hoppema, M., Humphreys, M. P., Ishii, M., Jeansson, E., Murata, A., Müller, J. D., Pérez, F. F., Schirnick, C., Steinfeldt, R., Suzuki, T., Ulfsbo, A., Velo, A., Woosley, R. J., and Key, R. M.: The annual update GLODAPv2.2023: the global interior ocean biogeochemical data product, Earth Syst. Sci. Data, 16, 2047–2072, https://doi.org/10.5194/essd-16-2047-2024, 2024
A6: =A5+1 -> 5 | B6: =HLOOKUP(B$1,google_form!$1:$216,$A6,FALSE) -> Data compilations | C6: =HLOOKUP(C$1,google_form!$1:$216,$A6,FALSE) -> Quality Edited Hydrographic Data | D6: =HLOOKUP(D$1,google_form!$1:$216,$A6,FALSE) -> Swift et al. (2026) | E6: =HLOOKUP(E$1,google_form!$1:$216,$A6,FALSE) -> https://i.ibb.co/Q7YZfHK2/Swift-Vertical-Section-Map.png | F6: =if(ISBLANK($C6), "", F$1) -> fa-solid fa-globe | G6: =if(ISBLANK($C6), "", G$1) -> Spatial domains | H6: =HLOOKUP(H$1,google_form!$1:$196,$A6,FALSE) -> Open ocean, Water column | I6: =if(ISBLANK($C6), "", I$1) -> fa-solid fa-hourglass-start | J6: =if(ISBLANK($C6), "", J$1) -> Temporal resolution | K6: =HLOOKUP(K$1,google_form!$1:$196,$A6,FALSE) -> irregular | L6: =if(ISBLANK($C6), "", L$1) -> fa-solid fa-ruler-horizontal | M6: =if(ISBLANK($C6), "", M$1) -> Spatial resolution | N6: =HLOOKUP(N$1,google_form!$1:$196,$A6,FALSE) | O6: =if(ISBLANK($C6), "", O$1) -> fa-solid fa-calendar-days | P6: =if(ISBLANK($C6), "", P$1) -> Period | Q6: =HLOOKUP(Q$1,google_form!$1:$196,$A6,FALSE) -> 1967-2025 | R6: =HLOOKUP(R$1,google_form!$1:$196,$A6,FALSE) -> Similar to GLODAPv2, with no adjustments | S6: =HLOOKUP(S$1,google_form!$1:$196,$A6,FALSE) -> Swift et al. (2026) | T6: =HLOOKUP(T$1,google_form!$1:$196,$A6,FALSE) -> n/a | U6: =HLOOKUP(U$1,google_form!$1:$196,$A6,FALSE) -> https://joa.ucsd.edu/Data_homepage | V6: =if(ISBLANK($C6), "", V$1) -> Description | W6: =HLOOKUP(W$1,google_form!$1:$196,$A6,FALSE) -> Similar to GLODAPv2, with no adjustments | X6: =if(ISBLANK($C6), "", X$1) -> Reference | Y6: =HLOOKUP(Y$1,google_form!$1:$196,$A6,FALSE) -> Swift, James H. and Barna, A. (2026). Quality Edited Vertical Ocean Section and Gridded Hydrographic Data. UC San Diego Library Digital Collections. Dataset. https://doi.org/10.6075/J0K074P0
A7: =A6+1 -> 6 | B7: =HLOOKUP(B$1,google_form!$1:$216,$A7,FALSE) -> Data compilations | C7: =HLOOKUP(C$1,google_form!$1:$216,$A7,FALSE) -> World Ocean Database | D7: =HLOOKUP(D$1,google_form!$1:$216,$A7,FALSE) -> Mishonov et al. (2024) | E7: =HLOOKUP(E$1,google_form!$1:$216,$A7,FALSE) -> https://www.ncei.noaa.gov/sites/g/files/anmtlf171/files/inline-images/World%20Ocean%20Atlas%202023%20Climatology%2C%20Decade%202015-2022.png | F7: =if(ISBLANK($C7), "", F$1) -> fa-solid fa-globe | G7: =if(ISBLANK($C7), "", G$1) -> Spatial domains | H7: =HLOOKUP(H$1,google_form!$1:$196,$A7,FALSE) -> Open ocean, Water column | I7: =if(ISBLANK($C7), "", I$1) -> fa-solid fa-hourglass-start | J7: =if(ISBLANK($C7), "", J$1) -> Temporal resolution | K7: =HLOOKUP(K$1,google_form!$1:$196,$A7,FALSE) -> discrete | L7: =if(ISBLANK($C7), "", L$1) -> fa-solid fa-ruler-horizontal | M7: =if(ISBLANK($C7), "", M$1) -> Spatial resolution | N7: =HLOOKUP(N$1,google_form!$1:$196,$A7,FALSE) | O7: =if(ISBLANK($C7), "", O$1) -> fa-solid fa-calendar-days | P7: =if(ISBLANK($C7), "", P$1) -> Period | Q7: =HLOOKUP(Q$1,google_form!$1:$196,$A7,FALSE) | R7: =HLOOKUP(R$1,google_form!$1:$196,$A7,FALSE) -> Similar to GLODAPv2, with no adjustments | S7: =HLOOKUP(S$1,google_form!$1:$196,$A7,FALSE) -> Mishonov et al. (2024) | T7: =HLOOKUP(T$1,google_form!$1:$196,$A7,FALSE) -> https://doi.org/10.25923/z885-h264 | U7: =HLOOKUP(U$1,google_form!$1:$196,$A7,FALSE) -> https://www.ncei.noaa.gov/products/world-ocean-database | V7: =if(ISBLANK($C7), "", V$1) -> Description | W7: =HLOOKUP(W$1,google_form!$1:$196,$A7,FALSE) -> In addition to the GLODAPv2 and JOA Suite, users can also access historical and recent original biogeochemical data collected from discrete bottle samples in a uniform format and units, along with their originator quality control (QC) flags, through the World Ocean Database (WOD) (Mishonov et al., 2024). Like the JOA Suite, these measured data remain unaltered. The WOD allows users to filter and subset data with specific variables, platforms, institutions, projects, regions, or time periods (Garcia et al., 2024). Users can visualize sampling locations on a “distribution plot” and access a cruise list for all selected data and variables. Users also have the option of exporting data in NetCDF or Comma-Separated Values (CSV) formats. Additionally, all data in the WOD are reproducible and traceable to their original data sources archived at NOAA’s National Centers for Environmental Information (NCEI). | X7: =if(ISBLANK($C7), "", X$1) -> Reference | Y7: =HLOOKUP(Y$1,google_form!$1:$196,$A7,FALSE) -> Mishonov, A. V., Boyer, T. P., Baranova, O. K., Bouchard, C. N., Cross, S. L., Garcia H. E., Locarnini, R. A., Paver, C. R., Wang, Z., Seidov, D., Grodsky, A. I., Beauchamp, J. G.: World Ocean Database 2023, C. Bouchard, Technical Ed., NOAA Atlas NESDIS 97, 206 pp., https://doi.org/10.25923/z885-h264, 2024.
A8: =A7+1 -> 7 | B8: =HLOOKUP(B$1,google_form!$1:$216,$A8,FALSE) -> Data compilations | C8: =HLOOKUP(C$1,google_form!$1:$216,$A8,FALSE) -> SNAPO-CO2 | D8: =HLOOKUP(D$1,google_form!$1:$216,$A8,FALSE) -> Metzl et al (2024) | E8: =HLOOKUP(E$1,google_form!$1:$216,$A8,FALSE) -> https://www.seanoe.org/data/00911/102337/illustration.gif | F8: =if(ISBLANK($C8), "", F$1) -> fa-solid fa-globe | G8: =if(ISBLANK($C8), "", G$1) -> Spatial domains | H8: =HLOOKUP(H$1,google_form!$1:$196,$A8,FALSE) -> Open ocean, Coastal ocean, Surface, Water column | I8: =if(ISBLANK($C8), "", I$1) -> fa-solid fa-hourglass-start | J8: =if(ISBLANK($C8), "", J$1) -> Temporal resolution | K8: =HLOOKUP(K$1,google_form!$1:$196,$A8,FALSE) -> discrete | L8: =if(ISBLANK($C8), "", L$1) -> fa-solid fa-ruler-horizontal | M8: =if(ISBLANK($C8), "", M$1) -> Spatial resolution | N8: =HLOOKUP(N$1,google_form!$1:$196,$A8,FALSE) | O8: =if(ISBLANK($C8), "", O$1) -> fa-solid fa-calendar-days | P8: =if(ISBLANK($C8), "", P$1) -> Period | Q8: =HLOOKUP(Q$1,google_form!$1:$196,$A8,FALSE) -> 1993-2022 | R8: =HLOOKUP(R$1,google_form!$1:$196,$A8,FALSE) -> A compilation of cruises from multiple French initiatives | S8: =HLOOKUP(S$1,google_form!$1:$196,$A8,FALSE) -> Metzl et al (2024) | T8: =HLOOKUP(T$1,google_form!$1:$196,$A8,FALSE) -> https://doi.org/10.5194/essd-16-89-2024 | U8: =HLOOKUP(U$1,google_form!$1:$196,$A8,FALSE) -> https://doi.org/10.17882/102337 | V8: =if(ISBLANK($C8), "", V$1) -> Description | W8: =HLOOKUP(W$1,google_form!$1:$196,$A8,FALSE) -> Synthesis of 44,400 measurements of DIC and TA from a series of research cruises and ships of opportunity across various oceanic regions from 1993-2022, from several French research programs, to create a product called “Service National d’Analyse des Paramètres Océaniques du CO2 (SNAPO-CO2)”. | X8: =if(ISBLANK($C8), "", X$1) -> Reference | Y8: =HLOOKUP(Y$1,google_form!$1:$196,$A8,FALSE) -> Metzl, N., Fin, J., Lo Monaco, C., Mignon, C., Alliouane, S., Antoine, D., Bourdin, G., Boutin, J., Bozec, Y., Conan, P., Coppola, L., Diaz, F., Douville, E., Durrieu de Madron, X., Gattuso, J.-P., Gazeau, F., Golbol, M., Lansard, B., Lefèvre, D., Lefèvre, N., Lombard, F., Louanchi, F., Merlivat, L., Olivier, L., Petrenko, A., Petton, S., Pujo-Pay, M., Rabouille, C., Reverdin, G., Ridame, C., Tribollet, A., Vellucci, V., Wagener, T., and Wimart-Rousseau, C.: A synthesis of ocean total alkalinity and dissolved inorganic carbon measurements from 1993 to 2022: the SNAPO-CO2-v1 dataset, Earth Syst. Sci. Data, 16, 89–120, https://doi.org/10.5194/essd-16-89-2024, 2024.
A9: =A8+1 -> 8 | B9: =HLOOKUP(B$1,google_form!$1:$216,$A9,FALSE) -> Data compilations | C9: =HLOOKUP(C$1,google_form!$1:$216,$A9,FALSE) -> CODAP-NA | D9: =HLOOKUP(D$1,google_form!$1:$216,$A9,FALSE) -> Jiang et al. (2021) | E9: =HLOOKUP(E$1,google_form!$1:$216,$A9,FALSE) -> https://essd.copernicus.org/articles/13/2777/2021/essd-13-2777-2021-f01-web.png | F9: =if(ISBLANK($C9), "", F$1) -> fa-solid fa-globe | G9: =if(ISBLANK($C9), "", G$1) -> Spatial domains | H9: =HLOOKUP(H$1,google_form!$1:$196,$A9,FALSE) -> Coastal ocean, Water column | I9: =if(ISBLANK($C9), "", I$1) -> fa-solid fa-hourglass-start | J9: =if(ISBLANK($C9), "", J$1) -> Temporal resolution | K9: =HLOOKUP(K$1,google_form!$1:$196,$A9,FALSE) -> discrete | L9: =if(ISBLANK($C9), "", L$1) -> fa-solid fa-ruler-horizontal | M9: =if(ISBLANK($C9), "", M$1) -> Spatial resolution | N9: =HLOOKUP(N$1,google_form!$1:$196,$A9,FALSE) | O9: =if(ISBLANK($C9), "", O$1) -> fa-solid fa-calendar-days | P9: =if(ISBLANK($C9), "", P$1) -> Period | Q9: =HLOOKUP(Q$1,google_form!$1:$196,$A9,FALSE) -> 2003 - 2018 | R9: =HLOOKUP(R$1,google_form!$1:$196,$A9,FALSE) -> A discrete bottle based data product similar to GLODAPv2, but for the North American coastal ocean | S9: =HLOOKUP(S$1,google_form!$1:$196,$A9,FALSE) -> Jiang et al. (2021) | T9: =HLOOKUP(T$1,google_form!$1:$196,$A9,FALSE) -> https://doi.org/10.5194/essd-13-2777-2021 | U9: =HLOOKUP(U$1,google_form!$1:$196,$A9,FALSE) -> https://www.ncei.noaa.gov/data/oceans/ncei/ocads/metadata/0219960.html | V9: =if(ISBLANK($C9), "", V$1) -> Description | W9: =HLOOKUP(W$1,google_form!$1:$196,$A9,FALSE) -> Jiang et al. (2021) synthesized two decades of discrete measurements of carbonate system variables, DO, and nutrient data from the North American continental shelves to generate the first version of Coastal Ocean Data Analysis Data Product in North America (CODAP-NA). The 2021 release encompasses 3,391 oceanographic profiles from 61 research cruises spanning the North American continental shelves from Alaska to Mexico in the west and from Canada to the Caribbean in the east. It includes 14 key variables, including temperature, salinity, DO, DIC, TA, pH, carbonate ion, fCO2, silicate, phosphate, nitrate. | X9: =if(ISBLANK($C9), "", X$1) -> Reference | Y9: =HLOOKUP(Y$1,google_form!$1:$196,$A9,FALSE) -> Jiang, L.-Q., Feely, R. A., Wanninkhof, R., Greeley, D., Barbero, L., Alin, S., Carter, B. R., Pierrot, D., Featherstone, C., Hooper, J., Melrose, C., Monacci, N., Sharp, J. D., Shellito, S., Xu, Y.-Y., Kozyr, A., Byrne, R. H., Cai, W.-J., Cross, J., Johnson, G. C., Hales, B., Langdon, C., Mathis, J., Salisbury, J., and Townsend, D. W.: Coastal Ocean Data Analysis Product in North America (CODAP-NA) – an internally consistent data product for discrete inorganic carbon, oxygen, and nutrients on the North American ocean margins, Earth Syst. Sci. Data, 13, 2777–2799, https://doi.org/10.5194/essd-13-2777-2021, 2021.
A10: 9 | B10: =HLOOKUP(B$1,google_form!$1:$216,$A10,FALSE) -> Data compilations | C10: =HLOOKUP(C$1,google_form!$1:$216,$A10,FALSE) -> AZMP Carbon | D10: =HLOOKUP(D$1,google_form!$1:$216,$A10,FALSE) -> Gibb et al. (2023) | E10: =HLOOKUP(E$1,google_form!$1:$216,$A10,FALSE) -> https://essd.copernicus.org/articles/15/4127/2023/essd-15-4127-2023-avatar-web.png | F10: =if(ISBLANK($C10), "", F$1) -> fa-solid fa-globe | G10: =if(ISBLANK($C10), "", G$1) -> Spatial domains | H10: =HLOOKUP(H$1,google_form!$1:$196,$A10,FALSE) -> Coastal ocean, Water column | I10: =if(ISBLANK($C10), "", I$1) -> fa-solid fa-hourglass-start | J10: =if(ISBLANK($C10), "", J$1) -> Temporal resolution | K10: =HLOOKUP(K$1,google_form!$1:$196,$A10,FALSE) -> irregular | L10: =if(ISBLANK($C10), "", L$1) -> fa-solid fa-ruler-horizontal | M10: =if(ISBLANK($C10), "", M$1) -> Spatial resolution | N10: =HLOOKUP(N$1,google_form!$1:$196,$A10,FALSE) | O10: =if(ISBLANK($C10), "", O$1) -> fa-solid fa-calendar-days | P10: =if(ISBLANK($C10), "", P$1) -> Period | Q10: =HLOOKUP(Q$1,google_form!$1:$196,$A10,FALSE) | R10: =HLOOKUP(R$1,google_form!$1:$196,$A10,FALSE) -> A compilation of cruises from the Atlantic Zone Monitoring Program (AZMP) since 2014 | S10: =HLOOKUP(S$1,google_form!$1:$196,$A10,FALSE) -> Gibb et al. (2023) | T10: =HLOOKUP(T$1,google_form!$1:$196,$A10,FALSE) -> https://doi.org/10.5194/essd-15-4127-2023 | U10: =HLOOKUP(U$1,google_form!$1:$196,$A10,FALSE) -> https://doi.org/10.20383/102.0673 | V10: =if(ISBLANK($C10), "", V$1) -> Description | W10: =HLOOKUP(W$1,google_form!$1:$196,$A10,FALSE) -> Gibb et al. (2023) compiled ocean carbonate system variables data from the Canadian Atlantic Zone Monitoring Program (AZMP Carbon) since 2014. More than 100 seagoing missions are represented in this dataset. The sampling strategy generally corresponds to full-depth water samples mostly collected along standardized hydrographic sections. Implemented in 1998, the AZMP aims to characterize and understand the causes of oceanic variability at the seasonal, interannual and decadal scales in support of, among other things, fisheries management in the Atlantic Zone (including the Gulf of St. Lawrence, the Scotian shelf and the Newfoundland and Labrador shelf). Since 2014, a minimum of two of the three following carbonate system variables, DIC, TA, and pH, are also acquired by the program at standardized hydrographic stations across the zone (sampled up to three times a year). Each measurement is completed with corresponding temperature, salinity and, when available, nutrients and DO concentration data. | X10: =if(ISBLANK($C10), "", X$1) -> Reference | Y10: =HLOOKUP(Y$1,google_form!$1:$196,$A10,FALSE) -> Gibb, O., Cyr, F., Azetsu-Scott, K., Chassé, J., Childs, D., Gabriel, C.-E., Galbraith, P. S., Maillet, G., Pepin, P., Punshon, S., and Starr, M.: Spatiotemporal variability in pH and carbonate parameters on the Canadian Atlantic continental shelf between 2014 and 2022, Earth Syst. Sci. Data, 15, 4127–4162, https://doi.org/10.5194/essd-15-4127-2023, 2023.
A11: 10 | B11: =HLOOKUP(B$1,google_form!$1:$216,$A11,FALSE) -> Data compilations | C11: =HLOOKUP(C$1,google_form!$1:$216,$A11,FALSE) -> MOCHA | D11: =HLOOKUP(D$1,google_form!$1:$216,$A11,FALSE) -> Kennedy et al., 2023 | E11: =HLOOKUP(E$1,google_form!$1:$216,$A11,FALSE) -> https://i.ibb.co/XrpxsXPX/data-locs-composite-bs.png | F11: =if(ISBLANK($C11), "", F$1) -> fa-solid fa-globe | G11: =if(ISBLANK($C11), "", G$1) -> Spatial domains | H11: =HLOOKUP(H$1,google_form!$1:$196,$A11,FALSE) -> Regional, Coastal ocean, Surface, Water column | I11: =if(ISBLANK($C11), "", I$1) -> fa-solid fa-hourglass-start | J11: =if(ISBLANK($C11), "", J$1) -> Temporal resolution | K11: =HLOOKUP(K$1,google_form!$1:$196,$A11,FALSE) -> irregular, daily | L11: =if(ISBLANK($C11), "", L$1) -> fa-solid fa-ruler-horizontal | M11: =if(ISBLANK($C11), "", M$1) -> Spatial resolution | N11: =HLOOKUP(N$1,google_form!$1:$196,$A11,FALSE) | O11: =if(ISBLANK($C11), "", O$1) -> fa-solid fa-calendar-days | P11: =if(ISBLANK($C11), "", P$1) -> Period | Q11: =HLOOKUP(Q$1,google_form!$1:$196,$A11,FALSE) -> 1949-2022 | R11: =HLOOKUP(R$1,google_form!$1:$196,$A11,FALSE) -> A compilation of cruises, autonomous sensors, and shore observations for the U.S. West Coast. | S11: =HLOOKUP(S$1,google_form!$1:$196,$A11,FALSE) -> Kennedy et al., 2023 | T11: =HLOOKUP(T$1,google_form!$1:$196,$A11,FALSE) -> https://doi.org/10.25921/2vve-fh39 | U11: =HLOOKUP(U$1,google_form!$1:$196,$A11,FALSE) -> https://www.ncei.noaa.gov/access/metadata/landing-page/bin/iso?id=gov.noaa.nodc:0277984 | V11: =if(ISBLANK($C11), "", V$1) -> Description | W11: =HLOOKUP(W$1,google_form!$1:$196,$A11,FALSE) -> MOCHA compiles temperature, salinity, DO, ocean carbonate system variables (DIC, TA, pH, pCO2 , fCO2 ), nutrients, and chlorophyll observations from the full water column along the U.S. west coast. This synthesis brings together 71 different sources, including high-resolution autonomous sensors, synoptic oceanographic cruises, and shoreline samples, into a single quality-controlled product that facilitates linking nearshore, high-resolution observations to broader oceanographic conditions. MOCHA spans from the shoreline to well-beyond the continental shelf and includes over 15 million observations. The MOCHA synthesis is also available as a "daily aggregated" dataset, with all data sources averaged by day, location, and depth. | X11: =if(ISBLANK($C11), "", X$1) -> Reference | Y11: =HLOOKUP(Y$1,google_form!$1:$196,$A11,FALSE) -> Kennedy, E. G., Zulian, M., Hamilton, S. L., Hill, T. M., Delgado, M., Fish, C. R., Gaylord, B., Kroeker, K. J., Palmer, H. M., Ricart, A. M., Sanford, E., Spalding, A. K., Ward, M., Carrasco, G., Elliott, M., Grisby, G. V., Harris, E., Jahncke, J., Rocheleau, C. N., Westering, S., and Wilmot, M. I.: A high-resolution synthesis dataset for multistressor analyses along the US West Coast, Earth Syst. Sci. Data, 16, 219-243, https://doi.org/10.5194/essd-16-219-2024, 2024.
A12: 11 | B12: =HLOOKUP(B$1,google_form!$1:$216,$A12,FALSE) -> Data compilations | C12: =HLOOKUP(C$1,google_form!$1:$216,$A12,FALSE) -> ARIOS | D12: =HLOOKUP(D$1,google_form!$1:$216,$A12,FALSE) -> Padin et al. (2020) | E12: =HLOOKUP(E$1,google_form!$1:$216,$A12,FALSE) -> https://essd.copernicus.org/articles/12/2647/2020/essd-12-2647-2020-f01-web.png | F12: =if(ISBLANK($C12), "", F$1) -> fa-solid fa-globe | G12: =if(ISBLANK($C12), "", G$1) -> Spatial domains | H12: =HLOOKUP(H$1,google_form!$1:$196,$A12,FALSE) -> Coastal ocean, Surface, Water column, Regional | I12: =if(ISBLANK($C12), "", I$1) -> fa-solid fa-hourglass-start | J12: =if(ISBLANK($C12), "", J$1) -> Temporal resolution | K12: =HLOOKUP(K$1,google_form!$1:$196,$A12,FALSE) -> irregular, discrete | L12: =if(ISBLANK($C12), "", L$1) -> fa-solid fa-ruler-horizontal | M12: =if(ISBLANK($C12), "", M$1) -> Spatial resolution | N12: =HLOOKUP(N$1,google_form!$1:$196,$A12,FALSE) | O12: =if(ISBLANK($C12), "", O$1) -> fa-solid fa-calendar-days | P12: =if(ISBLANK($C12), "", P$1) -> Period | Q12: =HLOOKUP(Q$1,google_form!$1:$196,$A12,FALSE) -> 1976-2018 | R12: =HLOOKUP(R$1,google_form!$1:$196,$A12,FALSE) -> 17,653 samples from 3,343 stations measuring pH, alkalinity, and biogeochemical params off NW Iberian Peninsula (1976-2018). Data primarily from Ría de Vigo, spanning Bay of Biscay to Portuguese coast | S12: =HLOOKUP(S$1,google_form!$1:$196,$A12,FALSE) -> Padin et al. (2020) | T12: =HLOOKUP(T$1,google_form!$1:$196,$A12,FALSE) -> https://doi.org/10.5194/essd-12-2647-2020 | U12: =HLOOKUP(U$1,google_form!$1:$196,$A12,FALSE) -> https://doi.org/10.20350/digitalCSIC/12498 | V12: =if(ISBLANK($C12), "", V$1) -> Description | W12: =HLOOKUP(W$1,google_form!$1:$196,$A12,FALSE) -> A data product of 17 653 discrete samples from 3343 oceanographic stations combining measurements of pH, alkalinity and other biogeochemical parameters off the northwestern Iberian Peninsula from June 1976 to September 2018 is presented in this study. The oceanography cruises funded by 24 projects were primarily carried out in the Ría de Vigo coastal inlet but also in an area ranging from the Bay of Biscay to the Portuguese coast. The robust seasonal cycles and long-term trends were only calculated along a longitudinal section, gathering data from the coastal and oceanic zone of the Iberian upwelling system. The pH in the surface waters of these separated regions, which were highly variable due to intense photosynthesis and the remineralization of organic matter, showed an interannual acidification ranging from −0.0012 to −0.0039 yr−1 that grew towards the coastline. This result is obtained despite the buffering capacity increasing in the coastal waters further inland as shown by the increase in alkalinity by 1.1±0.7 and 2.6±1.0 µmol kg−1 yr−1 in the inner and outer Ría de Vigo respectively, driven by interannual changes in the surface salinity of 0.0193±0.0056 and 0.0426±0.016 psu yr−1 respectively. The loss of the vertical salinity gradient in the long-term trend in the inner ria was consistent with other significant biogeochemical changes such as a lower oxygen concentration and fertilization of the surface waters. These findings seem to be related to a growing footprint of sediment remineralization of organic matter in the surface layer of a more homogeneous water column. | X12: =if(ISBLANK($C12), "", X$1) -> Reference | Y12: =HLOOKUP(Y$1,google_form!$1:$196,$A12,FALSE) -> Padin, X.A., Velo, A., Pérez, F.F., 2020. ARIOS: a database for ocean acidification assessment in the Iberian upwelling system (1976–2018). Earth Syst. Sci. Data 12, 2647–2663. https://doi.org/10.5194/essd-12-2647-2020
A13: 12 | B13: =HLOOKUP(B$1,google_form!$1:$216,$A13,FALSE) -> Data compilations | C13: =HLOOKUP(C$1,google_form!$1:$216,$A13,FALSE) -> Marine Inorganic Carbonate Chemistry in the Northern Gulf of Alaska | D13: =HLOOKUP(D$1,google_form!$1:$216,$A13,FALSE) -> Monacci et al. (2024) | E13: =HLOOKUP(E$1,google_form!$1:$216,$A13,FALSE) -> https://essd.copernicus.org/articles/16/647/2024/essd-16-647-2024-avatar-web.png | F13: =if(ISBLANK($C13), "", F$1) -> fa-solid fa-globe | G13: =if(ISBLANK($C13), "", G$1) -> Spatial domains | H13: =HLOOKUP(H$1,google_form!$1:$196,$A13,FALSE) -> Coastal ocean, Water column | I13: =if(ISBLANK($C13), "", I$1) -> fa-solid fa-hourglass-start | J13: =if(ISBLANK($C13), "", J$1) -> Temporal resolution | K13: =HLOOKUP(K$1,google_form!$1:$196,$A13,FALSE) -> discrete | L13: =if(ISBLANK($C13), "", L$1) -> fa-solid fa-ruler-horizontal | M13: =if(ISBLANK($C13), "", M$1) -> Spatial resolution | N13: =HLOOKUP(N$1,google_form!$1:$196,$A13,FALSE) | O13: =if(ISBLANK($C13), "", O$1) -> fa-solid fa-calendar-days | P13: =if(ISBLANK($C13), "", P$1) -> Period | Q13: =HLOOKUP(Q$1,google_form!$1:$196,$A13,FALSE) -> 2008 - 2017 | R13: =HLOOKUP(R$1,google_form!$1:$196,$A13,FALSE) -> A synthesis of twenty cruises from 2008 to 2017 on the Gulf of Alaska (GAK) Line | S13: =HLOOKUP(S$1,google_form!$1:$196,$A13,FALSE) -> Monacci et al. (2024) | T13: =HLOOKUP(T$1,google_form!$1:$196,$A13,FALSE) -> https://doi.org/10.5194/essd-16-647-2024 | U13: =HLOOKUP(U$1,google_form!$1:$196,$A13,FALSE) -> https://www.ncei.noaa.gov/data/oceans/ncei/ocads/metadata/0277034.html | V13: =if(ISBLANK($C13), "", V$1) -> Description | W13: =HLOOKUP(W$1,google_form!$1:$196,$A13,FALSE) -> Monacci et al. (2023) compiled a data product of discrete seawater samples collected each May and September over a 10-year period from 2008 to 2017 along the long-term hydrographic line in the Gulf of Alaska (GAK Line). Samples were collected from a sampling rosette on a profiling CTD. Data variables include profiled seawater temperature, salinity, and DO. Discrete sample variables include DO (i.e., Winkler titrations), macronutrients (nitrate, nitrite, phosphate, silicic acid), DIC, and TA. All carbonate system variables were analyzed at the Ocean Acidification Research Center (OARC) at the University of Alaska Fairbanks (UAF). The repeat hydrographic cruises were funded by the Alaska Ocean Observing System (AOOS), the Exxon Valdez Oil Spill Trustee Council (EVOS), Gulf Watch Alaska, and the North Pacific Research Board (NPRB) and were mostly conducted aboard the United States Fish and Wildlife Service (USFWS) R/V Tiĝlax̂. | X13: =if(ISBLANK($C13), "", X$1) -> Reference | Y13: =HLOOKUP(Y$1,google_form!$1:$196,$A13,FALSE) -> Monacci, N. M., Cross, J. N., Evans, W., Mathis, J. T., and Wang, H.: A decade of marine inorganic carbon chemistry observations in the northern Gulf of Alaska – insights into an environment in transition, Earth Syst. Sci. Data, 16, 647–665, https://doi.org/10.5194/essd-16-647-2024, 2024.
A14: 13 | B14: =HLOOKUP(B$1,google_form!$1:$216,$A14,FALSE) -> Data compilations | C14: =HLOOKUP(C$1,google_form!$1:$216,$A14,FALSE) -> Coral Reef Carbonate Chemistry Off the Florida Keys | D14: =HLOOKUP(D$1,google_form!$1:$216,$A14,FALSE) -> Palacio-Castro et al. (2023) | E14: =HLOOKUP(E$1,google_form!$1:$216,$A14,FALSE) -> https://i.ibb.co/yc5J25Q6/gbc21508-fig-0001-m.jpg | F14: =if(ISBLANK($C14), "", F$1) -> fa-solid fa-globe | G14: =if(ISBLANK($C14), "", G$1) -> Spatial domains | H14: =HLOOKUP(H$1,google_form!$1:$196,$A14,FALSE) -> Regional, Coastal ocean, Surface | I14: =if(ISBLANK($C14), "", I$1) -> fa-solid fa-hourglass-start | J14: =if(ISBLANK($C14), "", J$1) -> Temporal resolution | K14: =HLOOKUP(K$1,google_form!$1:$196,$A14,FALSE) -> irregular, bi-monthly | L14: =if(ISBLANK($C14), "", L$1) -> fa-solid fa-ruler-horizontal | M14: =if(ISBLANK($C14), "", M$1) -> Spatial resolution | N14: =HLOOKUP(N$1,google_form!$1:$196,$A14,FALSE) | O14: =if(ISBLANK($C14), "", O$1) -> fa-solid fa-calendar-days | P14: =if(ISBLANK($C14), "", P$1) -> Period | Q14: =HLOOKUP(Q$1,google_form!$1:$196,$A14,FALSE) | R14: =HLOOKUP(R$1,google_form!$1:$196,$A14,FALSE) -> Temporal trends of DIC, TA, pCO2, pH, Ωarag, in different areas of the Florida Keys | S14: =HLOOKUP(S$1,google_form!$1:$196,$A14,FALSE) -> Palacio-Castro et al. (2023) | T14: =HLOOKUP(T$1,google_form!$1:$196,$A14,FALSE) -> https://doi.org/10.1029/2023GB007789 | U14: =HLOOKUP(U$1,google_form!$1:$196,$A14,FALSE) -> https://www.ncei.noaa.gov/access/metadata/landing-page/bin/iso?id=gov.noaa.nodc:NCRMP-CO3-Atlantic | V14: =if(ISBLANK($C14), "", V$1) -> Description | W14: =HLOOKUP(W$1,google_form!$1:$196,$A14,FALSE) -> Analysis of discrete seawater samples compiled from 38 permanent stations located along 10 inshore-offshore transects at the Florida Coral Reef. These samples were collected as part of NOAA's National Coral Reef Monitoring Program (NCRMP) and the South Florida Ecosystem Restoration Research (SFER) cruises. The time-series analysis provides insight into the dynamic carbonate conditions spanning the inshore to offshore gradients, encompassing four distinct regions of the Florida Coral Reef: Biscayne Bay, the Upper Keys, Middle Keys, and Lower Keys. | X14: =if(ISBLANK($C14), "", X$1) -> Reference | Y14: =HLOOKUP(Y$1,google_form!$1:$196,$A14,FALSE) -> Palacio-Castro, A. M., Enochs, I. C., Besemer, N., Boyd, A., Jankulak, M., Kolodziej, G., et al. (2023). Coral reef carbonate chemistry reveals interannual, seasonal, and spatial impacts on ocean acidification off Florida. Global Biogeochemical Cycles, 37, e2023GB007789. https://doi.org/10.1029/2023GB007789
A15: 14 | B15: =HLOOKUP(B$1,google_form!$1:$216,$A15,FALSE) -> Data compilations | C15: =HLOOKUP(C$1,google_form!$1:$216,$A15,FALSE) -> Salish Cruise Data Package | D15: =HLOOKUP(D$1,google_form!$1:$216,$A15,FALSE) -> Alin et al. (2025a) | E15: =HLOOKUP(E$1,google_form!$1:$216,$A15,FALSE) -> https://essd.copernicus.org/articles/16/837/2024/essd-16-837-2024-avatar-web.png | F15: =if(ISBLANK($C15), "", F$1) -> fa-solid fa-globe | G15: =if(ISBLANK($C15), "", G$1) -> Spatial domains | H15: =HLOOKUP(H$1,google_form!$1:$196,$A15,FALSE) -> Coastal ocean, Estuaries, Water column | I15: =if(ISBLANK($C15), "", I$1) -> fa-solid fa-hourglass-start | J15: =if(ISBLANK($C15), "", J$1) -> Temporal resolution | K15: =HLOOKUP(K$1,google_form!$1:$196,$A15,FALSE) -> seasonal, discrete, continuous | L15: =if(ISBLANK($C15), "", L$1) -> fa-solid fa-ruler-horizontal | M15: =if(ISBLANK($C15), "", M$1) -> Spatial resolution | N15: =HLOOKUP(N$1,google_form!$1:$196,$A15,FALSE) | O15: =if(ISBLANK($C15), "", O$1) -> fa-solid fa-calendar-days | P15: =if(ISBLANK($C15), "", P$1) -> Period | Q15: =HLOOKUP(Q$1,google_form!$1:$196,$A15,FALSE) -> 2008–2024 | R15: =HLOOKUP(R$1,google_form!$1:$196,$A15,FALSE) -> A QCed compilation of cruise datasets from 2008 to 2024 in the southern Salish Sea and northern Washington coast. | S15: =HLOOKUP(S$1,google_form!$1:$196,$A15,FALSE) -> Alin et al. (2025a) | T15: =HLOOKUP(T$1,google_form!$1:$196,$A15,FALSE) -> https://doi.org/10.5194/essd-16-837-2024 | U15: =HLOOKUP(U$1,google_form!$1:$196,$A15,FALSE) -> https://www.ncei.noaa.gov/access/ocean-carbon-acidification-data-system/oceans/SalishCruise_DataPackage.html | V15: =if(ISBLANK($C15), "", V$1) -> Description | W15: =HLOOKUP(W$1,google_form!$1:$196,$A15,FALSE) -> Alin et al. (2025a) compiled data from 61 individual cruise data sets that sampled marine waters of the southern Salish Sea and northern Washington coast (United States) from 2008 to 2024. Ongoing seasonal sampling occurred during April, July, and September for Puget Sound cruises has occurred since 2014 and most frequently during May and October for Sound-to-Sea cruises, which sample from Puget Sound through the Strait of Juan de Fuca to the northern Washington coast. The Salish cruise data package contains observations from a oceanographic water column profiles, with CTD sensor measurements of temperature, salinity, and oxygen; as well as discrete measurements of oxygen, nutrient, and inorganic carbonate content. | X15: =if(ISBLANK($C15), "", X$1) -> Reference | Y15: =HLOOKUP(Y$1,google_form!$1:$196,$A15,FALSE) -> Alin, S.R., J.A. Newton, R.A. Feely, B. Curry, D. Greeley, J. Herndon, and M. Warner (2024a). A decade-long cruise time-series (2008–2018) of physical and biogeochemical conditions in the southern Salish Sea, North America. Earth System Science Data, 16, 837–865, https://doi.org/10.5194/essd-16-837-2024
A16: 15 | B16: =HLOOKUP(B$1,google_form!$1:$216,$A16,FALSE) -> Data compilations | C16: =HLOOKUP(C$1,google_form!$1:$216,$A16,FALSE) -> Salish Cruise Multi-stressor Data Product | D16: =HLOOKUP(D$1,google_form!$1:$216,$A16,FALSE) -> Alin et al. (2025b) | E16: =HLOOKUP(E$1,google_form!$1:$216,$A16,FALSE) -> https://bg.copernicus.org/articles/21/1639/2024/bg-21-1639-2024-avatar-web.png | F16: =if(ISBLANK($C16), "", F$1) -> fa-solid fa-globe | G16: =if(ISBLANK($C16), "", G$1) -> Spatial domains | H16: =HLOOKUP(H$1,google_form!$1:$196,$A16,FALSE) -> Coastal ocean, Estuaries, Water column | I16: =if(ISBLANK($C16), "", I$1) -> fa-solid fa-hourglass-start | J16: =if(ISBLANK($C16), "", J$1) -> Temporal resolution | K16: =HLOOKUP(K$1,google_form!$1:$196,$A16,FALSE) -> seasonal, discrete, continuous | L16: =if(ISBLANK($C16), "", L$1) -> fa-solid fa-ruler-horizontal | M16: =if(ISBLANK($C16), "", M$1) -> Spatial resolution | N16: =HLOOKUP(N$1,google_form!$1:$196,$A16,FALSE) | O16: =if(ISBLANK($C16), "", O$1) -> fa-solid fa-calendar-days | P16: =if(ISBLANK($C16), "", P$1) -> Period | Q16: =HLOOKUP(Q$1,google_form!$1:$196,$A16,FALSE) -> 2008–2024 | R16: =HLOOKUP(R$1,google_form!$1:$196,$A16,FALSE) -> A multi-stressor (ocean acidification, hypoxia, marine heatwaves) data product based on cruises from 2008 to 2024 in the southern Salish Sea and northern Washington coast (USA). | S16: =HLOOKUP(S$1,google_form!$1:$196,$A16,FALSE) -> Alin et al. (2025b) | T16: =HLOOKUP(T$1,google_form!$1:$196,$A16,FALSE) -> https://doi.org/10.5194/bg-21-1639-2024 | U16: =HLOOKUP(U$1,google_form!$1:$196,$A16,FALSE) -> https://www.ncei.noaa.gov/access/ocean-carbon-acidification-data-system/oceans/SalishCruises_DataProduct.html | V16: =if(ISBLANK($C16), "", V$1) -> Description | W16: =HLOOKUP(W$1,google_form!$1:$196,$A16,FALSE) -> Alin et al. (2025b) provides a data product including all finalized records from the Salish cruise data package that had a complete suite of measurements for CTD temperature, salinity, and oxygen, as well as discrete measurements of oxygen, nutrients, dissolved inorganic carbon, and total akalinity. This product also provides the most commonly used calculated carbonate system variables--pH (on the total scale), carbon dioxide fugacity (fCO2) and partial , Ωarag, and Ωcalc--to facilitate their use by a broader group of end users. | X16: =if(ISBLANK($C16), "", X$1) -> Reference | Y16: =HLOOKUP(Y$1,google_form!$1:$196,$A16,FALSE) -> Alin, S.R., J.A. Newton, R.A. Feely, S. Siedlecki, and D. Greeley (2024b). Seasonality and response of ocean acidification and hypoxia to major environmental anomalies in the southern Salish Sea, North America (2014–2018). Biogeosciences, 21, 1639–1673, https://doi.org/10.5194/bg-21-1639-2024
A17: 16 | B17: =HLOOKUP(B$1,google_form!$1:$216,$A17,FALSE) -> Data compilations | C17: =HLOOKUP(C$1,google_form!$1:$216,$A17,FALSE) -> Line P Marine Carbonate Chemistry Compilation | D17: =HLOOKUP(D$1,google_form!$1:$216,$A17,FALSE) -> Franco et al., (2021) | E17: =HLOOKUP(E$1,google_form!$1:$216,$A17,FALSE) -> https://i.ibb.co/4wb5JLp1/fig1-map-francoetal2021.png | F17: =if(ISBLANK($C17), "", F$1) -> fa-solid fa-globe | G17: =if(ISBLANK($C17), "", G$1) -> Spatial domains | H17: =HLOOKUP(H$1,google_form!$1:$196,$A17,FALSE) -> Open ocean, Water column, Regional | I17: =if(ISBLANK($C17), "", I$1) -> fa-solid fa-hourglass-start | J17: =if(ISBLANK($C17), "", J$1) -> Temporal resolution | K17: =HLOOKUP(K$1,google_form!$1:$196,$A17,FALSE) -> irregular, sub-annual, discrete | L17: =if(ISBLANK($C17), "", L$1) -> fa-solid fa-ruler-horizontal | M17: =if(ISBLANK($C17), "", M$1) -> Spatial resolution | N17: =HLOOKUP(N$1,google_form!$1:$196,$A17,FALSE) | O17: =if(ISBLANK($C17), "", O$1) -> fa-solid fa-calendar-days | P17: =if(ISBLANK($C17), "", P$1) -> Period | Q17: =HLOOKUP(Q$1,google_form!$1:$196,$A17,FALSE) -> 1990 - 2019 | R17: =HLOOKUP(R$1,google_form!$1:$196,$A17,FALSE) -> A compilation of fifty-five Line P cruises containing discrete DIC and TA profiles at five stations in the Northeast Pacific Ocean. Sampled approximately three times per year from 1990 to 2019 | S17: =HLOOKUP(S$1,google_form!$1:$196,$A17,FALSE) -> Franco et al., (2021) | T17: =HLOOKUP(T$1,google_form!$1:$196,$A17,FALSE) -> https://doi.org/10.1029/2020GB006829 | U17: =HLOOKUP(U$1,google_form!$1:$196,$A17,FALSE) -> https://www.ncei.noaa.gov/data/oceans/ncei/ocads/metadata/0234342.html | V17: =if(ISBLANK($C17), "", V$1) -> Description | W17: =HLOOKUP(W$1,google_form!$1:$196,$A17,FALSE) -> This dataset contains marine carbonate system measurements collected during 55 Line P cruises from 1990 to 2019 in the subarctic Northeast Pacific. The dataset contains quality-controlled, discrete profiles of dissolved inorganic carbon (DIC), total alkalinity (TA), temperature, salinity, dissolved oxygen and nutrients. From a total of 27 hydrographic time-series stations, only the five major stations where DIC and TA are routinely sampled were included in this compilation. Cruises were conducted approximately three times per year, typically in February, May/June and August/September. Each vertical profile was individually inspected and contrasted with the whole pool of data relative to salinity, density, and oxygen to detect and flag poor quality data following the World Ocean Circulation Experiment (WOCE) quality control convention. The recommended cruise-specific adjustments from the Pacific Ocean Interior Carbon (PACIFICA) data synthesis were applied. The Line P carbonate chemistry timeseries is maintained by Fisheries and Oceans Canada and continues to the present day. Data are available and continuously updated in the Line P repository, which can be publicly accessed after generating an account at https://waterproperties.ca. | X17: =if(ISBLANK($C17), "", X$1) -> Reference | Y17: =HLOOKUP(Y$1,google_form!$1:$196,$A17,FALSE) -> Franco, A. C., Ianson, D., Ross, T., Hamme, R. C., Monahan, A. H., Christian, J. R., Davelaar, M., Johnson, W. K., Miller, L. A., Robert, M., and Tortell, P. D. 2021. Anthropogenic and climatic contributions to observed carbon system trends in the northeast Pacific. Global Biogeochemical Cycles, 35(7). https://doi.org/10.1029/2020GB006829
A18: 17 | B18: =HLOOKUP(B$1,google_form!$1:$216,$A18,FALSE) -> Data compilations | C18: =HLOOKUP(C$1,google_form!$1:$216,$A18,FALSE) -> Anthropogenic Carbon in the Arctic Ocean | D18: =HLOOKUP(D$1,google_form!$1:$216,$A18,FALSE) -> Terhaar et al. (2020) | E18: =HLOOKUP(E$1,google_form!$1:$216,$A18,FALSE) -> https://www.seanoe.org/data/00927/103920/illustration.gif | F18: =if(ISBLANK($C18), "", F$1) -> fa-solid fa-globe | G18: =if(ISBLANK($C18), "", G$1) -> Spatial domains | H18: =HLOOKUP(H$1,google_form!$1:$196,$A18,FALSE) -> Open ocean | I18: =if(ISBLANK($C18), "", I$1) -> fa-solid fa-hourglass-start | J18: =if(ISBLANK($C18), "", J$1) -> Temporal resolution | K18: =HLOOKUP(K$1,google_form!$1:$196,$A18,FALSE) -> climatology | L18: =if(ISBLANK($C18), "", L$1) -> fa-solid fa-ruler-horizontal | M18: =if(ISBLANK($C18), "", M$1) -> Spatial resolution | N18: =HLOOKUP(N$1,google_form!$1:$196,$A18,FALSE) | O18: =if(ISBLANK($C18), "", O$1) -> fa-solid fa-calendar-days | P18: =if(ISBLANK($C18), "", P$1) -> Period | Q18: =HLOOKUP(Q$1,google_form!$1:$196,$A18,FALSE) -> 2005 | R18: =HLOOKUP(R$1,google_form!$1:$196,$A18,FALSE) -> Observation-based estimates of anthropogenic carbon in the Arctic Ocean | S18: =HLOOKUP(S$1,google_form!$1:$196,$A18,FALSE) -> Terhaar et al. (2020) | T18: =HLOOKUP(T$1,google_form!$1:$196,$A18,FALSE) -> https://doi.org/10.1029/2020jc016124 | U18: =HLOOKUP(U$1,google_form!$1:$196,$A18,FALSE) -> https://www.seanoe.org/data/00927/103920/ | V18: =if(ISBLANK($C18), "", V$1) -> Description | W18: =HLOOKUP(W$1,google_form!$1:$196,$A18,FALSE) -> This dataset includes anthropogenic carbon estimates in the Arctic Ocean based on measurements of transient tracers, such as CFC-12 and SF6 (Terhaar et al., 2020; Tanhua et al., 2009). Using the transient time distribution (TTD) method, anthropogenic carbon estimates were estimated at measurement locations across all basins of the Arctic Ocean between 1983 and 2005. In addition to these estimates, adjusted estimates of anthropogenic carbon at these locations are provided to account for differences in the saturation of transient tracers and anthropogenic carbon in Arctic Ocean surface waters that caused anthropogenic carbon estimates to be biased low (Terhaar et al., 2020). It is recommended to use the adjusted estimates. This dataset can be accessed at https://doi.org/10.17882/103920 (Terhaar et al., 2024). | X18: =if(ISBLANK($C18), "", X$1) -> Reference | Y18: =HLOOKUP(Y$1,google_form!$1:$196,$A18,FALSE) -> Terhaar, J., Tanhua, T., Stöven, T., Orr, J. C., and Bopp, L.: Evaluation of data‐based estimates of anthropogenic carbon in the Arctic Ocean, Journal of Geophysical Research: Oceans, 125(6), https://doi.org/10.1029/2020jc016124, 2020.
A19: 18 | B19: =HLOOKUP(B$1,google_form!$1:$216,$A19,FALSE) -> Time series | C19: =HLOOKUP(C$1,google_form!$1:$216,$A19,FALSE) -> BATS | D19: =HLOOKUP(D$1,google_form!$1:$216,$A19,FALSE) -> Bates and Johnson (2023) | E19: =HLOOKUP(E$1,google_form!$1:$216,$A19,FALSE) -> https://www.frontiersin.org/files/Articles/1289931/fmars-10-1289931-HTML-r1/image_m/fmars-10-1289931-g001.jpg | F19: =if(ISBLANK($C19), "", F$1) -> fa-solid fa-globe | G19: =if(ISBLANK($C19), "", G$1) -> Spatial domains | H19: =HLOOKUP(H$1,google_form!$1:$196,$A19,FALSE) -> Open ocean | I19: =if(ISBLANK($C19), "", I$1) -> fa-solid fa-hourglass-start | J19: =if(ISBLANK($C19), "", J$1) -> Temporal resolution | K19: =HLOOKUP(K$1,google_form!$1:$196,$A19,FALSE) -> monthly | L19: =if(ISBLANK($C19), "", L$1) -> fa-solid fa-ruler-horizontal | M19: =if(ISBLANK($C19), "", M$1) -> Spatial resolution | N19: =HLOOKUP(N$1,google_form!$1:$196,$A19,FALSE) | O19: =if(ISBLANK($C19), "", O$1) -> fa-solid fa-calendar-days | P19: =if(ISBLANK($C19), "", P$1) -> Period | Q19: =HLOOKUP(Q$1,google_form!$1:$196,$A19,FALSE) -> 1988-2025 | R19: =HLOOKUP(R$1,google_form!$1:$196,$A19,FALSE) -> Forty years of ocean acidification observations (1983-2023) in the Sargasso Sea at the Bermuda Atlantic Time-series Study (BATS) site. | S19: =HLOOKUP(S$1,google_form!$1:$196,$A19,FALSE) -> Bates and Johnson (2023) | T19: =HLOOKUP(T$1,google_form!$1:$196,$A19,FALSE) -> https://doi.org/10.3389/fmars.2023.1289931 | U19: =HLOOKUP(U$1,google_form!$1:$196,$A19,FALSE) -> https://www.bco-dmo.org/project/2124 | V19: =if(ISBLANK($C19), "", V$1) -> Description | W19: =HLOOKUP(W$1,google_form!$1:$196,$A19,FALSE) -> Ocean physical and biogeochemical conditions are rapidly changing over time. Forty years of observations from 1983 to 2023 collected at the Bermuda Atlantic Time-series Study (BATS) site near Bermuda in the North Atlantic Ocean shows continuing trends of surface warming, increase in salinity, loss of dissolved oxygen (DO), increase in carbon dioxide (CO2), and ocean acidification (OA) effects. Over this period, the ocean has warmed by about +1°C, increased in salinity by +0.136, and lost DO by 12.5 µmol kg−1 or ~6%. Since the 1980s, ocean dissolved inorganic carbon (DIC), total alkalinity (TA), a tracer of anthropogenic CO2 (CTrOCA), and fugacities/partial pressures of CO2 (i.e., fCO2 and pCO2) have continued to increase substantially, with no evidence of a reduction in the rates of change over time. Contemporaneously, ocean pH has decreased by ~0.1 pH units [with ocean acidity (i.e., H+) increasing by >30%], and the saturation states of calcium carbonate minerals (Ωcalcite and Ωaragonite) have decreased. These OA indicators show that the chemical conditions for calcification have become less favorable over the past 40 years. Updating of data and trends at the BATS site show how ocean chemistry of the 2020s is now outside the range observed in the 1980s, and how essential these data are for predicting the response of ocean chemistry and marine ecosystems to future shifting earth and ocean conditions. | X19: =if(ISBLANK($C19), "", X$1) -> Reference | Y19: =HLOOKUP(Y$1,google_form!$1:$196,$A19,FALSE) -> Bates, N., Johnson, R. J., Lomas, M. W., Smith, D., Lethaby, P. J., Bakker, R., Davey, E., Derbyshire, L., Enright, M., Garley, R., Hayden, M. G., Lomas, D., May, R., Medley, C., Stuart, E., Chambers, E. (2025) Discrete bottle samples collected at the Bermuda Atlantic Time-series Study (BATS) site in the Sargasso Sea from October 1988 through December 2024. Biological and Chemical Oceanography Data Management Office (BCO-DMO). (Version 8) Version Date 2025-06-27 [if applicable, indicate subset used]. doi:10.26008/1912/bco-dmo.3782.8 [access date];</br></br>Bates, N., and Johnson, R.J., 2023. Forty years of ocean acidification observations (1983-2023) in the Sargasso Sea at the Bermuda Atlantic Time-series Study (BATS) site. Frontiers in Marine Science, 10, https://doi.org/10.3389/fmars.2023.1289931.
A20: 19 | B20: =HLOOKUP(B$1,google_form!$1:$216,$A20,FALSE) -> Time series | C20: =HLOOKUP(C$1,google_form!$1:$216,$A20,FALSE) -> HOT | D20: =HLOOKUP(D$1,google_form!$1:$216,$A20,FALSE) -> Dore et al. (2009) | E20: =HLOOKUP(E$1,google_form!$1:$216,$A20,FALSE) -> https://i.ibb.co/B2vPqjyw/HOTlogo.jpg | F20: =if(ISBLANK($C20), "", F$1) -> fa-solid fa-globe | G20: =if(ISBLANK($C20), "", G$1) -> Spatial domains | H20: =HLOOKUP(H$1,google_form!$1:$196,$A20,FALSE) -> Open ocean, Water column | I20: =if(ISBLANK($C20), "", I$1) -> fa-solid fa-hourglass-start | J20: =if(ISBLANK($C20), "", J$1) -> Temporal resolution | K20: =HLOOKUP(K$1,google_form!$1:$196,$A20,FALSE) -> monthly | L20: =if(ISBLANK($C20), "", L$1) -> fa-solid fa-ruler-horizontal | M20: =if(ISBLANK($C20), "", M$1) -> Spatial resolution | N20: =HLOOKUP(N$1,google_form!$1:$196,$A20,FALSE) | O20: =if(ISBLANK($C20), "", O$1) -> fa-solid fa-calendar-days | P20: =if(ISBLANK($C20), "", P$1) -> Period | Q20: =HLOOKUP(Q$1,google_form!$1:$196,$A20,FALSE) -> 1988-2025 | R20: =HLOOKUP(R$1,google_form!$1:$196,$A20,FALSE) -> 35+ years of inorganic carbon dynamics in the open waters of the central North Pacific | S20: =HLOOKUP(S$1,google_form!$1:$196,$A20,FALSE) -> Dore et al. (2009) | T20: =HLOOKUP(T$1,google_form!$1:$196,$A20,FALSE) -> https://doi.org/10.1073/pnas.0906044106 | U20: =HLOOKUP(U$1,google_form!$1:$196,$A20,FALSE) -> https://doi.org/10.1575/1912/bco-dmo.3773.1 | V20: =if(ISBLANK($C20), "", V$1) -> Description | W20: =HLOOKUP(W$1,google_form!$1:$196,$A20,FALSE) -> The Hawaii Ocean Time-series (HOT) CO2 measurement program documents 35+ years of inorganic carbon dynamics in the open waters of the central North Pacific. Since October 1988, full ocean depth profiles of DIC and TA have been analyzed, and direct measurements of pH have been made over most of this longest-running Pacific Ocean time-series study. The program is based on shipboard observations and experiments conducted on ~10 expeditions per annum to Station ALOHA (22.75°N, 158°W). | X20: =if(ISBLANK($C20), "", X$1) -> Reference | Y20: =HLOOKUP(Y$1,google_form!$1:$196,$A20,FALSE) -> Dore, J. E., Lukas, R., Sadler, D. W., Church, M. J., and Karl, D. M.: Physical and biogeochemical modulation of ocean acidification in the central North Pacific, Proc. Natl. Acad. Sci., 106, 12235-12240, https://doi.org/10.1073/pnas.0906044106, 2009.
A21: 20 | B21: =HLOOKUP(B$1,google_form!$1:$216,$A21,FALSE) -> Time series | C21: =HLOOKUP(C$1,google_form!$1:$216,$A21,FALSE) -> ESTOC | D21: =HLOOKUP(D$1,google_form!$1:$216,$A21,FALSE) -> González-Dávila and Santana-Casiano (2023) | E21: =HLOOKUP(E$1,google_form!$1:$216,$A21,FALSE) -> https://www.frontiersin.org/files/Articles/1236214/fmars-10-1236214-HTML-r1/image_m/fmars-10-1236214-g001.jpg | F21: =if(ISBLANK($C21), "", F$1) -> fa-solid fa-globe | G21: =if(ISBLANK($C21), "", G$1) -> Spatial domains | H21: =HLOOKUP(H$1,google_form!$1:$196,$A21,FALSE) -> Open ocean | I21: =if(ISBLANK($C21), "", I$1) -> fa-solid fa-hourglass-start | J21: =if(ISBLANK($C21), "", J$1) -> Temporal resolution | K21: =HLOOKUP(K$1,google_form!$1:$196,$A21,FALSE) -> irregular | L21: =if(ISBLANK($C21), "", L$1) -> fa-solid fa-ruler-horizontal | M21: =if(ISBLANK($C21), "", M$1) -> Spatial resolution | N21: =HLOOKUP(N$1,google_form!$1:$196,$A21,FALSE) | O21: =if(ISBLANK($C21), "", O$1) -> fa-solid fa-calendar-days | P21: =if(ISBLANK($C21), "", P$1) -> Period | Q21: =HLOOKUP(Q$1,google_form!$1:$196,$A21,FALSE) | R21: =HLOOKUP(R$1,google_form!$1:$196,$A21,FALSE) -> The longest continuous monthly record of warming, rising carbon dioxide levels, and OA in the eastern North Atlantic | S21: =HLOOKUP(S$1,google_form!$1:$196,$A21,FALSE) -> González-Dávila and Santana-Casiano (2023) | T21: =HLOOKUP(T$1,google_form!$1:$196,$A21,FALSE) -> https://doi.org/10.3389/fmars.2023.1236214 | U21: =HLOOKUP(U$1,google_form!$1:$196,$A21,FALSE) -> https://doi.org/10.1594/PANGAEA.959856 | V21: =if(ISBLANK($C21), "", V$1) -> Description | W21: =HLOOKUP(W$1,google_form!$1:$196,$A21,FALSE) -> The European Station for Time-series in the Ocean (ESTOC) began carbon dioxide monitoring in October 1995, providing a 30-year record on DIC, TA, and pH. This dataset represents the longest continuous monthly record of warming, rising carbon dioxide levels, and acidification in the eastern North Atlantic (González-Dávila and Santana-Casiano, 2023). ESTOC is located 100 km north of the Canary Islands archipelago (https://plocan.eu/en/installations/ocean-observatory). The program includes a ship-based observation system, measuring physical, chemical, and biological variables throughout the 3,670-meter water column. It also features a moored platform for surface meteorological and oceanic observations as well as subsurface measurements, maintained by the Canary Island Oceanic Platform (PLOCAN, https://plocan.eu/en) and the University of Las Palmas de Gran Canaria (https://iocag.ulpgc.es/research/research-units/quima). Carbonate system measurements include full-depth bottle sampling for photometric pH, TA, and DIC, conducted monthly from 1995 to 2008, every two months until 2018, and semiannually in recent years due to limited ship time, timed to coincide with moored structure maintenance. ESTOC is also visited every two weeks by a volunteer observing ship, ES-SOOP-CanOA (https://meta.icos-cp.eu/resources/stations/OS_687B), part of the European Research Infrastructure ICOS (https://www.icos-cp.eu/observations/ocean/stations), which provides real-time surface data on carbon dioxide fluxes and OA. The program also includes the CO2-ESTOC oceanographic buoy (https://meta.icos-cp.eu/labeling/). | X21: =if(ISBLANK($C21), "", X$1) -> Reference | Y21: =HLOOKUP(Y$1,google_form!$1:$196,$A21,FALSE) -> González-Dávila, M. and Santana-Casiano J. M.: Long-term trends of pH and inorganic carbon in the Eastern North Atlantic: the ESTOC site, Front. Mar. Sci., 10, 1236214, https://doi.org/10.3389/fmars.2023.1236214, 2023.
... A122: 121 | B122: =HLOOKUP(B$1,google_form!$1:$216,$A122,FALSE) | C122: =HLOOKUP(C$1,google_form!$1:$216,$A122,FALSE) | D122: =HLOOKUP(D$1,google_form!$1:$216,$A122,FALSE) | E122: =HLOOKUP(E$1,google_form!$1:$216,$A122,FALSE) | F122: =if(ISBLANK($C122), "", F$1) | G122: =if(ISBLANK($C122), "", G$1) | H122: =HLOOKUP(H$1,google_form!$1:$196,$A122,FALSE) | I122: =if(ISBLANK($C122), "", I$1) | J122: =if(ISBLANK($C122), "", J$1) | K122: =HLOOKUP(K$1,google_form!$1:$196,$A122,FALSE) | L122: =if(ISBLANK($C122), "", L$1) | M122: =if(ISBLANK($C122), "", M$1) | N122: =HLOOKUP(N$1,google_form!$1:$196,$A122,FALSE) | O122: =if(ISBLANK($C122), "", O$1) | P122: =if(ISBLANK($C122), "", P$1) | Q122: =HLOOKUP(Q$1,google_form!$1:$196,$A122,FALSE) | R122: =HLOOKUP(R$1,google_form!$1:$196,$A122,FALSE) | S122: =HLOOKUP(S$1,google_form!$1:$196,$A122,FALSE) | T122: =HLOOKUP(T$1,google_form!$1:$196,$A122,FALSE) | U122: =HLOOKUP(U$1,google_form!$1:$196,$A122,FALSE) | V122: =if(ISBLANK($C122), "", V$1) | W122: =HLOOKUP(W$1,google_form!$1:$196,$A122,FALSE) | X122: =if(ISBLANK($C122), "", X$1) | Y122: =HLOOKUP(Y$1,google_form!$1:$196,$A122,FALSE)
